Workbook

Sheet Industrial
B2: INDUSTRIAL - SUMMARY INCOME STATEMENT
B4: Net Rentable Area | D4: 156160
B5: Period Ending | D5: 2019
B6: REVENUE
B7: Rental Revenue | C7: PSF | D7: Amount
B8: Potential Base Rent | C8: =+D8/$D$4 -> 4.449997 | D8: =OpSt!I6 -> 694911.53 | E8: Sum of all contract rent plus vacant space at market rent; concessed space at contract rate
B9: Actual Vacancy | C9: =+D9/$D$4 -> 0 | D9: =OpSt!I7 -> 0 | E9: Vacant space at market rent
B10: Actual Credit Loss | C10: =+D10/$D$4 -> 0 | D10: =OpSt!I8 -> 0 | E10: Loss due to tenants' nonpayment of rental obligations
B11: Concessions | C11: =+D11/$D$4 -> 0 | D11: =OpSt!I9 -> 0 | E11: Concessed space (e.g. free rent) at contract rate
B12: Total Rental Revenue | C12: =+D12/$D$4 -> 4.449997 | D12: =OpSt!I10 -> 694911.53 | E12: Actual rental Revenue in period
D13: =OpSt!I11 -> 0
B14: Other Income | D14: =OpSt!I12 -> 0
B15: CAM Reimbursement | C15: =+D15/$D$4 -> 0 | D15: =OpSt!I13 -> 0 | E15: Actual tenant reimbursement of common area maintenance (security, repairs and maintenance, landscaping, etc)
B16: Utility Reimbursement | C16: =+D16/$D$4 -> 0.0096878842 | D16: =OpSt!I14 -> 1512.86 | E16: Actual tenant reimbursement of utility expenses
B17: Real Estate Tax Reimbursement | C17: =+D17/$D$4 -> 0.79059919 | D17: =OpSt!I15 -> 123459.97 | E17: Actual tenant reimbursement of real estate taxes
B18: Other Income | C18: =+D18/$D$4 -> 0.46652856 | D18: =OpSt!I16 -> 72853.1 | E18: Actual other income
B19: Total Other Income | C19: =+D19/$D$4 -> 1.2668156 | D19: =OpSt!I17 -> 197825.93 | E19: Actual other Revenue
D20: =OpSt!I18 -> 0
B21: Effective Gross Revenue | D21: =OpSt!I19 -> 0
B22: Gross Revenue | C22: =+D22/$D$4 -> 5.7168126 | D22: =OpSt!I20 -> 892737.46 | E22: Sum of other income and rental revenue
B23: General Vacancy and Credit Loss | C23: =+D23/$D$4 -> 0 | D23: =OpSt!I21 -> 0 | E23: Additional vacancy taken on gross Revenue to account for unforeseen vacancy or credit loss; used in forecasted periods
B24: Total Effective Gross Revenue | C24: =+D24/$D$4 -> 5.7168126 | D24: =OpSt!I22 -> 892737.46 | E24: Gross revenue after adjusting for general vacancy and credit loss; commonly referred to as EGR
B25: OPERATING EXPENSES | D25: =OpSt!I23 -> 0
B26: Reimbursable Operating Expenses | D26: =OpSt!I24 -> 0 | E26: Operating expenses incurred by landlord that tenants have agreed to reimburse
B27: Variable Operating Expenses | D27: =OpSt!I25 -> 0 | E27: Expenses that fluctuate based on occupancy
B28: Repairs and Maintenance | C28: =+D28/$D$4 -> 0.21162897 | D28: =OpSt!I26 -> 33047.98 | E28: Expenses related to maintaining the general condition of the common areas
B29: Security | C29: =+D29/$D$4 -> 0 | D29: =OpSt!I27 -> 0 | E29: Expenses related to securing the premises
B30: Landscaping | C30: =+D30/$D$4 -> 0.080530738 | D30: =OpSt!I28 -> 12575.68 | E30: Expenses related to maintaining the landscaping in the common areas
B31: Property Management | C31: =+D31/$D$4 -> 0.04449968 | D31: =OpSt!I29 -> 6949.07 | E31: Fee paid to professional property management
B32: Utilities | C32: =+D32/$D$4 -> 0.048220415 | D32: =OpSt!I30 -> 7530.1 | E32: Electricity, gas, water, sewer, internet, and other utilities related to the common areas
B33: Other Variable Expenses | C33: =+D33/$D$4 -> 0.13726908 | D33: =OpSt!I31 -> 21435.94 | E33: Other variable expenses that are reimbursable
B34: Total Variable Expenses | C34: =+D34/$D$4 -> 0.52214889 | D34: =OpSt!I32 -> 81538.77
B35: Fixed Expenses | D35: =OpSt!I33 -> 0 | E35: Expense that are fixed regardless of occupancy
B36: Real Estate Taxes | C36: =+D36/$D$4 -> 0.75439857 | D36: =OpSt!I34 -> 117806.88 | E36: Real estate taxes levied by the local government
B37: Insurance | C37: =+D37/$D$4 -> 0.053944736 | D37: =OpSt!I35 -> 8424.01 | E37: Property and casualty insurance
B38: Total Fixed Operating Expenses | C38: =+D38/$D$4 -> 0.8083433 | D38: =OpSt!I36 -> 126230.89
D39: =OpSt!I37 -> 0
B40: Total Reimbursable OpEx | C40: =+D40/$D$4 -> 1.3304922 | D40: =OpSt!I38 -> 207769.66 | E40: Total operating expenses that are reimbursable
D41: =OpSt!I39 -> 0
B42: Non-Reimbursable Operating Expenses | D42: =OpSt!I40 -> 0 | E42: Operating expenses incurred by landlord that tenants are not obligated to reimburse
B43: Variable Operating Expenses | D43: =OpSt!I41 -> 0 | E43: Expenses that fluctuate based on occupancy
B44: Repairs and Maintenance | C44: =+D44/$D$4 -> 0 | D44: =OpSt!I42 -> 0 | E44: Expenses related to maintaining the general condition of the common areas
B45: Security | C45: =+D45/$D$4 -> 0 | D45: =OpSt!I43 -> 0 | E45: Expenses related to securing the premises
B46: Landscaping | C46: =+D46/$D$4 -> 0 | D46: =OpSt!I44 -> 0 | E46: Expenses related to maintaining the landscaping in the common areas
B47: Utilities | C47: =+D47/$D$4 -> 0 | D47: =OpSt!I45 -> 0 | E47: Electricity, gas, water, sewer, internet, and other utilities related to the common areas
B48: Other Variable Expenses | C48: =+D48/$D$4 -> 0 | D48: =OpSt!I46 -> 0 | E48: Other variable expenses that are not reimbursable
B49: Total Variable Expenses | C49: =+D49/$D$4 -> 0 | D49: =OpSt!I47 -> 0
B50: Fixed Expenses | D50: =OpSt!I48 -> 0 | E50: Expense that are fixed regardless of occupancy
B51: Real Estate Taxes | C51: =+D51/$D$4 -> 0 | D51: =OpSt!I49 -> 0 | E51: Real estate taxes levied by the local government
B52: Insurance | C52: =+D52/$D$4 -> 0 | D52: =OpSt!I50 -> 0 | E52: Property and casualty insurance
B53: Total Fixed Operating Expenses | C53: =+D53/$D$4 -> 0 | D53: =OpSt!I51 -> 0
D54: =OpSt!I52 -> 0
B55: Total Non-Reimbursable OpEx | C55: =+D55/$D$4 -> 0 | D55: =OpSt!I53 -> 0 | E55: Total operating expenses that are not reimbursable
D56: =OpSt!I54 -> 0
B57: Total Operating Expenses | C57: =+D57/$D$4 -> 1.3304922 | D57: =OpSt!I55 -> 207769.66 | E57: Sum of reimbursable and non-reimbursable operating expenses; commonly referred to as OpEx
D58: =OpSt!I56 -> 0
B59: NET OPERATING INCOME | C59: =+D59/$D$4 -> 4.3863204 | D59: =OpSt!I57 -> 684967.8 | E59: Effective gross income minus total operating expenses; commonly referred to as NOI
B60: CAPITAL EXPENDITURES
B61: Leasing Commissions | C61: =+D61/$D$4 -> 0.54782928 | D61: =OpSt!I59 -> 85549.02 | E61: Commissions paid to leasing brokers
B62: Tenant Improvements | C62: =+D62/$D$4 -> 0 | D62: =OpSt!I60 -> 0 | E62: Allowances offered to tenants upon signing a new lease or lease renewal; used to improve the tenant's physical space
B63: Capital Improvements | C63: =+D63/$D$4 -> 0.062246926 | D63: =OpSt!I61 -> 9720.48 | E63: Expenditures with a depreciable life greater than one year (e.g. roof repair, structural repairs, etc)
B64: Capital Reserve | C64: =+D64/$D$4 -> 0 | D64: =OpSt!I62 -> 0 | E64: Amount set aside for future capital improvements and/or leasing costs
B65: Total Capital Expenditures | C65: =+D65/$D$4 -> 0.6100762 | D65: =OpSt!I63 -> 95269.5
D66: =OpSt!I64 -> 0
B67: CASH FLOW FROM OPERATIONS | D67: =OpSt!I65 -> 589698.3 | E67: Net operating income minus total capital expenditures; commonly referred to as CFO
D68: =OpSt!I66 -> 0
B69: Debt Service | D69: =OpSt!I67 -> 120000 | E69: Payment to lender(s); payment is principal + interest unless loan is interest-only; commonly referred to as DS
D70: =OpSt!I68 -> 0
B71: CASH FLOW AFTER FINANCING | D71: =OpSt!I69 -> 469698.3 | E71: Cash flow from operations minus debt service and any ground lease payments, if applicable; commonly referred to as CFAF

Sheet OpSt
A1: Gully Logistics Center
A2: Annual Statement
A3: Period = Jan 2017-Dec 2019
A4: Property size: 156,160 SF
B5: EOY | C5: EOY | D5: EOY | E5: Label | G5: Label | H5: Rental Revenue | I5: Amount | J5: Error Check
B6: Dec 2017 | C6: Dec 2018 | D6: Dec 2019 | G6: RENT | H6: Potential Base Rent | I6: =SUMIF($E$7:$E$79,G6,$D$7:$D$79) -> 694911.53
A7: Base Rent | B7: 409632.48 | C7: 528775.31 | D7: 694911.53 | E7: RENT | G7: VAC | H7: Actual Vacancy | I7: =SUMIF($E$7:$E$79,G7,$D$7:$D$79) -> 0
A8: Rent Concessions | B8: 0 | C8: -27929.37 | D8: 0 | E8: CONC | G8: CREDIT | H8: Actual Credit Loss | I8: =SUMIF($E$7:$E$79,G8,$D$7:$D$79) -> 0
A9: Base Income | B9: 409632.48 | C9: 500845.94 | D9: 694911.53 | G9: CONC | H9: Concessions | I9: =SUMIF($E$7:$E$79,G9,$D$7:$D$79) -> 0
A10: Recoveries-Operating Expense | B10: 66729.86 | C10: 76534.69 | D10: 72853.1 | E10: OI | H10: Total Rental Revenue | I10: =SUM(I6:I9) -> 694911.53
A11: Recoveries-Real Estate Tax | B11: 0 | C11: 15066.4 | D11: 123459.97 | E11: RET
A12: Recoveries-Insurance | B12: 57167.15 | C12: 82929.42 | D12: 0 | E12: I | H12: Other Income
A13: Recoveries-Utilities | B13: 0 | C13: 0 | D13: 1512.86 | E13: U | G13: CAM | H13: CAM Reimbursement | I13: =SUMIF($E$7:$E$79,G13,$D$7:$D$79) -> 0
A14: Recovery Income | B14: 123897.01 | C14: 174530.51 | D14: 197825.93 | G14: U | H14: Utility Reimbursement | I14: =SUMIF($E$7:$E$79,G14,$D$7:$D$79) -> 1512.86
A15: Revenues | B15: 533529.49 | C15: 675376.45 | D15: 892737.46 | G15: RET | H15: Real Estate Tax Reimbursement | I15: =SUMIF($E$7:$E$79,G15,$D$7:$D$79) -> 123459.97
G16: OI | H16: Other Income | I16: =SUMIF($E$7:$E$79,G16,$D$7:$D$79) -> 72853.1
A17: Cleaning-Window Cleaning | B17: 320 | C17: 160 | D17: 320 | H17: Total Other Income | I17: =SUM(I13:I16) -> 197825.93
A18: Cleaning Expenses | B18: 320 | C18: 160 | D18: 320 | E18: RM
A19: R&M-Staff Payroll | B19: 6488.1 | C19: 4818.88 | D19: 2698 | E19: RM | H19: Effective Gross Revenue
A20: R&M-HVAC-Contract | B20: 0 | C20: 3438 | D20: 2777 | E20: RM | H20: Gross Revenue | I20: =+I17+I10 -> 892737.46
A21: R&M-HVAC-Maintenance&Repairs | B21: 3677.63 | C21: 1689.5 | D21: 7187.87 | E21: RM | H21: General Vacancy and Credit Loss | I21: 0
A22: R&M-Plumbing-Supplies | B22: 0 | C22: 0 | D22: 60.1 | E22: RM | H22: Total Effective Gross Revenue | I22: =+I20+I21 -> 892737.46 | J22: =D15 -> 892737.46
A23: R&M-Plumbing-Maint & Repairs | B23: 1746 | C23: 1490 | D23: 0 | E23: RM | H23: OPERATING EXPENSES
A24: R&M-Electrical-Maint & Repairs | B24: 1876.62 | C24: 1380.84 | D24: 961.34 | E24: RM | H24: Reimbursable Operating Expenses
A25: R&M-Genl Bldg-Tools & Supplies | B25: 0 | C25: 0 | D25: 41.49 | E25: RM | H25: Variable Operating Expenses
A26: R&M-Genl Bldg-Hardware/Keys | B26: 0 | C26: 0 | D26: 483.5 | E26: RM | G26: RM | H26: Repairs and Maintenance | I26: =SUMIF($E$7:$E$79,G26,$D$7:$D$79) -> 33047.98
A27: R&M-Genl Bldg-Roof Repairs | B27: 0 | C27: 1464.5 | D27: 5411.6 | E27: RM | G27: SEC | H27: Security | I27: =SUMIF($E$7:$E$79,G27,$D$7:$D$79) -> 0
A28: R&M-Genl Bldg-Other | B28: 0 | C28: 328.72 | D28: 0 | E28: RM | G28: LAND | H28: Landscaping | I28: =SUMIF($E$7:$E$79,G28,$D$7:$D$79) -> 12575.68
A29: R&M-Life Safety-Monit Contract | B29: 6609.25 | C29: 4529.84 | D29: 5287.41 | E29: RM | G29: PM | H29: Property Management | I29: =SUMIF($E$7:$E$79,G29,$D$7:$D$79) -> 6949.07
A30: R&M-Life Safety-Supplies | B30: 0 | C30: 0 | D30: 80.19 | E30: RM | G30: UR | H30: Utilities | I30: =SUMIF($E$7:$E$79,G30,$D$7:$D$79) -> 7530.1
A31: R&M-Life Safety-Maint & Repair | B31: 1900 | C31: 516 | D31: 3051.08 | E31: RM | G31: OVE | H31: Other Variable Expenses | I31: =SUMIF($E$7:$E$79,G31,$D$7:$D$79) -> 21435.94
A32: R&M Other | B32: 2928 | C32: 0 | D32: 0 | E32: RM | H32: Total Variable Expenses | I32: =SUM(I26:I31) -> 81538.77
A33: R&M Billed to Tenant | B33: -469.36 | C33: 0 | D33: -77.62 | E33: RM | H33: Fixed Expenses
A34: R&M-Other-Miscellaneous | B34: 401.54 | C34: 131.21 | D34: 4766.02 | E34: RM | G34: RETR | H34: Real Estate Taxes | I34: =SUMIF($E$7:$E$79,G34,$D$7:$D$79) -> 117806.88
A35: Landscaping-Contracted Service | B35: 10530.36 | C35: 11197.64 | D35: 12575.68 | E35: LAND | G35: IR | H35: Insurance | I35: =SUMIF($E$7:$E$79,G35,$D$7:$D$79) -> 8424.01
A36: Repairs/Maintenance | B36: 35688.14 | C36: 30985.13 | D36: 45303.66 | H36: Total Fixed Operating Expenses | I36: =SUM(I34:I35) -> 126230.89
A37: Utilities-Electric Expense | B37: 9773.88 | C37: 9175.94 | D37: 7239.11
A38: Utilities-Gas/Oil Expense | B38: 3182 | C38: 2210.48 | D38: -620 | H38: Total Reimbursable OpEx | I38: =+I36+I32 -> 207769.66
A39: Utilities-Water/Sewer Expense | B39: 810.63 | C39: 1131.26 | D39: 910.99
A40: Utilities | B40: 13766.51 | C40: 12517.68 | D40: 7530.1 | E40: UR | H40: Non-Reimbursable Operating Expenses
A41: Mgmt Office-Staff Payroll | B41: 346.74 | C41: 0 | D41: 0 | H41: Variable Operating Expenses
A42: Mgmt Office-Telephone | B42: 0 | C42: 0 | D42: 147.25 | G42: RMN | H42: Repairs and Maintenance | I42: =SUMIF($E$7:$E$79,G42,$D$7:$D$79) -> 0
A43: Mgmt Office-Postage/Delivery | B43: 10.94 | C43: 117.11 | D43: 98.32 | G43: SECN | H43: Security | I43: =SUMIF($E$7:$E$79,G43,$D$7:$D$79) -> 0
A44: Mgmt Office-Admin-Other | B44: 0 | C44: 12.53 | D44: 0 | G44: LANDN | H44: Landscaping | I44: =SUMIF($E$7:$E$79,G44,$D$7:$D$79) -> 0
A45: Admin-Travel Expense | B45: 0 | C45: 9.2 | D45: 38.18 | G45: UN | H45: Utilities | I45: =SUMIF($E$7:$E$79,G45,$D$7:$D$79) -> 0
A46: Administrative Services | B46: 357.68 | C46: 138.84 | D46: 283.75 | E46: OVE | G46: OVEN | H46: Other Variable Expenses | I46: =SUMIF($E$7:$E$79,G46,$D$7:$D$79) -> 0
A47: Real Estate Taxes | H47: Total Variable Expenses | I47: =SUM(I42:I46) -> 0
A48: Taxes-Real Estate | B48: 121662 | C48: 122160 | D48: 121200 | H48: Fixed Expenses
A49: Taxes-Real Estate-PY Adj | B49: -18376.92 | C49: -3056.04 | D49: -4496.22 | G49: RETN | H49: Real Estate Taxes | I49: =SUMIF($E$7:$E$79,G49,$D$7:$D$79) -> 0
A50: Taxes-Tax Consultant | B50: 6151.44 | C50: 608.7 | D50: 1103.1 | G50: IN | H50: Insurance | I50: =SUMIF($E$7:$E$79,G50,$D$7:$D$79) -> 0
A51: Real Estate Taxes | B51: 109436.52 | C51: 119712.66 | D51: 117806.88 | E51: RETR | H51: Total Fixed Operating Expenses | I51: =SUM(I49:I50) -> 0
A52: Land Owner Assoc. Fees | B52: 0 | C52: 3920 | D52: 0
A53: Other Taxes and Fees | B53: 0 | C53: 3920 | D53: 0 | E53: OVE | H53: Total Non-Reimbursable OpEx | I53: =+I51+I47 -> 0
A54: Insurance-Casualty | B54: 9763 | C54: 8995.9 | D54: 8424.01
A55: Insurance Expense | B55: 9763 | C55: 8995.9 | D55: 8424.01 | E55: IR | H55: Total Operating Expenses | I55: =I53+I38 -> 207769.66 | J55: =D71 -> 207769.66
A56: Marketing-Holiday Gifts | B56: 150 | C56: 258.58 | D56: 263.44
A57: Marketing-Signage | B57: 1860 | C57: 3000 | D57: 0 | H57: NET OPERATING INCOME | I57: =+I22-I55 -> 684967.8 | J57: =D73 -> 684967.8
A58: Marketing/Advertising | B58: 2010 | C58: 3258.58 | D58: 263.44 | E58: OVE | H58: CAPITAL EXPENDITURES
A59: Gar/Park-Snow Removal/Salt | B59: 24180 | C59: 18971.88 | D59: 16990 | H59: Leasing Commissions | I59: =-D78 -> 85549.02
A60: Gar/Park-Cleaning Exp | B60: 0 | C60: 0 | D60: 900 | H60: Tenant Improvements | I60: =D77 -> 0
A61: Gar/Park-Paving/Patching/Walks | B61: 10790 | C61: 10255 | D61: 2998.75 | H61: Capital Improvements | I61: =-D76 -> 9720.48
A62: Parking Operations | B62: 34970 | C62: 29226.88 | D62: 20888.75 | E62: OVE | H62: Capital Reserve | I62: 0
A63: Leasing Trans-Legal Expenses | B63: 0 | C63: 4650 | D63: 0 | H63: Total Capital Expenditures | I63: =SUM(I59:I62) -> 95269.5
A64: Leasing Expenses | B64: 0 | C64: 4650 | D64: 0 | E64: OVE
A65: Non-Recoverable - Utilities | B65: 11894.81 | C65: 6480.01 | D65: 0 | H65: CASH FLOW FROM OPERATIONS | I65: =+I57-I63 -> 589698.3 | J65: =D79 -> 589698.3
A66: Non-Recoverable | B66: 11894.81 | C66: 6480.01 | D66: 0 | E66: UN
A67: Property Management Fee | B67: 4411.25 | C67: 5682.74 | D67: 6949.07 | H67: Debt Service | I67: 120000
A68: Property Management Fee | B68: 4411.25 | C68: 5682.74 | D68: 6949.07 | E68: PM
A69: Non Oper - Legal | B69: 1137.5 | C69: 0 | D69: 0 | H69: CASH FLOW AFTER FINANCING | I69: =+I65-I67 -> 469698.3
A70: Non-Operating Expenses | B70: 1137.5 | C70: 0 | D70: 0 | E70: OVE
A71: Expenses | B71: 223755.41 | C71: 225728.42 | D71: 207769.66
A73: NET OPERATING INCOME | B73: 309774.08 | C73: 449648.03 | D73: 684967.8
A75: ADJUSTMENTS
A76: Building And Improvements | B76: 0 | C76: 0 | D76: -9720.48
A77: Tenant Improvements | B77: -11320 | C77: -83553 | D77: 0
A78: Leasing Commissions | B78: 0 | C78: -75608 | D78: -85549.02
A79: CASH FLOW | B79: 298454.08 | C79: 290487.03 | D79: 589698.3

Sheet Leasing Cost Calculator
B2: LEASING COST RESERVE CALCULATION
B4: Property Size | H4: 156160
B5: Renewal Probability | H5: 0.7
B6: Typical Lease Term | H6: 7
B7: Market Rent /SF | H7: 4.5
B8: Tenant Improvement Allowance /SF (New) | H8: 1.5
B9: Tenant Improvement Allowance /SF (Renewal) | H9: 0.5
B10: Leasing Commission % (New) | H10: 0.05
B11: Leasing Commission % (Renewal) | H11: 0.025
B13: Tenant Improvement Allowance (New) | H13: =H8*H4*(1-H5) -> 70272
B14: Tenant Improvement Allowance (Renewal) | H14: =H9*H4*H5 -> 54656
B15: Leasing Commission (New) | H15: =H4*H7*H6*H10*(1-H5) -> 73785.6
B16: Leasing Commission (Renewal) | H16: =H4*H7*H6*H11*H5 -> 86083.2
B17: Total Leasing Costs | H17: =SUM(H13:H16) -> 284796.8
B19: Annual Leasing Cost Reserve | H19: =H17/H6 -> 40685.257
B21: Annual Leasing Cost Reserve (In one formula) | H21: =(H8*(1-H5)+H9*H5+H10*(1-H5)*H7*H6+H11*H5*H7*H6)*H4/H6 -> 40685.257
