Workbook

Sheet Property-Level Cash Flow
B2: FROST AND MAIN - SUMMARY PROPERTY-LEVEL CASH FLOWS
B4: DEVELOPMENT CASH FLOWS
D5: 43830 | E5: =EOMONTH(D5,1) -> 43861 | F5: =EOMONTH(E5,1) -> 43890 | G5: =EOMONTH(F5,1) -> 43921 | H5: =EOMONTH(G5,1) -> 43951 | I5: =EOMONTH(H5,1) -> 43982 | J5: =EOMONTH(I5,1) -> 44012 | K5: =EOMONTH(J5,1) -> 44043 | L5: =EOMONTH(K5,1) -> 44074 | ... DT5: =EOMONTH(DS5,1) -> 47483
D6: =ROUNDUP(D7/12,0) -> 0 | E6: =ROUNDUP(E7/12,0) -> 1 | F6: =ROUNDUP(F7/12,0) -> 1 | G6: =ROUNDUP(G7/12,0) -> 1 | H6: =ROUNDUP(H7/12,0) -> 1 | I6: =ROUNDUP(I7/12,0) -> 1 | J6: =ROUNDUP(J7/12,0) -> 1 | K6: =ROUNDUP(K7/12,0) -> 1 | ... DT6: =ROUNDUP(DT7/12,0) -> 10
D7: 0 | E7: =D7+1 -> 1 | F7: =E7+1 -> 2 | G7: =F7+1 -> 3 | H7: =G7+1 -> 4 | I7: =H7+1 -> 5 | J7: =I7+1 -> 6 | K7: =J7+1 -> 7 | L7: =K7+1 -> 8 | ... DT7: =DS7+1 -> 120
B8: Total Project Cost | D8: -1914790.8 | E8: -9600.4767 | F8: -22344.154 | G8: -47790.626 | H8: -93935.734 | I8: -169679.63 | J8: -281670.02 | K8: -379699.33 | L8: -502424.74 | M8: -578026.71 | N8: 0 | O8: 0 | P8: 0 | Q8: 0 | R8: 0 | S8: 0 | T8: 0 | U8: 0 | V8: 0 | W8: 0 | X8: 0 | Y8: 0 | Z8: 0 | AA8: 0 | AB8: 0 | AC8: 0 | AD8: 0 | AE8: 0 | AF8: 0 | AG8: 0 | AH8: 0 | AI8: 0 | AJ8: 0 | AK8: 0 | AL8: 0 | AM8: 0 | AN8: 0 | AO8: 0 | AP8: 0 | AQ8: 0 | AR8: 0 | AS8: 0 | AT8: 0 | AU8: 0 | AV8: 0 | AW8: 0 | AX8: 0 | AY8: 0 | AZ8: 0 | BA8: 0 | BB8: 0 | BC8: 0 | BD8: 0 | BE8: 0 | BF8: 0 | BG8: 0 | BH8: 0 | BI8: 0 | BJ8: 0 | BK8: 0 | BL8: 0 | BM8: 0 | BN8: 0 | BO8: 0 | BP8: 0 | BQ8: 0 | BR8: 0 | BS8: 0 | BT8: 0 | BU8: 0 | BV8: 0 | BW8: 0 | BX8: 0 | BY8: 0 | BZ8: 0 | CA8: 0 | CB8: 0 | CC8: 0 | CD8: 0 | CE8: 0 | CF8: 0 | CG8: 0 | CH8: 0 | CI8: 0 | CJ8: 0 | CK8: 0 | CL8: 0 | CM8: 0 | CN8: 0 | CO8: 0 | CP8: 0 | CQ8: 0 | CR8: 0 | CS8: 0 | CT8: 0 | CU8: 0 | CV8: 0 | CW8: 0 | CX8: 0 | CY8: 0 | CZ8: 0 | DA8: 0 | DB8: 0 | DC8: 0 | DD8: 0 | DE8: 0 | DF8: 0 | DG8: 0 | DH8: 0 | DI8: 0 | DJ8: 0 | DK8: 0 | DL8: 0 | DM8: 0 | DN8: 0 | DO8: 0 | DP8: 0 | DQ8: 0 | DR8: 0 | DS8: 0 | DT8: 0
B9: Cash Flow after Financing | D9: 0 | E9: 0 | F9: 0 | G9: 0 | H9: 0 | I9: 0 | J9: 0 | K9: 0 | L9: 0 | M9: 0 | N9: 0 | O9: 0 | P9: 0 | Q9: 0 | R9: 0 | S9: 0 | T9: 0 | U9: 0 | V9: 0 | W9: 0 | X9: 0 | Y9: 0 | Z9: 0 | AA9: 0 | AB9: 0 | AC9: 0 | AD9: 0 | AE9: 0 | AF9: 0 | AG9: 0 | AH9: 39483.976 | AI9: 22477.421 | AJ9: 22477.421 | AK9: 22477.421 | AL9: 22477.421 | AM9: 22477.421 | AN9: 23113.074 | AO9: 23113.074 | AP9: 23113.074 | AQ9: 23113.074 | AR9: 23113.074 | AS9: 23113.074 | AT9: 23113.074 | AU9: 23113.074 | AV9: 23113.074 | AW9: 23113.074 | AX9: 23113.074 | AY9: 23113.074 | AZ9: 25489.355 | BA9: 25489.355 | BB9: 25489.355 | BC9: 25489.355 | BD9: 25489.355 | BE9: 25489.355 | BF9: 25489.355 | BG9: 14593.282 | BH9: 14593.282 | BI9: 14593.282 | BJ9: 14593.282 | BK9: 14593.282 | BL9: 17053.941 | BM9: 17053.941 | BN9: 17053.941 | BO9: 17053.941 | BP9: 17053.941 | BQ9: 17053.941 | BR9: 17053.941 | BS9: 17053.941 | BT9: 17053.941 | BU9: 17053.941 | BV9: 17053.941 | BW9: 17053.941 | BX9: 19601.77 | BY9: 19601.77 | BZ9: 19601.77 | CA9: 19601.77 | CB9: 19601.77 | CC9: 19601.77 | CD9: 19601.77 | CE9: 19601.77 | CF9: 19601.77 | CG9: 19601.77 | CH9: 19601.77 | CI9: 19601.77 | CJ9: 22239.653 | CK9: 22239.653 | CL9: 22239.653 | CM9: 22239.653 | CN9: 22239.653 | CO9: 22239.653 | CP9: 22239.653 | CQ9: 22239.653 | CR9: 22239.653 | CS9: 22239.653 | CT9: 22239.653 | CU9: 22239.653 | CV9: 24970.562 | CW9: 24970.562 | CX9: 24970.562 | CY9: 24970.562 | CZ9: 24970.562 | DA9: 24970.562 | DB9: 24970.562 | DC9: 24970.562 | DD9: 24970.562 | DE9: 24970.562 | DF9: 24970.562 | DG9: 24970.562 | DH9: 27797.566 | DI9: 27797.566 | DJ9: 27797.566 | DK9: 27797.566 | DL9: 27797.566 | DM9: 27797.566 | DN9: 27797.566 | DO9: 27797.566 | DP9: 27797.566 | DQ9: 27797.566 | DR9: 27797.566 | DS9: 27797.566 | DT9: 27797.566
B10: Net Proceeds from Sale | D10: 0 | E10: 0 | F10: 0 | G10: 0 | H10: 0 | I10: 0 | J10: 0 | K10: 0 | L10: 0 | M10: 0 | N10: 0 | O10: 0 | P10: 0 | Q10: 0 | R10: 0 | S10: 0 | T10: 0 | U10: 0 | V10: 0 | W10: 0 | X10: 0 | Y10: 0 | Z10: 0 | AA10: 0 | AB10: 0 | AC10: 0 | AD10: 0 | AE10: 0 | AF10: 0 | AG10: 0 | AH10: 0 | AI10: 0 | AJ10: 0 | AK10: 0 | AL10: 0 | AM10: 0 | AN10: 0 | AO10: 0 | AP10: 0 | AQ10: 0 | AR10: 0 | AS10: 0 | AT10: 0 | AU10: 0 | AV10: 0 | AW10: 0 | AX10: 0 | AY10: 0 | AZ10: 0 | BA10: 0 | BB10: 0 | BC10: 0 | BD10: 0 | BE10: 0 | BF10: 0 | BG10: 0 | BH10: 0 | BI10: 0 | BJ10: 0 | BK10: 0 | BL10: 0 | BM10: 0 | BN10: 0 | BO10: 0 | BP10: 0 | BQ10: 0 | BR10: 0 | BS10: 0 | BT10: 0 | BU10: 0 | BV10: 0 | BW10: 0 | BX10: 0 | BY10: 0 | BZ10: 0 | CA10: 0 | CB10: 0 | CC10: 0 | CD10: 0 | CE10: 0 | CF10: 0 | CG10: 0 | CH10: 0 | CI10: 0 | CJ10: 0 | CK10: 0 | CL10: 0 | CM10: 0 | CN10: 0 | CO10: 0 | CP10: 0 | CQ10: 0 | CR10: 0 | CS10: 0 | CT10: 0 | CU10: 0 | CV10: 0 | CW10: 0 | CX10: 0 | CY10: 0 | CZ10: 0 | DA10: 0 | DB10: 0 | DC10: 0 | DD10: 0 | DE10: 0 | DF10: 0 | DG10: 0 | DH10: 0 | DI10: 0 | DJ10: 0 | DK10: 0 | DL10: 0 | DM10: 0 | DN10: 0 | DO10: 0 | DP10: 0 | DQ10: 0 | DR10: 0 | DS10: 0 | DT10: 9736709.2
B11: Net Levered Cash Flow | D11: =SUM(D8:D10) -> -1914790.8 | E11: =SUM(E8:E10) -> -9600.4767 | F11: =SUM(F8:F10) -> -22344.154 | G11: =SUM(G8:G10) -> -47790.626 | H11: =SUM(H8:H10) -> -93935.734 | I11: =SUM(I8:I10) -> -169679.63 | J11: =SUM(J8:J10) -> -281670.02 | K11: =SUM(K8:K10) -> -379699.33 | ... DT11: =SUM(DT8:DT10) -> 9764506.8 | DV11: =+#REF! -> #REF! | DW11: =+#REF! -> #REF!
B12: Levered Internal Rate of Return | D12: =XIRR(D11:DT11,D5:DT5) -> 0.12964537
B13: Levered Equity Multiple | D13: =SUMIF(D11:DT11,">0")/-SUMIF(D11:DT11,"<0") -> 2.9463
B20: Hint: The Net Levered Cash Flow line should link to the GP-LP waterfall

Sheet GP-LP Returns
B2: PARTNERSHIP LEVEL RETURNS - EQUITY WATERFALL (IRR RETURN HURDLES)
B4: Equity Contributions | C4: % | D4: Amount
B5: General Partner (GP) | C5: 0.1 | D5: =+D27 -> 399996.22
B6: Limited Partner (LP) | C6: =1-C5 -> 0.9 | D6: =+D20 -> 3599966
B7: Total Equity | C7: =SUM(C5:C6) -> 1 | D7: =SUM(D5:D6) -> 3999962.2
F8: Promote Structure | H8: Distribution as % | K8: Error Check: | L8: =IF(L9=L10,"OK","ERROR") -> OK
B9: Promote Structure | F9: Incentive Breakdown | H9: GP % | I9: LP % | K9: Profit Dist.: | L9: =ROUND(D21+D28,0)/1000000 -> 7.785126
B10: Hurdle 1 (Preferred Return) | E10: 0.08 | F10: GP | G10: Partnership | H10: =C5 -> 0.1 | I10: =C6 -> 0.9 | K10: Net BTCF: | L10: =ROUND(SUM(F33:DV33),0)/1000000 -> 7.785126
B11: Hurdle 2 | D11: =E10 -> 0.08 | E11: 0.11 | F11: 0.2 | G11: =1-F11 -> 0.8 | H11: =F11+$C$5*G11 -> 0.28 | I11: =1-H11 -> 0.72
B12: Hurdle 3 | D12: =E11 -> 0.11 | E12: 0.14 | F12: 0.3 | G12: =1-F12 -> 0.7 | H12: =F12+$C$5*G12 -> 0.37 | I12: =1-H12 -> 0.63
B13: Hurdle 4 | D13: =E12 -> 0.14 | F13: 0.4 | G13: =1-F13 -> 0.6 | H13: =F13+$C$5*G13 -> 0.46 | I13: =1-H13 -> 0.54
E15: Month ending | F15: ='Property-Level Cash Flow'!D5 -> 43830 | G15: ='Property-Level Cash Flow'!E5 -> 43861 | H15: ='Property-Level Cash Flow'!F5 -> 43890 | I15: ='Property-Level Cash Flow'!G5 -> 43921 | J15: ='Property-Level Cash Flow'!H5 -> 43951 | K15: ='Property-Level Cash Flow'!I5 -> 43982 | L15: ='Property-Level Cash Flow'!J5 -> 44012 | M15: ='Property-Level Cash Flow'!K5 -> 44043 | ... DV15: ='Property-Level Cash Flow'!DT5 -> 47483
F16: =IF(F31="","",ROUNDUP(F31/12,0)) -> 0 | G16: =IF(G31="","",ROUNDUP(G31/12,0)) -> 1 | H16: =IF(H31="","",ROUNDUP(H31/12,0)) -> 1 | I16: =IF(I31="","",ROUNDUP(I31/12,0)) -> 1 | J16: =IF(J31="","",ROUNDUP(J31/12,0)) -> 1 | K16: =IF(K31="","",ROUNDUP(K31/12,0)) -> 1 | L16: =IF(L31="","",ROUNDUP(L31/12,0)) -> 1 | M16: =IF(M31="","",ROUNDUP(M31/12,0)) -> 1 | ... DV16: =IF(DV31="","",ROUNDUP(DV31/12,0)) -> 10
B17: Summary of Investor Level Returns | F17: 0 | G17: =F17+1 -> 1 | H17: =G17+1 -> 2 | I17: =H17+1 -> 3 | J17: =I17+1 -> 4 | K17: =J17+1 -> 5 | L17: =K17+1 -> 6 | M17: =L17+1 -> 7 | N17: =M17+1 -> 8 | ... DV17: =DU17+1 -> 120
B18: Limited Partner (LP) Returns
B19: Total LP Distributions | D19: =SUM(F19:DV19) -> 9764032.6 | F19: =F47+F62+F77+F84 -> 0 | G19: =G47+G62+G77+G84 -> 0 | H19: =H47+H62+H77+H84 -> 0 | I19: =I47+I62+I77+I84 -> 0 | J19: =J47+J62+J77+J84 -> 0 | K19: =K47+K62+K77+K84 -> 0 | L19: =L47+L62+L77+L84 -> 0 | M19: =M47+M62+M77+M84 -> 0 | ... DV19: =DV47+DV62+DV77+DV84 -> 7945509
B20: Total LP Contributions | D20: =SUM(F20:DV20) -> 3599966 | F20: =F42 -> 1723311.7 | G20: =G42 -> 8640.429 | H20: =H42 -> 20109.738 | I20: =I42 -> 43011.563 | J20: =J42 -> 84542.161 | K20: =K42 -> 152711.67 | L20: =L42 -> 253503.02 | M20: =M42 -> 341729.4 | ... DV20: =DV42 -> 0
B21: Total LP Profit | D21: =D19-D20 -> 6164066.6
B22: LP IRR | D22: =XIRR(F22:DV22,$F$15:$DV$15) -> 0.119866 | F22: =-F20+F19 -> -1723311.7 | G22: =-G20+G19 -> -8640.429 | H22: =-H20+H19 -> -20109.738 | I22: =-I20+I19 -> -43011.563 | J22: =-J20+J19 -> -84542.161 | K22: =-K20+K19 -> -152711.67 | L22: =-L20+L19 -> -253503.02 | M22: =-M20+M19 -> -341729.4 | ... DV22: =-DV20+DV19 -> 7945509
B23: LP Equity Multiple | D23: =SUMIF(F22:DV22,">0")/-SUMIF($F$22:$DV$22,"<0") -> 2.7122569
B25: GP Returns
B26: Total GP Distributions | D26: =SUM(F26:DV26) -> 2021056 | F26: =+F48+F63+F78+F85+F32 -> 0 | G26: =+G48+G63+G78+G85+G32 -> 0 | H26: =+H48+H63+H78+H85+H32 -> 0 | I26: =+I48+I63+I78+I85+I32 -> 0 | J26: =+J48+J63+J78+J85+J32 -> 0 | K26: =+K48+K63+K78+K85+K32 -> 0 | L26: =+L48+L63+L78+L85+L32 -> 0 | M26: =+M48+M63+M78+M85+M32 -> 0 | ... DV26: =+DV48+DV63+DV78+DV85+DV32 -> 1818997.8
B27: Total GP Contributions | D27: =SUM(F27:DV27) -> 399996.22 | F27: =-(MIN(F34,0)+F42) -> 191479.08 | G27: =-(MIN(G34,0)+G42) -> 960.04767 | H27: =-(MIN(H34,0)+H42) -> 2234.4154 | I27: =-(MIN(I34,0)+I42) -> 4779.0626 | J27: =-(MIN(J34,0)+J42) -> 9393.5734 | K27: =-(MIN(K34,0)+K42) -> 16967.963 | L27: =-(MIN(L34,0)+L42) -> 28167.002 | M27: =-(MIN(M34,0)+M42) -> 37969.933 | ... DV27: =-(MIN(DV34,0)+DV42) -> 0
B28: Total GP Profit | D28: =D26-D27 -> 1621059.8
B29: GP IRR | D29: =XIRR(F29:DV29,$F$15:$DV$15) -> 0.19425916 | F29: =-F27+F26 -> -191479.08 | G29: =-G27+G26 -> -960.04767 | H29: =-H27+H26 -> -2234.4154 | I29: =-I27+I26 -> -4779.0626 | J29: =-J27+J26 -> -9393.5734 | K29: =-K27+K26 -> -16967.963 | L29: =-L27+L26 -> -28167.002 | M29: =-M27+M26 -> -37969.933 | ... DV29: =-DV27+DV26 -> 1818997.8
B30: GP Equity Multiple | D30: =SUMIF(F29:DV29,">0")/-SUMIF($F$29:$DV$29,"<0") -> 5.0526877
B31: Net Cash Flow for Distribution | D31: AUM Fee % | E31: AUM | F31: 0 | G31: =F31+1 -> 1 | H31: =G31+1 -> 2 | I31: =H31+1 -> 3 | J31: =I31+1 -> 4 | K31: =J31+1 -> 5 | L31: =K31+1 -> 6 | M31: =L31+1 -> 7 | N31: =M31+1 -> 8 | ... DV31: =DU31+1 -> 120
B32: General Partner Fees | F32: 0 | G32: 0 | H32: 0 | I32: 0 | J32: 0 | K32: 0 | L32: 0 | M32: 0 | N32: 0 | O32: 0 | P32: 0 | Q32: 0 | R32: 0 | S32: 0 | T32: 0 | U32: 0 | V32: 0 | W32: 0 | X32: 0 | Y32: 0 | Z32: 0 | AA32: 0 | AB32: 0 | AC32: 0 | AD32: 0 | AE32: 0 | AF32: 0 | AG32: 0 | AH32: 0 | AI32: 0 | AJ32: 0 | AK32: 0 | AL32: 0 | AM32: 0 | AN32: 0 | AO32: 0 | AP32: 0 | AQ32: 0 | AR32: 0 | AS32: 0 | AT32: 0 | AU32: 0 | AV32: 0 | AW32: 0 | AX32: 0 | AY32: 0 | AZ32: 0 | BA32: 0 | BB32: 0 | BC32: 0 | BD32: 0 | BE32: 0 | BF32: 0 | BG32: 0 | BH32: 0 | BI32: 0 | BJ32: 0 | BK32: 0 | BL32: 0 | BM32: 0 | BN32: 0 | BO32: 0 | BP32: 0 | BQ32: 0 | BR32: 0 | BS32: 0 | BT32: 0 | BU32: 0 | BV32: 0 | BW32: 0 | BX32: 0 | BY32: 0 | BZ32: 0 | CA32: 0 | CB32: 0 | CC32: 0 | CD32: 0 | CE32: 0 | CF32: 0 | CG32: 0 | CH32: 0 | CI32: 0 | CJ32: 0 | CK32: 0 | CL32: 0 | CM32: 0 | CN32: 0 | CO32: 0 | CP32: 0 | CQ32: 0 | CR32: 0 | CS32: 0 | CT32: 0 | CU32: 0 | CV32: 0 | CW32: 0 | CX32: 0 | CY32: 0 | CZ32: 0 | DA32: 0 | DB32: 0 | DC32: 0 | DD32: 0 | DE32: 0 | DF32: 0 | DG32: 0 | DH32: 0 | DI32: 0 | DJ32: 0 | DK32: 0 | DL32: 0 | DM32: 0 | DN32: 0 | DO32: 0 | DP32: 0 | DQ32: 0 | DR32: 0 | DS32: 0 | DT32: 0 | DU32: 0 | DV32: 0
B33: Gross Property Levered Before Tax Cash Flow | F33: ='Property-Level Cash Flow'!D11 -> -1914790.8 | G33: ='Property-Level Cash Flow'!E11 -> -9600.4767 | H33: ='Property-Level Cash Flow'!F11 -> -22344.154 | I33: ='Property-Level Cash Flow'!G11 -> -47790.626 | J33: ='Property-Level Cash Flow'!H11 -> -93935.734 | K33: ='Property-Level Cash Flow'!I11 -> -169679.63 | L33: ='Property-Level Cash Flow'!J11 -> -281670.02 | M33: ='Property-Level Cash Flow'!K11 -> -379699.33 | ... DV33: ='Property-Level Cash Flow'!DT11 -> 9764506.8
B34: Net Property Levered Before Tax Cash Flow | F34: =F33-F32 -> -1914790.8 | G34: =G33-G32 -> -9600.4767 | H34: =H33-H32 -> -22344.154 | I34: =I33-I32 -> -47790.626 | J34: =J33-J32 -> -93935.734 | K34: =K33-K32 -> -169679.63 | L34: =L33-L32 -> -281670.02 | M34: =M33-M32 -> -379699.33 | ... DV34: =DV33-DV32 -> 9764506.8
B35: Property Levered IRR (Net of GP Fees) | F35: =XIRR($F$34:$DV$34,$F$15:$DV$15) -> 0.12964537
B36: Property Levered Emx (Net of GP Fees) | F36: =SUMIF(F34:DV34,">0")/-SUMIF($F$34:$DV$34,"<0") -> 2.9463
B38: Hurdle 1
B39: LP Req'd Return | C39: =E10 -> 0.08 | F39: =F$17 -> 0 | G39: =G$17 -> 1 | H39: =H$17 -> 2 | I39: =I$17 -> 3 | J39: =J$17 -> 4 | K39: =K$17 -> 5 | L39: =L$17 -> 6 | M39: =M$17 -> 7 | ... DV39: =DV$17 -> 120
B40: Beginning Balance (LP Capital Account) | F40: =E44 -> 0 | G40: =F44 -> 1723311.7 | H40: =G44 -> 1743040 | I40: =H44 -> 1774364.5 | J40: =I44 -> 1828792.4 | K40: =J44 -> 1925101 | L40: =K44 -> 2090198.8 | M40: =L44 -> 2357150.3 | ... DV40: =DU44 -> 5107045.5
B41: Req'd Return by LP (Pref) | F41: =F40*((1+$C$39)^(1/12)-1) -> 0 | G41: =G40*((1+$C$39)^(1/12)-1) -> 11087.839 | H41: =H40*((1+$C$39)^(1/12)-1) -> 11214.772 | I41: =I40*((1+$C$39)^(1/12)-1) -> 11416.314 | J41: =J40*((1+$C$39)^(1/12)-1) -> 11766.505 | K41: =K40*((1+$C$39)^(1/12)-1) -> 12386.158 | L41: =L40*((1+$C$39)^(1/12)-1) -> 13448.402 | M41: =M40*((1+$C$39)^(1/12)-1) -> 15165.976 | ... DV41: =DV40*((1+$C$39)^(1/12)-1) -> 32858.884
B42: Contributions from LP | F42: =-MIN(F34,0)*$C$6 -> 1723311.7 | G42: =-MIN(G34,0)*$C$6 -> 8640.429 | H42: =-MIN(H34,0)*$C$6 -> 20109.738 | I42: =-MIN(I34,0)*$C$6 -> 43011.563 | J42: =-MIN(J34,0)*$C$6 -> 84542.161 | K42: =-MIN(K34,0)*$C$6 -> 152711.67 | L42: =-MIN(L34,0)*$C$6 -> 253503.02 | M42: =-MIN(M34,0)*$C$6 -> 341729.4 | ... DV42: =-MIN(DV34,0)*$C$6 -> 0
B43: Distributions to LP (Hurdle 1) | F43: =MIN(F40+F41,MAX(F34,0)*$I$10) -> 0 | G43: =MIN(G40+G41,MAX(G34,0)*$I$10) -> 0 | H43: =MIN(H40+H41,MAX(H34,0)*$I$10) -> 0 | I43: =MIN(I40+I41,MAX(I34,0)*$I$10) -> 0 | J43: =MIN(J40+J41,MAX(J34,0)*$I$10) -> 0 | K43: =MIN(K40+K41,MAX(K34,0)*$I$10) -> 0 | L43: =MIN(L40+L41,MAX(L34,0)*$I$10) -> 0 | M43: =MIN(M40+M41,MAX(M34,0)*$I$10) -> 0 | ... DV43: =MIN(DV40+DV41,MAX(DV34,0)*$I$10) -> 5139904.4
B44: Ending Balance (LP Capital Account) | F44: =F40+F41+F42-F43 -> 1723311.7 | G44: =G40+G41+G42-G43 -> 1743040 | H44: =H40+H41+H42-H43 -> 1774364.5 | I44: =I40+I41+I42-I43 -> 1828792.4 | J44: =J40+J41+J42-J43 -> 1925101 | K44: =K40+K41+K42-K43 -> 2090198.8 | L44: =L40+L41+L42-L43 -> 2357150.3 | M44: =M40+M41+M42-M43 -> 2714045.6 | ... DV44: =DV40+DV41+DV42-DV43 -> 0
B45: =C39 -> 0.08 | E45: =XIRR(F45:DV45,$F$15:$DV$15) -> 0.079936638 | F45: =-F42+F43 -> -1723311.7 | G45: =-G42+G43 -> -8640.429 | H45: =-H42+H43 -> -20109.738 | I45: =-I42+I43 -> -43011.563 | J45: =-J42+J43 -> -84542.161 | K45: =-K42+K43 -> -152711.67 | L45: =-L42+L43 -> -253503.02 | M45: =-M42+M43 -> -341729.4 | ... DV45: =-DV42+DV43 -> 5139904.4
B47: Distribution to LP | F47: =+F43 -> 0 | G47: =+G43 -> 0 | H47: =+H43 -> 0 | I47: =+I43 -> 0 | J47: =+J43 -> 0 | K47: =+K43 -> 0 | L47: =+L43 -> 0 | M47: =+M43 -> 0 | ... DV47: =+DV43 -> 5139904.4
B48: Distribution to GP | F48: =F47/$I$10*$H$10 -> 0 | G48: =G47/$I$10*$H$10 -> 0 | H48: =H47/$I$10*$H$10 -> 0 | I48: =I47/$I$10*$H$10 -> 0 | J48: =J47/$I$10*$H$10 -> 0 | K48: =K47/$I$10*$H$10 -> 0 | L48: =L47/$I$10*$H$10 -> 0 | M48: =M47/$I$10*$H$10 -> 0 | ... DV48: =DV47/$I$10*$H$10 -> 571100.48
B49: ="Total Distributions ("&B38&")" -> Total Distributions (Hurdle 1) | F49: =SUM(F47:F48) -> 0 | G49: =SUM(G47:G48) -> 0 | H49: =SUM(H47:H48) -> 0 | I49: =SUM(I47:I48) -> 0 | J49: =SUM(J47:J48) -> 0 | K49: =SUM(K47:K48) -> 0 | L49: =SUM(L47:L48) -> 0 | M49: =SUM(M47:M48) -> 0 | ... DV49: =SUM(DV47:DV48) -> 5711004.8
B50: Cash Flow Remaining | F50: =MAX(F34-F49,0) -> 0 | G50: =MAX(G34-G49,0) -> 0 | H50: =MAX(H34-H49,0) -> 0 | I50: =MAX(I34-I49,0) -> 0 | J50: =MAX(J34-J49,0) -> 0 | K50: =MAX(K34-K49,0) -> 0 | L50: =MAX(L34-L49,0) -> 0 | M50: =MAX(M34-M49,0) -> 0 | ... DV50: =MAX(DV34-DV49,0) -> 4053501.9
B52: Hurdle 2
B53: LP Req'd Return | C53: =E11 -> 0.11 | F53: =F$17 -> 0 | G53: =G$17 -> 1 | H53: =H$17 -> 2 | I53: =I$17 -> 3 | J53: =J$17 -> 4 | K53: =K$17 -> 5 | L53: =L$17 -> 6 | M53: =M$17 -> 7 | ... DV53: =DV$17 -> 120
B54: Beginning Balance (LP Capital Account) | F54: =E59 -> 0 | G54: =F59 -> 1723311.7 | H54: =G59 -> 1747004.6 | I54: =H59 -> 1782373.7 | J54: =I59 -> 1840953.5 | K54: =J59 -> 1941575.7 | L54: =K59 -> 2111246.2 | M54: =L59 -> 2383190.1 | ... DV54: =DU59 -> 7093135.9
B55: Req'd Return by LP | F55: =F54*((1+$C$53)^(1/12)-1) -> 0 | G55: =G54*((1+$C$53)^(1/12)-1) -> 15052.428 | H55: =H54*((1+$C$53)^(1/12)-1) -> 15259.375 | I55: =I54*((1+$C$53)^(1/12)-1) -> 15568.31 | J55: =J54*((1+$C$53)^(1/12)-1) -> 16079.981 | K55: =K54*((1+$C$53)^(1/12)-1) -> 16958.875 | L55: =L54*((1+$C$53)^(1/12)-1) -> 18440.878 | M55: =M54*((1+$C$53)^(1/12)-1) -> 20816.198 | ... DV55: =DV54*((1+$C$53)^(1/12)-1) -> 61955.661
B56: Contributions from LP | F56: =F42 -> 1723311.7 | G56: =G42 -> 8640.429 | H56: =H42 -> 20109.738 | I56: =I42 -> 43011.563 | J56: =J42 -> 84542.161 | K56: =K42 -> 152711.67 | L56: =L42 -> 253503.02 | M56: =M42 -> 341729.4 | ... DV56: =DV42 -> 0
B57: Prior Distributions | F57: =F47 -> 0 | G57: =G47 -> 0 | H57: =H47 -> 0 | I57: =I47 -> 0 | J57: =J47 -> 0 | K57: =K47 -> 0 | L57: =L47 -> 0 | M57: =M47 -> 0 | ... DV57: =DV47 -> 5139904.4
B58: ="Distributions to LP "&B52 -> Distributions to LP Hurdle 2 | F58: =MIN(F54+F55-F57,F50*$I$11) -> 0 | G58: =MIN(G54+G55-G57,G50*$I$11) -> 0 | H58: =MIN(H54+H55-H57,H50*$I$11) -> 0 | I58: =MIN(I54+I55-I57,I50*$I$11) -> 0 | J58: =MIN(J54+J55-J57,J50*$I$11) -> 0 | K58: =MIN(K54+K55-K57,K50*$I$11) -> 0 | L58: =MIN(L54+L55-L57,L50*$I$11) -> 0 | M58: =MIN(M54+M55-M57,M50*$I$11) -> 0 | ... DV58: =MIN(DV54+DV55-DV57,DV50*$I$11) -> 2015187.2
B59: Ending Balance (LP Capital Account) | F59: =F54+F55+F56-F57-F58 -> 1723311.7 | G59: =G54+G55+G56-G57-G58 -> 1747004.6 | H59: =H54+H55+H56-H57-H58 -> 1782373.7 | I59: =I54+I55+I56-I57-I58 -> 1840953.5 | J59: =J54+J55+J56-J57-J58 -> 1941575.7 | K59: =K54+K55+K56-K57-K58 -> 2111246.2 | L59: =L54+L55+L56-L57-L58 -> 2383190.1 | M59: =M54+M55+M56-M57-M58 -> 2745735.7 | ... DV59: =DV54+DV55+DV56-DV57-DV58 -> 0
B60: =C53 -> 0.11 | E60: =XIRR(F60:DV60,$F$15:$DV$15) -> 0.10991047 | F60: =-F56+F57+F58 -> -1723311.7 | G60: =-G56+G57+G58 -> -8640.429 | H60: =-H56+H57+H58 -> -20109.738 | I60: =-I56+I57+I58 -> -43011.563 | J60: =-J56+J57+J58 -> -84542.161 | K60: =-K56+K57+K58 -> -152711.67 | L60: =-L56+L57+L58 -> -253503.02 | M60: =-M56+M57+M58 -> -341729.4 | ... DV60: =-DV56+DV57+DV58 -> 7155091.6
B61: .
B62: Distribution to LP | F62: =F58 -> 0 | G62: =G58 -> 0 | H62: =H58 -> 0 | I62: =I58 -> 0 | J62: =J58 -> 0 | K62: =K58 -> 0 | L62: =L58 -> 0 | M62: =M58 -> 0 | ... DV62: =DV58 -> 2015187.2
B63: Distribution to GP | F63: =F62/$I$11*$H$11 -> 0 | G63: =G62/$I$11*$H$11 -> 0 | H63: =H62/$I$11*$H$11 -> 0 | I63: =I62/$I$11*$H$11 -> 0 | J63: =J62/$I$11*$H$11 -> 0 | K63: =K62/$I$11*$H$11 -> 0 | L63: =L62/$I$11*$H$11 -> 0 | M63: =M62/$I$11*$H$11 -> 0 | ... DV63: =DV62/$I$11*$H$11 -> 783683.93
B64: ="Total Distributions ("&B52&")" -> Total Distributions (Hurdle 2) | F64: =SUM(F62:F63) -> 0 | G64: =SUM(G62:G63) -> 0 | H64: =SUM(H62:H63) -> 0 | I64: =SUM(I62:I63) -> 0 | J64: =SUM(J62:J63) -> 0 | K64: =SUM(K62:K63) -> 0 | L64: =SUM(L62:L63) -> 0 | M64: =SUM(M62:M63) -> 0 | ... DV64: =SUM(DV62:DV63) -> 2798871.2
B65: Cash Flow Remaining | F65: =MAX(F34-F49-F64,0) -> 0 | G65: =MAX(G34-G49-G64,0) -> 0 | H65: =MAX(H34-H49-H64,0) -> 0 | I65: =MAX(I34-I49-I64,0) -> 0 | J65: =MAX(J34-J49-J64,0) -> 0 | K65: =MAX(K34-K49-K64,0) -> 0 | L65: =MAX(L34-L49-L64,0) -> 0 | M65: =MAX(M34-M49-M64,0) -> 0 | ... DV65: =MAX(DV34-DV49-DV64,0) -> 1254630.8
B67: Hurdle 3
B68: LP Req'd Return | C68: =E12 -> 0.14 | F68: =F$17 -> 0 | G68: =G$17 -> 1 | H68: =H$17 -> 2 | I68: =I$17 -> 3 | J68: =J$17 -> 4 | K68: =K$17 -> 5 | L68: =L$17 -> 6 | M68: =M$17 -> 7 | ... DV68: =DV$17 -> 120
B69: Beginning Balance (LP Capital Account) | F69: =E74 -> 0 | G69: =F74 -> 1723311.7 | H69: =G74 -> 1750872.1 | I69: =H74 -> 1790204.4 | J69: =I74 -> 1852870.4 | K69: =J74 -> 1957754.9 | L69: =K74 -> 2131960.5 | M69: =L74 -> 2408870 | ... DV69: =DU74 -> 9639625.3
B70: Req'd Return by LP | F70: =F69*((1+$C$68)^(1/12)-1) -> 0 | G70: =G69*((1+$C$68)^(1/12)-1) -> 18919.984 | H70: =H69*((1+$C$68)^(1/12)-1) -> 19222.566 | I70: =I69*((1+$C$68)^(1/12)-1) -> 19654.389 | J70: =J69*((1+$C$68)^(1/12)-1) -> 20342.389 | K70: =K69*((1+$C$68)^(1/12)-1) -> 21493.901 | L70: =L69*((1+$C$68)^(1/12)-1) -> 23406.479 | M70: =M69*((1+$C$68)^(1/12)-1) -> 26446.627 | ... DV70: =DV69*((1+$C$68)^(1/12)-1) -> 105832.02
B71: Contributions from LP | F71: =F56 -> 1723311.7 | G71: =G56 -> 8640.429 | H71: =H56 -> 20109.738 | I71: =I56 -> 43011.563 | J71: =J56 -> 84542.161 | K71: =K56 -> 152711.67 | L71: =L56 -> 253503.02 | M71: =M56 -> 341729.4 | ... DV71: =DV56 -> 0
B72: Prior Distributions | F72: =F47+F62 -> 0 | G72: =G47+G62 -> 0 | H72: =H47+H62 -> 0 | I72: =I47+I62 -> 0 | J72: =J47+J62 -> 0 | K72: =K47+K62 -> 0 | L72: =L47+L62 -> 0 | M72: =M47+M62 -> 0 | ... DV72: =DV47+DV62 -> 7155091.6
B73: ="Distributions to LP "&B67 -> Distributions to LP Hurdle 3 | F73: =MIN(F69+F70-F72,F65*$I$12) -> 0 | G73: =MIN(G69+G70-G72,G65*$I$12) -> 0 | H73: =MIN(H69+H70-H72,H65*$I$12) -> 0 | I73: =MIN(I69+I70-I72,I65*$I$12) -> 0 | J73: =MIN(J69+J70-J72,J65*$I$12) -> 0 | K73: =MIN(K69+K70-K72,K65*$I$12) -> 0 | L73: =MIN(L69+L70-L72,L65*$I$12) -> 0 | M73: =MIN(M69+M70-M72,M65*$I$12) -> 0 | ... DV73: =MIN(DV69+DV70-DV72,DV65*$I$12) -> 790417.39
B74: Ending Balance (LP Capital Account) | F74: =F69+F70+F71-F72-F73 -> 1723311.7 | G74: =G69+G70+G71-G72-G73 -> 1750872.1 | H74: =H69+H70+H71-H72-H73 -> 1790204.4 | I74: =I69+I70+I71-I72-I73 -> 1852870.4 | J74: =J69+J70+J71-J72-J73 -> 1957754.9 | K74: =K69+K70+K71-K72-K73 -> 2131960.5 | L74: =L69+L70+L71-L72-L73 -> 2408870 | M74: =M69+M70+M71-M72-M73 -> 2777046 | ... DV74: =DV69+DV70+DV71-DV72-DV73 -> 1799948.3
B75: =C68 -> 0.14 | E75: =XIRR(F75:DV75,$F$15:$DV$15) -> 0.119866 | F75: =-F71+F72+F73 -> -1723311.7 | G75: =-G71+G72+G73 -> -8640.429 | H75: =-H71+H72+H73 -> -20109.738 | I75: =-I71+I72+I73 -> -43011.563 | J75: =-J71+J72+J73 -> -84542.161 | K75: =-K71+K72+K73 -> -152711.67 | L75: =-L71+L72+L73 -> -253503.02 | M75: =-M71+M72+M73 -> -341729.4 | ... DV75: =-DV71+DV72+DV73 -> 7945509
B76: .
B77: Distribution to LP | F77: =F73 -> 0 | G77: =G73 -> 0 | H77: =H73 -> 0 | I77: =I73 -> 0 | J77: =J73 -> 0 | K77: =K73 -> 0 | L77: =L73 -> 0 | M77: =M73 -> 0 | ... DV77: =DV73 -> 790417.39
B78: Distribution to GP | F78: =F77/$I$12*$H$12 -> 0 | G78: =G77/$I$12*$H$12 -> 0 | H78: =H77/$I$12*$H$12 -> 0 | I78: =I77/$I$12*$H$12 -> 0 | J78: =J77/$I$12*$H$12 -> 0 | K78: =K77/$I$12*$H$12 -> 0 | L78: =L77/$I$12*$H$12 -> 0 | M78: =M77/$I$12*$H$12 -> 0 | ... DV78: =DV77/$I$12*$H$12 -> 464213.39
B79: ="Total Distributions ("&B67&")" -> Total Distributions (Hurdle 3) | F79: =SUM(F77:F78) -> 0 | G79: =SUM(G77:G78) -> 0 | H79: =SUM(H77:H78) -> 0 | I79: =SUM(I77:I78) -> 0 | J79: =SUM(J77:J78) -> 0 | K79: =SUM(K77:K78) -> 0 | L79: =SUM(L77:L78) -> 0 | M79: =SUM(M77:M78) -> 0 | ... DV79: =SUM(DV77:DV78) -> 1254630.8
B80: Cash Flow Remaining | F80: =MAX(F34-F49-F64-F79,0) -> 0 | G80: =MAX(G34-G49-G64-G79,0) -> 0 | H80: =MAX(H34-H49-H64-H79,0) -> 0 | I80: =MAX(I34-I49-I64-I79,0) -> 0 | J80: =MAX(J34-J49-J64-J79,0) -> 0 | K80: =MAX(K34-K49-K64-K79,0) -> 0 | L80: =MAX(L34-L49-L64-L79,0) -> 0 | M80: =MAX(M34-M49-M64-M79,0) -> 0 | ... DV80: =MAX(DV34-DV49-DV64-DV79,0) -> 0
B82: Hurdle 4
B83: LP Req'd Return | F83: =F$17 -> 0 | G83: =G$17 -> 1 | H83: =H$17 -> 2 | I83: =I$17 -> 3 | J83: =J$17 -> 4 | K83: =K$17 -> 5 | L83: =L$17 -> 6 | M83: =M$17 -> 7 | ... DV83: =DV$17 -> 120
B84: Distribution to LP | F84: =F80*$I$13 -> 0 | G84: =G80*$I$13 -> 0 | H84: =H80*$I$13 -> 0 | I84: =I80*$I$13 -> 0 | J84: =J80*$I$13 -> 0 | K84: =K80*$I$13 -> 0 | L84: =L80*$I$13 -> 0 | M84: =M80*$I$13 -> 0 | ... DV84: =DV80*$I$13 -> 0
B85: Distribution to GP | F85: =F80*$H$13 -> 0 | G85: =G80*$H$13 -> 0 | H85: =H80*$H$13 -> 0 | I85: =I80*$H$13 -> 0 | J85: =J80*$H$13 -> 0 | K85: =K80*$H$13 -> 0 | L85: =L80*$H$13 -> 0 | M85: =M80*$H$13 -> 0 | ... DV85: =DV80*$H$13 -> 0
B86: ="Total Distributions ("&B82&")" -> Total Distributions (Hurdle 4) | F86: =SUM(F84:F85) -> 0 | G86: =SUM(G84:G85) -> 0 | H86: =SUM(H84:H85) -> 0 | I86: =SUM(I84:I85) -> 0 | J86: =SUM(J84:J85) -> 0 | K86: =SUM(K84:K85) -> 0 | L86: =SUM(L84:L85) -> 0 | M86: =SUM(M84:M85) -> 0 | ... DV86: =SUM(DV84:DV85) -> 0
B87: Cash Flow Remaining | F87: =MAX(F34-F49-F64-F79-F86,0) -> 0 | G87: =MAX(G34-G49-G64-G79-G86,0) -> 0 | H87: =MAX(H34-H49-H64-H79-H86,0) -> 0 | I87: =MAX(I34-I49-I64-I79-I86,0) -> 0 | J87: =MAX(J34-J49-J64-J79-J86,0) -> 0 | K87: =MAX(K34-K49-K64-K79-K86,0) -> 0 | L87: =MAX(L34-L49-L64-L79-L86,0) -> 0 | M87: =MAX(M34-M49-M64-M79-M86,0) -> 0 | ... DV87: =MAX(DV34-DV49-DV64-DV79-DV86,0) -> 0

Sheet Co-GP Returns
B2: PARTNERSHIP LEVEL RETURNS - EQUITY WATERFALL (IRR RETURN HURDLES)
B4: Equity Contributions | C4: % | D4: Amount
B5: General Partner (Sponsor) | C5: 0.05 | D5: =+D27 -> 19999.811
B6: Limited Partner (Investors) | C6: =1-C5 -> 0.95 | D6: =+D20 -> 379996.41
B7: Total Equity | C7: =SUM(C5:C6) -> 1 | D7: =SUM(D5:D6) -> 399996.22
F8: Promote Structure | H8: Distribution as % | K8: Error Check: | L8: =IF(L9=L10,"OK","ERROR") -> OK
B9: Promote Structure | F9: Incentive Breakdown | H9: Sponsor % | I9: Investors % | K9: Profit Dist.: | L9: =ROUND(D21+D28,0)/1000000 -> 1.62106
B10: Hurdle 1 (Preferred Return) | E10: 0.15 | F10: Sponsor | G10: Partnership | H10: =C5 -> 0.05 | I10: =C6 -> 0.95 | K10: Net BTCF: | L10: =ROUND(SUM(F33:DV33),0)/1000000 -> 1.62106
B11: Hurdle 2 | D11: =E10 -> 0.15 | E11: 9.99 | F11: 0.4 | G11: =1-F11 -> 0.6 | H11: =F11+$C$5*G11 -> 0.43 | I11: =1-H11 -> 0.57
B12: Hurdle 3 | D12: =E11 -> 9.99 | E12: 9.99 | F12: 0.4 | G12: =1-F12 -> 0.6 | H12: =F12+$C$5*G12 -> 0.43 | I12: =1-H12 -> 0.57
B13: Hurdle 4 | D13: =E12 -> 9.99 | F13: 0.4 | G13: =1-F13 -> 0.6 | H13: =F13+$C$5*G13 -> 0.43 | I13: =1-H13 -> 0.57
E15: Month ending | F15: ='GP-LP Returns'!F15 -> 43830 | G15: ='GP-LP Returns'!G15 -> 43861 | H15: ='GP-LP Returns'!H15 -> 43890 | I15: ='GP-LP Returns'!I15 -> 43921 | J15: ='GP-LP Returns'!J15 -> 43951 | K15: ='GP-LP Returns'!K15 -> 43982 | L15: ='GP-LP Returns'!L15 -> 44012 | M15: ='GP-LP Returns'!M15 -> 44043 | ... DV15: ='GP-LP Returns'!DV15 -> 47483
F16: =IF(F31="","",ROUNDUP(F31/12,0)) -> 0 | G16: =IF(G31="","",ROUNDUP(G31/12,0)) -> 1 | H16: =IF(H31="","",ROUNDUP(H31/12,0)) -> 1 | I16: =IF(I31="","",ROUNDUP(I31/12,0)) -> 1 | J16: =IF(J31="","",ROUNDUP(J31/12,0)) -> 1 | K16: =IF(K31="","",ROUNDUP(K31/12,0)) -> 1 | L16: =IF(L31="","",ROUNDUP(L31/12,0)) -> 1 | M16: =IF(M31="","",ROUNDUP(M31/12,0)) -> 1 | ... DV16: =IF(DV31="","",ROUNDUP(DV31/12,0)) -> 10
B17: Summary of Investor Level Returns | F17: 0 | G17: =F17+1 -> 1 | H17: =G17+1 -> 2 | I17: =H17+1 -> 3 | J17: =I17+1 -> 4 | K17: =J17+1 -> 5 | L17: =K17+1 -> 6 | M17: =L17+1 -> 7 | N17: =M17+1 -> 8 | ... DV17: =DU17+1 -> 120
B18: Limited Partner (Investors) Returns
B19: Total Investors Distributions | D19: =SUM(F19:DV19) -> 1683071.3 | F19: =F47+F62+F77+F84 -> 0 | G19: =G47+G62+G77+G84 -> 0 | H19: =H47+H62+H77+H84 -> 0 | I19: =I47+I62+I77+I84 -> 0 | J19: =J47+J62+J77+J84 -> 0 | K19: =K47+K62+K77+K84 -> 0 | L19: =L47+L62+L77+L84 -> 0 | M19: =M47+M62+M77+M84 -> 0 | ... DV19: =DV47+DV62+DV77+DV84 -> 1491116
B20: Total Investors Contributions | D20: =SUM(F20:DV20) -> 379996.41 | F20: =F42 -> 181905.12 | G20: =G42 -> 912.04528 | H20: =H42 -> 2122.6946 | I20: =I42 -> 4540.1095 | J20: =J42 -> 8923.8948 | K20: =K42 -> 16119.565 | L20: =L42 -> 26758.652 | M20: =M42 -> 36071.436 | ... DV20: =DV42 -> 0
B21: Total Investors Profit | D21: =D19-D20 -> 1303074.9
B22: Investors IRR | D22: =XIRR(F22:DV22,$F$15:$DV$15) -> 0.17829801 | F22: =-F20+F19 -> -181905.12 | G22: =-G20+G19 -> -912.04528 | H22: =-H20+H19 -> -2122.6946 | I22: =-I20+I19 -> -4540.1095 | J22: =-J20+J19 -> -8923.8948 | K22: =-K20+K19 -> -16119.565 | L22: =-L20+L19 -> -26758.652 | M22: =-M20+M19 -> -36071.436 | ... DV22: =-DV20+DV19 -> 1491116
B23: Investors Equity Multiple | D23: =SUMIF(F22:DV22,">0")/-SUMIF($F$22:$DV$22,"<0") -> 4.4291768
B25: Sponsor Returns
B26: Total Sponsor Distributions | D26: =SUM(F26:DV26) -> 337984.71 | F26: =+F48+F63+F78+F85+F32 -> 0 | G26: =+G48+G63+G78+G85+G32 -> 0 | H26: =+H48+H63+H78+H85+H32 -> 0 | I26: =+I48+I63+I78+I85+I32 -> 0 | J26: =+J48+J63+J78+J85+J32 -> 0 | K26: =+K48+K63+K78+K85+K32 -> 0 | L26: =+L48+L63+L78+L85+L32 -> 0 | M26: =+M48+M63+M78+M85+M32 -> 0 | ... DV26: =+DV48+DV63+DV78+DV85+DV32 -> 327881.8
B27: Total Sponsor Contributions | D27: =SUM(F27:DV27) -> 19999.811 | F27: =-(MIN(F34,0)+F42) -> 9573.9539 | G27: =-(MIN(G34,0)+G42) -> 48.002383 | H27: =-(MIN(H34,0)+H42) -> 111.72077 | I27: =-(MIN(I34,0)+I42) -> 238.95313 | J27: =-(MIN(J34,0)+J42) -> 469.67867 | K27: =-(MIN(K34,0)+K42) -> 848.39815 | L27: =-(MIN(L34,0)+L42) -> 1408.3501 | M27: =-(MIN(M34,0)+M42) -> 1898.4967 | ... DV27: =-(MIN(DV34,0)+DV42) -> 0
B28: Total Sponsor Profit | D28: =D26-D27 -> 317984.9
B29: Sponsor IRR | D29: =XIRR(F29:DV29,$F$15:$DV$15) -> 0.34897895 | F29: =-F27+F26 -> -9573.9539 | G29: =-G27+G26 -> -48.002383 | H29: =-H27+H26 -> -111.72077 | I29: =-I27+I26 -> -238.95313 | J29: =-J27+J26 -> -469.67867 | K29: =-K27+K26 -> -848.39815 | L29: =-L27+L26 -> -1408.3501 | M29: =-M27+M26 -> -1898.4967 | ... DV29: =-DV27+DV26 -> 327881.8
B30: Sponsor Equity Multiple | D30: =SUMIF(F29:DV29,">0")/-SUMIF($F$29:$DV$29,"<0") -> 16.899395
B31: Net Cash Flow for Distribution | D31: AUM Fee % | E31: AUM | F31: 0 | G31: =F31+1 -> 1 | H31: =G31+1 -> 2 | I31: =H31+1 -> 3 | J31: =I31+1 -> 4 | K31: =J31+1 -> 5 | L31: =K31+1 -> 6 | M31: =L31+1 -> 7 | N31: =M31+1 -> 8 | ... DV31: =DU31+1 -> 120
B32: General Partner Fees | D32: 0.005 | E32: 0 | F32: 0 | G32: 0 | H32: 0 | I32: 0 | J32: 0 | K32: 0 | L32: 0 | M32: 0 | N32: 0 | O32: 0 | P32: 0 | Q32: 0 | R32: 0 | S32: 0 | T32: 0 | U32: 0 | V32: 0 | W32: 0 | X32: 0 | Y32: 0 | Z32: 0 | AA32: 0 | AB32: 0 | AC32: 0 | AD32: 0 | AE32: 0 | AF32: 0 | AG32: 0 | AH32: 0 | AI32: 0 | AJ32: 0 | AK32: 0 | AL32: 0 | AM32: 0 | AN32: 0 | AO32: 0 | AP32: 0 | AQ32: 0 | AR32: 0 | AS32: 0 | AT32: 0 | AU32: 0 | AV32: 0 | AW32: 0 | AX32: 0 | AY32: 0 | AZ32: 0 | BA32: 0 | BB32: 0 | BC32: 0 | BD32: 0 | BE32: 0 | BF32: 0 | BG32: 0 | BH32: 0 | BI32: 0 | BJ32: 0 | BK32: 0 | BL32: 0 | BM32: 0 | BN32: 0 | BO32: 0 | BP32: 0 | BQ32: 0 | BR32: 0 | BS32: 0 | BT32: 0 | BU32: 0 | BV32: 0 | BW32: 0 | BX32: 0 | BY32: 0 | BZ32: 0 | CA32: 0 | CB32: 0 | CC32: 0 | CD32: 0 | CE32: 0 | CF32: 0 | CG32: 0 | CH32: 0 | CI32: 0 | CJ32: 0 | CK32: 0 | CL32: 0 | CM32: 0 | CN32: 0 | CO32: 0 | CP32: 0 | CQ32: 0 | CR32: 0 | CS32: 0 | CT32: 0 | CU32: 0 | CV32: 0 | CW32: 0 | CX32: 0 | CY32: 0 | CZ32: 0 | DA32: 0 | DB32: 0 | DC32: 0 | DD32: 0 | DE32: 0 | DF32: 0 | DG32: 0 | DH32: 0 | DI32: 0 | DJ32: 0 | DK32: 0 | DL32: 0 | DM32: 0 | DN32: 0 | DO32: 0 | DP32: 0 | DQ32: 0 | DR32: 0 | DS32: 0 | DT32: 0 | DU32: 0 | DV32: 0
B33: Gross Property Levered Before Tax Cash Flow | F33: ='GP-LP Returns'!F29 -> -191479.08 | G33: ='GP-LP Returns'!G29 -> -960.04767 | H33: ='GP-LP Returns'!H29 -> -2234.4154 | I33: ='GP-LP Returns'!I29 -> -4779.0626 | J33: ='GP-LP Returns'!J29 -> -9393.5734 | K33: ='GP-LP Returns'!K29 -> -16967.963 | L33: ='GP-LP Returns'!L29 -> -28167.002 | M33: ='GP-LP Returns'!M29 -> -37969.933 | ... DV33: ='GP-LP Returns'!DV29 -> 1818997.8
B34: Net Property Levered Before Tax Cash Flow | F34: =F33-F32 -> -191479.08 | G34: =G33-G32 -> -960.04767 | H34: =H33-H32 -> -2234.4154 | I34: =I33-I32 -> -4779.0626 | J34: =J33-J32 -> -9393.5734 | K34: =K33-K32 -> -16967.963 | L34: =L33-L32 -> -28167.002 | M34: =M33-M32 -> -37969.933 | ... DV34: =DV33-DV32 -> 1818997.8
B35: Property Levered IRR (Net of Sponsor Fees) | F35: =XIRR($F$34:$DV$34,$F$15:$DV$15) -> 0.19425916
B36: Property Levered Emx (Net of Sponsor Fees) | F36: =SUMIF(F34:DV34,">0")/-SUMIF($F$34:$DV$34,"<0") -> 5.0526877
B38: Hurdle 1
B39: Investors Req'd Return | C39: =E10 -> 0.15 | F39: =F$17 -> 0 | G39: =G$17 -> 1 | H39: =H$17 -> 2 | I39: =I$17 -> 3 | J39: =J$17 -> 4 | K39: =K$17 -> 5 | L39: =L$17 -> 6 | M39: =M$17 -> 7 | ... DV39: =DV$17 -> 120
B40: Beginning Balance (Investors Capital Account) | F40: =E44 -> 0 | G40: =F44 -> 181905.12 | H40: =G44 -> 184948.17 | I40: =H44 -> 189237.52 | J40: =I44 -> 195994.53 | K40: =J44 -> 207214.48 | L40: =K44 -> 225761.55 | M40: =L44 -> 255164.98 | ... DV40: =DU44 -> 1122567.4
B41: Req'd Return by Investors (Pref) | F41: =F40*((1+$C$39)^(1/12)-1) -> 0 | G41: =G40*((1+$C$39)^(1/12)-1) -> 2131.0034 | H41: =H40*((1+$C$39)^(1/12)-1) -> 2166.6525 | I41: =I40*((1+$C$39)^(1/12)-1) -> 2216.9018 | J41: =J40*((1+$C$39)^(1/12)-1) -> 2296.0596 | K41: =K40*((1+$C$39)^(1/12)-1) -> 2427.5005 | L41: =L40*((1+$C$39)^(1/12)-1) -> 2644.7778 | M41: =M40*((1+$C$39)^(1/12)-1) -> 2989.2365 | ... DV41: =DV40*((1+$C$39)^(1/12)-1) -> 13150.783
B42: Contributions from Investors | F42: =-MIN(F34,0)*$C$6 -> 181905.12 | G42: =-MIN(G34,0)*$C$6 -> 912.04528 | H42: =-MIN(H34,0)*$C$6 -> 2122.6946 | I42: =-MIN(I34,0)*$C$6 -> 4540.1095 | J42: =-MIN(J34,0)*$C$6 -> 8923.8948 | K42: =-MIN(K34,0)*$C$6 -> 16119.565 | L42: =-MIN(L34,0)*$C$6 -> 26758.652 | M42: =-MIN(M34,0)*$C$6 -> 36071.436 | ... DV42: =-MIN(DV34,0)*$C$6 -> 0
B43: Distributions to Investors (Hurdle 1) | F43: =MIN(F40+F41,MAX(F34,0)*$I$10) -> 0 | G43: =MIN(G40+G41,MAX(G34,0)*$I$10) -> 0 | H43: =MIN(H40+H41,MAX(H34,0)*$I$10) -> 0 | I43: =MIN(I40+I41,MAX(I34,0)*$I$10) -> 0 | J43: =MIN(J40+J41,MAX(J34,0)*$I$10) -> 0 | K43: =MIN(K40+K41,MAX(K34,0)*$I$10) -> 0 | L43: =MIN(L40+L41,MAX(L34,0)*$I$10) -> 0 | M43: =MIN(M40+M41,MAX(M34,0)*$I$10) -> 0 | ... DV43: =MIN(DV40+DV41,MAX(DV34,0)*$I$10) -> 1135718.1
B44: Ending Balance (Investors Capital Account) | F44: =F40+F41+F42-F43 -> 181905.12 | G44: =G40+G41+G42-G43 -> 184948.17 | H44: =H40+H41+H42-H43 -> 189237.52 | I44: =I40+I41+I42-I43 -> 195994.53 | J44: =J40+J41+J42-J43 -> 207214.48 | K44: =K40+K41+K42-K43 -> 225761.55 | L44: =L40+L41+L42-L43 -> 255164.98 | M44: =M40+M41+M42-M43 -> 294225.65 | ... DV44: =DV40+DV41+DV42-DV43 -> 0
B45: =C39 -> 0.15 | E45: =XIRR(F45:DV45,$F$15:$DV$15) -> 0.14987404 | F45: =-F42+F43 -> -181905.12 | G45: =-G42+G43 -> -912.04528 | H45: =-H42+H43 -> -2122.6946 | I45: =-I42+I43 -> -4540.1095 | J45: =-J42+J43 -> -8923.8948 | K45: =-K42+K43 -> -16119.565 | L45: =-L42+L43 -> -26758.652 | M45: =-M42+M43 -> -36071.436 | ... DV45: =-DV42+DV43 -> 1135718.1
B47: Distribution to Investors | F47: =+F43 -> 0 | G47: =+G43 -> 0 | H47: =+H43 -> 0 | I47: =+I43 -> 0 | J47: =+J43 -> 0 | K47: =+K43 -> 0 | L47: =+L43 -> 0 | M47: =+M43 -> 0 | ... DV47: =+DV43 -> 1135718.1
B48: Distribution to Sponsor | F48: =F47/$I$10*$H$10 -> 0 | G48: =G47/$I$10*$H$10 -> 0 | H48: =H47/$I$10*$H$10 -> 0 | I48: =I47/$I$10*$H$10 -> 0 | J48: =J47/$I$10*$H$10 -> 0 | K48: =K47/$I$10*$H$10 -> 0 | L48: =L47/$I$10*$H$10 -> 0 | M48: =M47/$I$10*$H$10 -> 0 | ... DV48: =DV47/$I$10*$H$10 -> 59774.639
B49: ="Total Distributions ("&B38&")" -> Total Distributions (Hurdle 1) | F49: =SUM(F47:F48) -> 0 | G49: =SUM(G47:G48) -> 0 | H49: =SUM(H47:H48) -> 0 | I49: =SUM(I47:I48) -> 0 | J49: =SUM(J47:J48) -> 0 | K49: =SUM(K47:K48) -> 0 | L49: =SUM(L47:L48) -> 0 | M49: =SUM(M47:M48) -> 0 | ... DV49: =SUM(DV47:DV48) -> 1195492.8
B50: Cash Flow Remaining | F50: =MAX(F34-F49,0) -> 0 | G50: =MAX(G34-G49,0) -> 0 | H50: =MAX(H34-H49,0) -> 0 | I50: =MAX(I34-I49,0) -> 0 | J50: =MAX(J34-J49,0) -> 0 | K50: =MAX(K34-K49,0) -> 0 | L50: =MAX(L34-L49,0) -> 0 | M50: =MAX(M34-M49,0) -> 0 | ... DV50: =MAX(DV34-DV49,0) -> 623505.02
B52: Hurdle 2
B53: Investors Req'd Return | C53: =E11 -> 9.99 | F53: =F$17 -> 0 | G53: =G$17 -> 1 | H53: =H$17 -> 2 | I53: =I$17 -> 3 | J53: =J$17 -> 4 | K53: =K$17 -> 5 | L53: =L$17 -> 6 | M53: =M$17 -> 7 | ... DV53: =DV$17 -> 120
B54: Beginning Balance (Investors Capital Account) | F54: =E59 -> 0 | G54: =F59 -> 181905.12 | H54: =G59 -> 223035.66 | I54: =H59 -> 274470.65 | J54: =I59 -> 339695.12 | K54: =J59 -> 423724.25 | L54: =K59 -> 533527.55 | M54: =L59 -> 678247.01 | ... DV54: =DU59 -> 4.8880068e+15
B55: Req'd Return by Investors | F55: =F54*((1+$C$53)^(1/12)-1) -> 0 | G55: =G54*((1+$C$53)^(1/12)-1) -> 40218.495 | H55: =H54*((1+$C$53)^(1/12)-1) -> 49312.292 | I55: =I54*((1+$C$53)^(1/12)-1) -> 60684.362 | J55: =J54*((1+$C$53)^(1/12)-1) -> 75105.232 | K55: =K54*((1+$C$53)^(1/12)-1) -> 93683.735 | L55: =L54*((1+$C$53)^(1/12)-1) -> 117960.81 | M55: =M54*((1+$C$53)^(1/12)-1) -> 149957.7 | ... DV55: =DV54*((1+$C$53)^(1/12)-1) -> 1.0807187e+15
B56: Contributions from Investors | F56: =F42 -> 181905.12 | G56: =G42 -> 912.04528 | H56: =H42 -> 2122.6946 | I56: =I42 -> 4540.1095 | J56: =J42 -> 8923.8948 | K56: =K42 -> 16119.565 | L56: =L42 -> 26758.652 | M56: =M42 -> 36071.436 | ... DV56: =DV42 -> 0
B57: Prior Distributions | F57: =F47 -> 0 | G57: =G47 -> 0 | H57: =H47 -> 0 | I57: =I47 -> 0 | J57: =J47 -> 0 | K57: =K47 -> 0 | L57: =L47 -> 0 | M57: =M47 -> 0 | ... DV57: =DV47 -> 1135718.1
B58: ="Distributions to Investors "&B52 -> Distributions to Investors Hurdle 2 | F58: =MIN(F54+F55-F57,F50*$I$11) -> 0 | G58: =MIN(G54+G55-G57,G50*$I$11) -> 0 | H58: =MIN(H54+H55-H57,H50*$I$11) -> 0 | I58: =MIN(I54+I55-I57,I50*$I$11) -> 0 | J58: =MIN(J54+J55-J57,J50*$I$11) -> 0 | K58: =MIN(K54+K55-K57,K50*$I$11) -> 0 | L58: =MIN(L54+L55-L57,L50*$I$11) -> 0 | M58: =MIN(M54+M55-M57,M50*$I$11) -> 0 | ... DV58: =MIN(DV54+DV55-DV57,DV50*$I$11) -> 355397.86
B59: Ending Balance (Investors Capital Account) | F59: =F54+F55+F56-F57-F58 -> 181905.12 | G59: =G54+G55+G56-G57-G58 -> 223035.66 | H59: =H54+H55+H56-H57-H58 -> 274470.65 | I59: =I54+I55+I56-I57-I58 -> 339695.12 | J59: =J54+J55+J56-J57-J58 -> 423724.25 | K59: =K54+K55+K56-K57-K58 -> 533527.55 | L59: =L54+L55+L56-L57-L58 -> 678247.01 | M59: =M54+M55+M56-M57-M58 -> 864276.14 | ... DV59: =DV54+DV55+DV56-DV57-DV58 -> 5.9687255e+15
B60: =C53 -> 9.99 | E60: =XIRR(F60:DV60,$F$15:$DV$15) -> 0.17829801 | F60: =-F56+F57+F58 -> -181905.12 | G60: =-G56+G57+G58 -> -912.04528 | H60: =-H56+H57+H58 -> -2122.6946 | I60: =-I56+I57+I58 -> -4540.1095 | J60: =-J56+J57+J58 -> -8923.8948 | K60: =-K56+K57+K58 -> -16119.565 | L60: =-L56+L57+L58 -> -26758.652 | M60: =-M56+M57+M58 -> -36071.436 | ... DV60: =-DV56+DV57+DV58 -> 1491116
B61: .
B62: Distribution to Investors | F62: =F58 -> 0 | G62: =G58 -> 0 | H62: =H58 -> 0 | I62: =I58 -> 0 | J62: =J58 -> 0 | K62: =K58 -> 0 | L62: =L58 -> 0 | M62: =M58 -> 0 | ... DV62: =DV58 -> 355397.86
B63: Distribution to Sponsor | F63: =F62/$I$11*$H$11 -> 0 | G63: =G62/$I$11*$H$11 -> 0 | H63: =H62/$I$11*$H$11 -> 0 | I63: =I62/$I$11*$H$11 -> 0 | J63: =J62/$I$11*$H$11 -> 0 | K63: =K62/$I$11*$H$11 -> 0 | L63: =L62/$I$11*$H$11 -> 0 | M63: =M62/$I$11*$H$11 -> 0 | ... DV63: =DV62/$I$11*$H$11 -> 268107.16
B64: ="Total Distributions ("&B52&")" -> Total Distributions (Hurdle 2) | F64: =SUM(F62:F63) -> 0 | G64: =SUM(G62:G63) -> 0 | H64: =SUM(H62:H63) -> 0 | I64: =SUM(I62:I63) -> 0 | J64: =SUM(J62:J63) -> 0 | K64: =SUM(K62:K63) -> 0 | L64: =SUM(L62:L63) -> 0 | M64: =SUM(M62:M63) -> 0 | ... DV64: =SUM(DV62:DV63) -> 623505.02
B65: Cash Flow Remaining | F65: =MAX(F34-F49-F64,0) -> 0 | G65: =MAX(G34-G49-G64,0) -> 0 | H65: =MAX(H34-H49-H64,0) -> 0 | I65: =MAX(I34-I49-I64,0) -> 0 | J65: =MAX(J34-J49-J64,0) -> 0 | K65: =MAX(K34-K49-K64,0) -> 0 | L65: =MAX(L34-L49-L64,0) -> 0 | M65: =MAX(M34-M49-M64,0) -> 0 | ... DV65: =MAX(DV34-DV49-DV64,0) -> 0
B67: Hurdle 3
B68: Investors Req'd Return | C68: =E12 -> 9.99 | F68: =F$17 -> 0 | G68: =G$17 -> 1 | H68: =H$17 -> 2 | I68: =I$17 -> 3 | J68: =J$17 -> 4 | K68: =K$17 -> 5 | L68: =L$17 -> 6 | M68: =M$17 -> 7 | ... DV68: =DV$17 -> 120
B69: Beginning Balance (Investors Capital Account) | F69: =E74 -> 0 | G69: =F74 -> 181905.12 | H69: =G74 -> 223035.66 | I69: =H74 -> 274470.65 | J69: =I74 -> 339695.12 | K69: =J74 -> 423724.25 | L69: =K74 -> 533527.55 | M69: =L74 -> 678247.01 | ... DV69: =DU74 -> 4.8880068e+15
B70: Req'd Return by Investors | F70: =F69*((1+$C$68)^(1/12)-1) -> 0 | G70: =G69*((1+$C$68)^(1/12)-1) -> 40218.495 | H70: =H69*((1+$C$68)^(1/12)-1) -> 49312.292 | I70: =I69*((1+$C$68)^(1/12)-1) -> 60684.362 | J70: =J69*((1+$C$68)^(1/12)-1) -> 75105.232 | K70: =K69*((1+$C$68)^(1/12)-1) -> 93683.735 | L70: =L69*((1+$C$68)^(1/12)-1) -> 117960.81 | M70: =M69*((1+$C$68)^(1/12)-1) -> 149957.7 | ... DV70: =DV69*((1+$C$68)^(1/12)-1) -> 1.0807187e+15
B71: Contributions from Investors | F71: =F56 -> 181905.12 | G71: =G56 -> 912.04528 | H71: =H56 -> 2122.6946 | I71: =I56 -> 4540.1095 | J71: =J56 -> 8923.8948 | K71: =K56 -> 16119.565 | L71: =L56 -> 26758.652 | M71: =M56 -> 36071.436 | ... DV71: =DV56 -> 0
B72: Prior Distributions | F72: =F47+F62 -> 0 | G72: =G47+G62 -> 0 | H72: =H47+H62 -> 0 | I72: =I47+I62 -> 0 | J72: =J47+J62 -> 0 | K72: =K47+K62 -> 0 | L72: =L47+L62 -> 0 | M72: =M47+M62 -> 0 | ... DV72: =DV47+DV62 -> 1491116
B73: ="Distributions to Investors "&B67 -> Distributions to Investors Hurdle 3 | F73: =MIN(F69+F70-F72,F65*$I$12) -> 0 | G73: =MIN(G69+G70-G72,G65*$I$12) -> 0 | H73: =MIN(H69+H70-H72,H65*$I$12) -> 0 | I73: =MIN(I69+I70-I72,I65*$I$12) -> 0 | J73: =MIN(J69+J70-J72,J65*$I$12) -> 0 | K73: =MIN(K69+K70-K72,K65*$I$12) -> 0 | L73: =MIN(L69+L70-L72,L65*$I$12) -> 0 | M73: =MIN(M69+M70-M72,M65*$I$12) -> 0 | ... DV73: =MIN(DV69+DV70-DV72,DV65*$I$12) -> 0
B74: Ending Balance (Investors Capital Account) | F74: =F69+F70+F71-F72-F73 -> 181905.12 | G74: =G69+G70+G71-G72-G73 -> 223035.66 | H74: =H69+H70+H71-H72-H73 -> 274470.65 | I74: =I69+I70+I71-I72-I73 -> 339695.12 | J74: =J69+J70+J71-J72-J73 -> 423724.25 | K74: =K69+K70+K71-K72-K73 -> 533527.55 | L74: =L69+L70+L71-L72-L73 -> 678247.01 | M74: =M69+M70+M71-M72-M73 -> 864276.14 | ... DV74: =DV69+DV70+DV71-DV72-DV73 -> 5.9687255e+15
B75: =C68 -> 9.99 | E75: =XIRR(F75:DV75,$F$15:$DV$15) -> 0.17829801 | F75: =-F71+F72+F73 -> -181905.12 | G75: =-G71+G72+G73 -> -912.04528 | H75: =-H71+H72+H73 -> -2122.6946 | I75: =-I71+I72+I73 -> -4540.1095 | J75: =-J71+J72+J73 -> -8923.8948 | K75: =-K71+K72+K73 -> -16119.565 | L75: =-L71+L72+L73 -> -26758.652 | M75: =-M71+M72+M73 -> -36071.436 | ... DV75: =-DV71+DV72+DV73 -> 1491116
B76: .
B77: Distribution to Investors | F77: =F73 -> 0 | G77: =G73 -> 0 | H77: =H73 -> 0 | I77: =I73 -> 0 | J77: =J73 -> 0 | K77: =K73 -> 0 | L77: =L73 -> 0 | M77: =M73 -> 0 | ... DV77: =DV73 -> 0
B78: Distribution to Sponsor | F78: =F77/$I$12*$H$12 -> 0 | G78: =G77/$I$12*$H$12 -> 0 | H78: =H77/$I$12*$H$12 -> 0 | I78: =I77/$I$12*$H$12 -> 0 | J78: =J77/$I$12*$H$12 -> 0 | K78: =K77/$I$12*$H$12 -> 0 | L78: =L77/$I$12*$H$12 -> 0 | M78: =M77/$I$12*$H$12 -> 0 | ... DV78: =DV77/$I$12*$H$12 -> 0
B79: ="Total Distributions ("&B67&")" -> Total Distributions (Hurdle 3) | F79: =SUM(F77:F78) -> 0 | G79: =SUM(G77:G78) -> 0 | H79: =SUM(H77:H78) -> 0 | I79: =SUM(I77:I78) -> 0 | J79: =SUM(J77:J78) -> 0 | K79: =SUM(K77:K78) -> 0 | L79: =SUM(L77:L78) -> 0 | M79: =SUM(M77:M78) -> 0 | ... DV79: =SUM(DV77:DV78) -> 0
B80: Cash Flow Remaining | F80: =MAX(F34-F49-F64-F79,0) -> 0 | G80: =MAX(G34-G49-G64-G79,0) -> 0 | H80: =MAX(H34-H49-H64-H79,0) -> 0 | I80: =MAX(I34-I49-I64-I79,0) -> 0 | J80: =MAX(J34-J49-J64-J79,0) -> 0 | K80: =MAX(K34-K49-K64-K79,0) -> 0 | L80: =MAX(L34-L49-L64-L79,0) -> 0 | M80: =MAX(M34-M49-M64-M79,0) -> 0 | ... DV80: =MAX(DV34-DV49-DV64-DV79,0) -> 0
B82: Hurdle 4
B83: Investors Req'd Return | F83: =F$17 -> 0 | G83: =G$17 -> 1 | H83: =H$17 -> 2 | I83: =I$17 -> 3 | J83: =J$17 -> 4 | K83: =K$17 -> 5 | L83: =L$17 -> 6 | M83: =M$17 -> 7 | ... DV83: =DV$17 -> 120
B84: Distribution to Investors | F84: =F80*$I$13 -> 0 | G84: =G80*$I$13 -> 0 | H84: =H80*$I$13 -> 0 | I84: =I80*$I$13 -> 0 | J84: =J80*$I$13 -> 0 | K84: =K80*$I$13 -> 0 | L84: =L80*$I$13 -> 0 | M84: =M80*$I$13 -> 0 | ... DV84: =DV80*$I$13 -> 0
B85: Distribution to Sponsor | F85: =F80*$H$13 -> 0 | G85: =G80*$H$13 -> 0 | H85: =H80*$H$13 -> 0 | I85: =I80*$H$13 -> 0 | J85: =J80*$H$13 -> 0 | K85: =K80*$H$13 -> 0 | L85: =L80*$H$13 -> 0 | M85: =M80*$H$13 -> 0 | ... DV85: =DV80*$H$13 -> 0
B86: ="Total Distributions ("&B82&")" -> Total Distributions (Hurdle 4) | F86: =SUM(F84:F85) -> 0 | G86: =SUM(G84:G85) -> 0 | H86: =SUM(H84:H85) -> 0 | I86: =SUM(I84:I85) -> 0 | J86: =SUM(J84:J85) -> 0 | K86: =SUM(K84:K85) -> 0 | L86: =SUM(L84:L85) -> 0 | M86: =SUM(M84:M85) -> 0 | ... DV86: =SUM(DV84:DV85) -> 0
B87: Cash Flow Remaining | F87: =MAX(F34-F49-F64-F79-F86,0) -> 0 | G87: =MAX(G34-G49-G64-G79-G86,0) -> 0 | H87: =MAX(H34-H49-H64-H79-H86,0) -> 0 | I87: =MAX(I34-I49-I64-I79-I86,0) -> 0 | J87: =MAX(J34-J49-J64-J79-J86,0) -> 0 | K87: =MAX(K34-K49-K64-K79-K86,0) -> 0 | L87: =MAX(L34-L49-L64-L79-L86,0) -> 0 | M87: =MAX(M34-M49-M64-M79-M86,0) -> 0 | ... DV87: =MAX(DV34-DV49-DV64-DV79-DV86,0) -> 0
