Workbook

Sheet Multifamily
B2: MULTIFAMILY (STANDARD) - SUMMARY INCOME STATEMENT
B4: Units | D4: 300
B5: Period Ending | D5: 2019
B6: REVENUE
B7: Rental Revenue | C7: /Unit/Mo. | D7: Amount
B8: Market Rent | C8: =D8/$D$4/12 -> 2090.8169 | D8: =OpSt!W5 -> 7526941 | E8: Total market rent
B9: Loss-to-Lease | C9: =D9/$D$4/12 -> -28.745 | D9: =OpSt!W6 -> -103482 | E9: Difference between market rent and in-place rent
B10: Actual Vacancy & Credit Loss | C10: =D10/$D$4/12 -> -1560.879 | D10: =OpSt!W7 -> -5619164.5 | E10: Vacant space at market rent
B11: Concessions | C11: =D11/$D$4/12 -> -83.289994 | D11: =OpSt!W8 -> -299843.98 | E11: Concessed space (e.g. free rent) at in-place rent
B12: Total Rental Revenue | C12: =SUM(C8:C11) -> 417.90293 | D12: =SUM(D8:D11) -> 1504450.6 | E12: Actual rental Revenue in period
B14: Other Income
B15: RUBS | C15: =D15/$D$4/12 -> 14.169086 | D15: =OpSt!W12 -> 51008.71 | E15: Ratio Utility Billing; a method by which the landlord bills residents for the residents' pro rata share of utility costs
B16: Parking Income | C16: =D16/$D$4/12 -> 16.424708 | D16: =OpSt!W13 -> 59128.95 | E16: Net income derived from charging residents for parking
B17: Storage Income | C17: =D17/$D$4/12 -> 1.4020306 | D17: =OpSt!W14 -> 5047.31 | E17: Net income derived from renting on-site storage units
B18: Other Income | C18: =D18/$D$4/12 -> 45.432122 | D18: =OpSt!W15 -> 163555.64 | E18: Other income including pet rent, application fees, amenities fees, cable and internet income, etc.
B19: Total Other Income | C19: =SUM(C15:C18) -> 77.427947 | D19: =SUM(D15:D18) -> 278740.61 | E19: Actual other income
B21: Effective Gross Revenue
B22: Gross Revenue | C22: =D22/$D$4/12 -> 495.33088 | D22: =+D19+D12 -> 1783191.2 | E22: Sum of other income and rental revenue
B23: General Vacancy and Credit Loss | C23: =D23/$D$4/12 -> 0 | D23: 0 | E23: Additional vacancy taken on gross Revenue to account for unforeseen vacancy or credit loss; used in forecasted periods
B24: Total Effective Gross Revenue | C24: =SUM(C22:C23) -> 495.33088 | D24: =+D22+D23 -> 1783191.2 | E24: Gross revenue after adjusting for general vacancy and credit loss; commonly referred to as EGR
B25: OPERATING EXPENSES
B26: Operating Expenses | C26: /Unit/Yr.
B27: Repairs and Maintenance | C27: =D27/$D$4 -> 212.21687 | D27: =OpSt!W24 -> 63665.06 | E27: Expenses related to maintaining the general condition of the common areas
B28: Security | C28: =D28/$D$4 -> 6.8253333 | D28: =OpSt!W25 -> 2047.6 | E28: Expenses related to securing the premises
B29: Landscaping | C29: =D29/$D$4 -> 1.4557667 | D29: =OpSt!W26 -> 436.73 | E29: Expenses related to maintaining the landscaping in the common areas
B30: Administrative | C30: =D30/$D$4 -> 230.62193 | D30: =OpSt!W27 -> 69186.58 | E30: Expenses related to the administration of the property
B31: Property Management | C31: =D31/$D$4 -> 377.03333 | D31: =OpSt!W28 -> 113110 | E31: Fee paid to professional property management; generally a percentage of EGR
B32: Advertising/Marketing | C32: =D32/$D$4 -> 596.79393 | D32: =OpSt!W29 -> 179038.18 | E32: Expenses related to marketing and advertising the property; may include locator fees
B33: Payroll | C33: =D33/$D$4 -> 1729.1561 | D33: =OpSt!W30 -> 518746.83 | E33: Expenses related to salary and benefits for property management personnel
B34: Utilities | C34: =D34/$D$4 -> 682.67163 | D34: =OpSt!W31 -> 204801.49 | E34: Electricity, gas, water, sewer, internet, and other utilities; generally only related to the common areas
B35: Property Insurance | C35: =D35/$D$4 -> 39.869933 | D35: =OpSt!W32 -> 11960.98 | E35: Property and casualty insurance
B36: Real Estate Taxes | C36: =D36/$D$4 -> 85.340433 | D36: =OpSt!W33 -> 25602.13 | E36: Real estate taxes levied by the local government
B37: Total Operating Expenses | C37: =SUM(C27:C36) -> 3961.9853 | D37: =SUM(D27:D36) -> 1188595.6 | E37: Sum of operating expenses; commonly referred to as OpEx
B39: NET OPERATING INCOME | D39: =+D24-D37 -> 594595.59 | E39: Effective gross income minus total operating expenses; commonly referred to as NOI
B40: CAPITAL EXPENDITURES
B41: Capital Improvements | C41: =D41/$D$4 -> 0 | D41: =OpSt!W38 -> 0 | E41: Expenditures with a depreciable life greater than one year (e.g. roof repair, structural repairs, etc)
B42: Capital Reserve | C42: =D42/$D$4 -> 0 | D42: =OpSt!W39 -> 0 | E42: Amount set aside for future capital improvements and/or leasing costs
B43: Total Capital Expenditures | C43: =SUM(C41:C42) -> 0 | D43: =SUM(D41:D42) -> 0
B45: CASH FLOW FROM OPERATIONS | D45: =+D39-D43 -> 594595.59 | E45: Net operating income minus total capital expenditures; commonly referred to as CFO
B47: Debt Service | E47: Payment to lender(s); payment is principal + interest unless loan is interest-only; commonly referred to as DS
B49: CASH FLOW AFTER FINANCING | D49: =+D45-D47 -> 594595.59 | E49: Cash flow from operations minus debt service and any ground lease payments, if applicable; commonly referred to as CFAF

Sheet OpSt
A1: Jellystone Apartments | B1: Jellystone Apartments
A2: Statement (12 months) | B2: STATEMENT (12 MONTHS)
A3: Period = Dec 2018-Oct 2019 | B3: Period = Dec 2018 through Oct 2019; Book = Accrual
C4: 43435 | D4: 43466 | E4: 43497 | F4: 43525 | G4: 43556 | H4: 43586 | I4: 43617 | J4: 43647 | K4: 43678 | L4: 43709 | M4: 43739 | N4: Total | O4: T1 | P4: T3 | Q4: T6 | R4: Label | U4: Label | V4: Rental Revenue | W4: Amount | X4: T1 | Y4: T3 | Z4: T6 | AA4: Error Check
A5: 4100-0010 | B5: Gross Potential Mkt Rent | C5: 678055 | D5: 678055 | E5: 678055 | F5: 686597 | G5: 686597 | H5: 686597 | I5: 686597 | J5: 686597 | K5: 686597 | L5: 686597 | M5: 686597 | N5: 7526941 | O5: =IF($N$5="","",M5*12) -> 8239164 | P5: =IF($N$5="","",SUM(K5:M5)*4) -> 8239164 | Q5: =IF($N$5="","",SUM(H5:M5)*2) -> 8239164 | R5: RENT | U5: RENT | V5: Market Rent | W5: =SUMIF($R$5:$R$263,$U5,N$5:N$263) -> 7526941 | X5: =SUMIF($R$5:$R$263,$U5,O$5:O$263) -> 8239164 | Y5: =SUMIF($R$5:$R$263,$U5,P$5:P$263) -> 8239164 | Z5: =SUMIF($R$5:$R$263,$U5,Q$5:Q$263) -> 8239164
A6: 4100-0030 | B6: Loss to Lease | C6: -2590 | D6: -1158 | E6: -2041 | F6: -4581 | G6: -5800 | H6: -7372 | I6: -9334 | J6: -13830 | K6: -16809 | L6: -19517 | M6: -20450 | N6: -103482 | O6: =IF($N$5="","",M6*12) -> -245400 | P6: =IF($N$5="","",SUM(K6:M6)*4) -> -227104 | Q6: =IF($N$5="","",SUM(H6:M6)*2) -> -174624 | R6: L2L | U6: L2L | V6: Loss-to-Lease | W6: =SUMIF($R$5:$R$263,$U6,N$5:N$263) -> -103482 | X6: =SUMIF($R$5:$R$263,$U6,O$5:O$263) -> -245400 | Y6: =SUMIF($R$5:$R$263,$U6,P$5:P$263) -> -227104 | Z6: =SUMIF($R$5:$R$263,$U6,Q$5:Q$263) -> -174624
A7: 4100-0055 | B7: Actual Potential Rent | C7: 675465 | D7: 676897 | E7: 676014 | F7: 682016 | G7: 680797 | H7: 679225 | I7: 677263 | J7: 672767 | K7: 669788 | L7: 667080 | M7: 666147 | N7: 7423459 | O7: =IF($N$5="","",M7*12) -> 7993764 | P7: =IF($N$5="","",SUM(K7:M7)*4) -> 8012060 | Q7: =IF($N$5="","",SUM(H7:M7)*2) -> 8064540 | U7: ACTVAC | V7: Actual Vacancy & Credit Loss | W7: =SUMIF($R$5:$R$263,$U7,N$5:N$263) -> -5619164.5 | X7: =SUMIF($R$5:$R$263,$U7,O$5:O$263) -> -3051387.5 | Y7: =SUMIF($R$5:$R$263,$U7,P$5:P$263) -> -3719700.2 | Z7: =SUMIF($R$5:$R$263,$U7,Q$5:Q$263) -> -4847017.4
A8: 4100-0060 | B8: Vacancy Loss | C8: -670605 | D8: -657652.11 | E8: -640847.17 | F8: -612927.63 | G8: -575232.23 | H8: -540221.89 | I8: -491103.12 | J8: -425980.43 | K8: -363138.66 | L8: -296985.82 | M8: -246702.19 | N8: -5521396.2 | O8: =IF($N$5="","",M8*12) -> -2960426.3 | P8: =IF($N$5="","",SUM(K8:M8)*4) -> -3627306.7 | Q8: =IF($N$5="","",SUM(H8:M8)*2) -> -4728264.2 | R8: ACTVAC | U8: CONC | V8: Concessions | W8: =SUMIF($R$5:$R$263,$U8,N$5:N$263) -> -299843.98 | X8: =SUMIF($R$5:$R$263,$U8,O$5:O$263) -> -486204 | Y8: =SUMIF($R$5:$R$263,$U8,P$5:P$263) -> -490800.48 | Z8: =SUMIF($R$5:$R$263,$U8,Q$5:Q$263) -> -434467.14
B9: Non Rev Producing Units | C9: -4860 | D9: -8154.35 | E9: -1297.5 | F9: -8422.5 | G9: -9602.7 | H9: -10115.1 | I9: -10115.1 | J9: -7580.1 | K9: -7580.1 | L9: -7580.1 | M9: -7580.1 | N9: -82887.65 | O9: =IF($N$5="","",M9*12) -> -90961.2 | P9: =IF($N$5="","",SUM(K9:M9)*4) -> -90961.2 | Q9: =IF($N$5="","",SUM(H9:M9)*2) -> -101101.2 | R9: ACTVAC | V9: Total Rental Revenue | W9: =SUM(W5:W8) -> 1504450.6 | X9: =SUM(X5:X8) -> 4456172.5 | Y9: =SUM(Y5:Y8) -> 3801559.3 | Z9: =SUM(Z5:Z8) -> 2783055.4
A10: 4100-0100 | B10: Employee Units | C10: -1350 | D10: 0 | E10: -7125 | F10: 0 | G10: 0 | H10: 0 | I10: 0 | J10: 0 | K10: 0 | L10: 0 | M10: 0 | N10: -8475 | O10: =IF($N$5="","",M10*12) -> 0 | P10: =IF($N$5="","",SUM(K10:M10)*4) -> 0 | Q10: =IF($N$5="","",SUM(H10:M10)*2) -> 0 | R10: ACTVAC
A11: 4100-0150 | B11: Rental Concessions | C11: 0 | D11: -10222.5 | E11: -20272.5 | F11: -21453.75 | G11: -30661.66 | H11: -25113.66 | I11: -43684.02 | J11: -25735.77 | K11: -37623.5 | L11: -44559.62 | M11: -40517 | N11: -299843.98 | O11: =IF($N$5="","",M11*12) -> -486204 | P11: =IF($N$5="","",SUM(K11:M11)*4) -> -490800.48 | Q11: =IF($N$5="","",SUM(H11:M11)*2) -> -434467.14 | R11: CONC | V11: Other Income
A12: 4100-0240 | B12: Other Month Rent/Past Due | C12: 0 | D12: 51.61 | E12: 0 | F12: 2439.56 | G12: -70.72 | H12: 159.8 | I12: 0 | J12: -12.4 | K12: 0 | L12: 358.08 | M12: 0 | N12: 2925.93 | O12: =IF($N$5="","",M12*12) -> 0 | P12: =IF($N$5="","",SUM(K12:M12)*4) -> 1432.32 | Q12: =IF($N$5="","",SUM(H12:M12)*2) -> 1010.96 | R12: ACTVAC | U12: RUBS | V12: RUBS | W12: =SUMIF($R$5:$R$263,$U12,N$5:N$263) -> 51008.71 | X12: =SUMIF($R$5:$R$263,$U12,O$5:O$263) -> 167265.48 | Y12: =SUMIF($R$5:$R$263,$U12,P$5:P$263) -> 130625.68 | Z12: =SUMIF($R$5:$R$263,$U12,Q$5:Q$263) -> 95777.4
A13: 4100-0320 | B13: Bad Debt Expense | C13: 0 | D13: 0 | E13: 0 | F13: 0 | G13: 0 | H13: -6769.04 | I13: -1846.29 | J13: 0 | K13: 0 | L13: -716.16 | M13: 0 | N13: -9331.49 | O13: =IF($N$5="","",M13*12) -> 0 | P13: =IF($N$5="","",SUM(K13:M13)*4) -> -2864.64 | Q13: =IF($N$5="","",SUM(H13:M13)*2) -> -18662.98 | R13: ACTVAC | U13: PARK | V13: Parking Income | W13: =SUMIF($R$5:$R$263,$U13,N$5:N$263) -> 59128.95 | X13: =SUMIF($R$5:$R$263,$U13,O$5:O$263) -> 179659.44 | Y13: =SUMIF($R$5:$R$263,$U13,P$5:P$263) -> 152795.48 | Z13: =SUMIF($R$5:$R$263,$U13,Q$5:Q$263) -> 107948.34
A14: 4199-9999 | B14: Total Gross Potential Mkt Rent | C14: -1350 | D14: 919.65 | E14: 6471.83 | F14: 41651.68 | G14: 65229.69 | H14: 97165.11 | I14: 130514.47 | J14: 213458.3 | K14: 261445.74 | L14: 317596.38 | M14: 371347.71 | N14: 1504450.6 | O14: =IF($N$5="","",M14*12) -> 4456172.5 | P14: =IF($N$5="","",SUM(K14:M14)*4) -> 3801559.3 | Q14: =IF($N$5="","",SUM(H14:M14)*2) -> 2783055.4 | U14: STORAGE | V14: Storage Income | W14: =SUMIF($R$5:$R$263,$U14,N$5:N$263) -> 5047.31 | X14: =SUMIF($R$5:$R$263,$U14,O$5:O$263) -> 15772.08 | Y14: =SUMIF($R$5:$R$263,$U14,P$5:P$263) -> 13499.68 | Z14: =SUMIF($R$5:$R$263,$U14,Q$5:Q$263) -> 9430.66
O15: =IF($N$5="","",M15*12) -> 0 | P15: =IF($N$5="","",SUM(K15:M15)*4) -> 0 | Q15: =IF($N$5="","",SUM(H15:M15)*2) -> 0 | U15: OI | V15: Other Income | W15: =SUMIF($R$5:$R$263,$U15,N$5:N$263) -> 163555.64 | X15: =SUMIF($R$5:$R$263,$U15,O$5:O$263) -> 329736.48 | Y15: =SUMIF($R$5:$R$263,$U15,P$5:P$263) -> 281372.48 | Z15: =SUMIF($R$5:$R$263,$U15,Q$5:Q$263) -> 230061.32
A16: 4200-0000 | B16: Other Income | O16: =IF($N$5="","",M16*12) -> 0 | P16: =IF($N$5="","",SUM(K16:M16)*4) -> 0 | Q16: =IF($N$5="","",SUM(H16:M16)*2) -> 0 | V16: Total Other Income | W16: =SUM(W12:W15) -> 278740.61 | X16: =SUM(X12:X15) -> 692433.48 | Y16: =SUM(Y12:Y15) -> 578293.32 | Z16: =SUM(Z12:Z15) -> 443217.72
O17: =IF($N$5="","",M17*12) -> 0 | P17: =IF($N$5="","",SUM(K17:M17)*4) -> 0 | Q17: =IF($N$5="","",SUM(H17:M17)*2) -> 0
A18: 4200-0001 | B18: Other Income | O18: =IF($N$5="","",M18*12) -> 0 | P18: =IF($N$5="","",SUM(K18:M18)*4) -> 0 | Q18: =IF($N$5="","",SUM(H18:M18)*2) -> 0 | V18: Effective Gross Revenue
A19: 4200-0050 | B19: Resident Fees | C19: 0 | D19: 3600 | E19: 10000 | F19: 10100 | G19: 6040 | H19: 6000 | I19: 5300 | J19: 5100 | K19: 8200 | L19: 3200 | M19: 3000 | N19: 60540 | O19: =IF($N$5="","",M19*12) -> 36000 | P19: =IF($N$5="","",SUM(K19:M19)*4) -> 57600 | Q19: =IF($N$5="","",SUM(H19:M19)*2) -> 61600 | R19: OI | V19: Gross Revenue | W19: =+W16+W9 -> 1783191.2 | X19: =+X16+X9 -> 5148606 | Y19: =+Y16+Y9 -> 4379852.6 | Z19: =+Z16+Z9 -> 3226273.1
A20: 4200-0060 | B20: Application Fees | C20: 120 | D20: 2185 | E20: 2370 | F20: 3835 | G20: 2720 | H20: 3900 | I20: 4260 | J20: 4080 | K20: 4275 | L20: 3405 | M20: 3240 | N20: 34390 | O20: =IF($N$5="","",M20*12) -> 38880 | P20: =IF($N$5="","",SUM(K20:M20)*4) -> 43680 | Q20: =IF($N$5="","",SUM(H20:M20)*2) -> 46320 | R20: OI | V20: General Vacancy and Credit Loss | W20: 0 | X20: 0 | Y20: 0 | Z20: 0
A21: 4200-0110 | B21: Garage Income | C21: 0 | D21: 304.84 | E21: 637.49 | F21: 1021.48 | G21: 3190.97 | H21: 3596.13 | I21: 4731.93 | J21: 7447.24 | K21: 10364.51 | L21: 12862.74 | M21: 14971.62 | N21: 59128.95 | O21: =IF($N$5="","",M21*12) -> 179659.44 | P21: =IF($N$5="","",SUM(K21:M21)*4) -> 152795.48 | Q21: =IF($N$5="","",SUM(H21:M21)*2) -> 107948.34 | R21: PARK | V21: Total Effective Gross Revenue | W21: =+W19+W20 -> 1783191.2 | X21: =+X19+X20 -> 5148606 | Y21: =+Y19+Y20 -> 4379852.6 | Z21: =+Z19+Z20 -> 3226273.1 | AA21: =N52 -> 1783191.2 | AB21: =O52 -> 5148606 | AC21: =P52 -> 4379852.6 | AD21: =Q52 -> 3226273.1
A22: 4200-0160 | B22: Storage Income | C22: 0 | D22: 0 | E22: 32.14 | F22: 87.1 | G22: 224.84 | H22: 317.02 | I22: 300 | J22: 723.39 | K22: 1012.9 | L22: 1059.78 | M22: 1314.34 | N22: 5071.51 | O22: =IF($N$5="","",M22*12) -> 15772.08 | P22: =IF($N$5="","",SUM(K22:M22)*4) -> 13548.08 | Q22: =IF($N$5="","",SUM(H22:M22)*2) -> 9454.86 | R22: STORAGE | V22: OPERATING EXPENSES
A23: 4200-0170 | B23: Storage Concession | C23: 0 | D23: 0 | E23: 0 | F23: -12.1 | G23: 0 | H23: 0 | I23: 0 | J23: 0 | K23: 0 | L23: -12.1 | M23: 0 | N23: -24.2 | O23: =IF($N$5="","",M23*12) -> 0 | P23: =IF($N$5="","",SUM(K23:M23)*4) -> -48.4 | Q23: =IF($N$5="","",SUM(H23:M23)*2) -> -24.2 | R23: STORAGE | V23: Operating Expenses
A24: 4200-0180 | B24: Damage Fees | C24: 0 | D24: 0 | E24: 150 | F24: 0 | G24: 0 | H24: 540 | I24: 0 | J24: 110 | K24: 839 | L24: -147 | M24: 3767.77 | N24: 5259.77 | O24: =IF($N$5="","",M24*12) -> 45213.24 | P24: =IF($N$5="","",SUM(K24:M24)*4) -> 17839.08 | Q24: =IF($N$5="","",SUM(H24:M24)*2) -> 10219.54 | R24: OI | U24: RM | V24: Repairs and Maintenance | W24: =SUMIF($R$5:$R$263,$U24,N$5:N$263) -> 63665.06 | X24: =SUMIF($R$5:$R$263,$U24,O$5:O$263) -> 137846.4 | Y24: =SUMIF($R$5:$R$263,$U24,P$5:P$263) -> 149230.92 | Z24: =SUMIF($R$5:$R$263,$U24,Q$5:Q$263) -> 112242.98
A25: 4200-0230 | B25: Termination Fees | C25: 0 | D25: 0 | E25: 0 | F25: 0 | G25: 0 | H25: 0 | I25: 0 | J25: 0 | K25: 3700 | L25: -1430 | M25: 10243.09 | N25: 12513.09 | O25: =IF($N$5="","",M25*12) -> 122917.08 | P25: =IF($N$5="","",SUM(K25:M25)*4) -> 50052.36 | Q25: =IF($N$5="","",SUM(H25:M25)*2) -> 25026.18 | R25: OI | U25: SEC | V25: Security | W25: =SUMIF($R$5:$R$263,$U25,N$5:N$263) -> 2047.6 | X25: =SUMIF($R$5:$R$263,$U25,O$5:O$263) -> 0 | Y25: =SUMIF($R$5:$R$263,$U25,P$5:P$263) -> 2094 | Z25: =SUMIF($R$5:$R$263,$U25,Q$5:Q$263) -> 4005.2
A26: 4200-0270 | B26: MTM Premium | C26: 0 | D26: 0 | E26: 0 | F26: 0 | G26: 0 | H26: 0 | I26: 0 | J26: 0 | K26: 0 | L26: 760 | M26: 241.94 | N26: 1001.94 | O26: =IF($N$5="","",M26*12) -> 2903.28 | P26: =IF($N$5="","",SUM(K26:M26)*4) -> 4007.76 | Q26: =IF($N$5="","",SUM(H26:M26)*2) -> 2003.88 | R26: OI | U26: LAND | V26: Landscaping | W26: =SUMIF($R$5:$R$263,$U26,N$5:N$263) -> 436.73 | X26: =SUMIF($R$5:$R$263,$U26,O$5:O$263) -> 5240.76 | Y26: =SUMIF($R$5:$R$263,$U26,P$5:P$263) -> 1746.92 | Z26: =SUMIF($R$5:$R$263,$U26,Q$5:Q$263) -> 873.46
A27: 4200-0280 | B27: Short Term Lease Premium | C27: 0 | D27: 0 | E27: 0 | F27: 0 | G27: 0 | H27: 0 | I27: 0 | J27: 0 | K27: 0 | L27: 0 | M27: 541.94 | N27: 541.94 | O27: =IF($N$5="","",M27*12) -> 6503.28 | P27: =IF($N$5="","",SUM(K27:M27)*4) -> 2167.76 | Q27: =IF($N$5="","",SUM(H27:M27)*2) -> 1083.88 | R27: OI | U27: ADMIN | V27: Administrative | W27: =SUMIF($R$5:$R$263,$U27,N$5:N$263) -> 69186.58 | X27: =SUMIF($R$5:$R$263,$U27,O$5:O$263) -> 72994.68 | Y27: =SUMIF($R$5:$R$263,$U27,P$5:P$263) -> 79125.2 | Z27: =SUMIF($R$5:$R$263,$U27,Q$5:Q$263) -> 79953.58
A28: 4200-0300 | B28: Transfer Fees | C28: 0 | D28: 0 | E28: 0 | F28: 0 | G28: 0 | H28: 0 | I28: 0 | J28: 0 | K28: 0 | L28: 500 | M28: 0 | N28: 500 | O28: =IF($N$5="","",M28*12) -> 0 | P28: =IF($N$5="","",SUM(K28:M28)*4) -> 2000 | Q28: =IF($N$5="","",SUM(H28:M28)*2) -> 1000 | R28: OI | U28: PM | V28: Property Management | W28: =SUMIF($R$5:$R$263,$U28,N$5:N$263) -> 113110 | X28: =SUMIF($R$5:$R$263,$U28,O$5:O$263) -> 147612 | Y28: =SUMIF($R$5:$R$263,$U28,P$5:P$263) -> 132440 | Z28: =SUMIF($R$5:$R$263,$U28,Q$5:Q$263) -> 126220
A29: 4200-0340 | B29: Pet Rent | C29: 0 | D29: 635.48 | E29: 1025.54 | F29: 1126.5 | G29: 1911.46 | H29: 2029.36 | I29: 3394.5 | J29: 4597.42 | K29: 4795.16 | L29: 4860.46 | M29: 4889.7 | N29: 29265.58 | O29: =IF($N$5="","",M29*12) -> 58676.4 | P29: =IF($N$5="","",SUM(K29:M29)*4) -> 58181.28 | Q29: =IF($N$5="","",SUM(H29:M29)*2) -> 49133.2 | R29: OI | U29: MARK | V29: Advertising/Marketing | W29: =SUMIF($R$5:$R$263,$U29,N$5:N$263) -> 179038.18 | X29: =SUMIF($R$5:$R$263,$U29,O$5:O$263) -> 181175.28 | Y29: =SUMIF($R$5:$R$263,$U29,P$5:P$263) -> 194429.72 | Z29: =SUMIF($R$5:$R$263,$U29,Q$5:Q$263) -> 238100.82
A30: 4200-0360 | B30: Amenity Fees | C30: 150 | D30: 20 | E30: 670 | F30: 700 | G30: 706 | H30: -158.33 | I30: 1098 | J30: 662 | K30: -150 | L30: 1030.6 | M30: 1534.9 | N30: 6263.17 | O30: =IF($N$5="","",M30*12) -> 18418.8 | P30: =IF($N$5="","",SUM(K30:M30)*4) -> 9662 | Q30: =IF($N$5="","",SUM(H30:M30)*2) -> 8034.34 | R30: OI | U30: P | V30: Payroll | W30: =SUMIF($R$5:$R$263,$U30,N$5:N$263) -> 518746.83 | X30: =SUMIF($R$5:$R$263,$U30,O$5:O$263) -> 521369.4 | Y30: =SUMIF($R$5:$R$263,$U30,P$5:P$263) -> 739625.16 | Z30: =SUMIF($R$5:$R$263,$U30,Q$5:Q$263) -> 691009.9
A31: 4200-0370 | B31: Late Fees | C31: 0 | D31: 0 | E31: 0 | F31: 0 | G31: 0 | H31: 0 | I31: 0 | J31: 0 | K31: 503.8 | L31: 0 | M31: -503.8 | N31: 0 | O31: =IF($N$5="","",M31*12) -> -6045.6 | P31: =IF($N$5="","",SUM(K31:M31)*4) -> 0 | Q31: =IF($N$5="","",SUM(H31:M31)*2) -> 0 | R31: OI | U31: U | V31: Utilities | W31: =SUMIF($R$5:$R$263,$U31,N$5:N$263) -> 204801.49 | X31: =SUMIF($R$5:$R$263,$U31,O$5:O$263) -> 410916.36 | Y31: =SUMIF($R$5:$R$263,$U31,P$5:P$263) -> 270746.96 | Z31: =SUMIF($R$5:$R$263,$U31,Q$5:Q$263) -> 334543.72
A32: 4200-0380 | B32: Administrative Fees | C32: 200 | D32: 0 | E32: 0 | F32: 0 | G32: 0 | H32: 0 | I32: 0 | J32: 0 | K32: 0 | L32: 0 | M32: 0 | N32: 200 | O32: =IF($N$5="","",M32*12) -> 0 | P32: =IF($N$5="","",SUM(K32:M32)*4) -> 0 | Q32: =IF($N$5="","",SUM(H32:M32)*2) -> 0 | R32: OI | U32: I | V32: Property Insurance | W32: =SUMIF($R$5:$R$263,$U32,N$5:N$263) -> 11960.98 | X32: =SUMIF($R$5:$R$263,$U32,O$5:O$263) -> 0 | Y32: =SUMIF($R$5:$R$263,$U32,P$5:P$263) -> 11739.44 | Z32: =SUMIF($R$5:$R$263,$U32,Q$5:Q$263) -> 14832
A33: 4200-0400 | B33: Forfeited Deposit | C33: 0 | D33: 0 | E33: 0 | F33: 0 | G33: 0 | H33: 2000 | I33: 0 | J33: 0 | K33: 0 | L33: 0 | M33: 0 | N33: 2000 | O33: =IF($N$5="","",M33*12) -> 0 | P33: =IF($N$5="","",SUM(K33:M33)*4) -> 0 | Q33: =IF($N$5="","",SUM(H33:M33)*2) -> 4000 | R33: OI | U33: RET | V33: Real Estate Taxes | W33: =SUMIF($R$5:$R$263,$U33,N$5:N$263) -> 25602.13 | X33: =SUMIF($R$5:$R$263,$U33,O$5:O$263) -> 0 | Y33: =SUMIF($R$5:$R$263,$U33,P$5:P$263) -> 40050.96 | Z33: =SUMIF($R$5:$R$263,$U33,Q$5:Q$263) -> 39681.92
A34: 4299-9999 | B34: Total Other Income | C34: 470 | D34: 6745.32 | E34: 14885.17 | F34: 16857.98 | G34: 14793.27 | H34: 18224.18 | I34: 19084.43 | J34: 22720.05 | K34: 33540.37 | L34: 26089.48 | M34: 43241.5 | N34: 216651.75 | O34: =IF($N$5="","",M34*12) -> 518898 | P34: =IF($N$5="","",SUM(K34:M34)*4) -> 411485.4 | Q34: =IF($N$5="","",SUM(H34:M34)*2) -> 325800.02 | V34: Total Operating Expenses | W34: =SUM(W24:W33) -> 1188595.6 | X34: =SUM(X24:X33) -> 1477154.9 | Y34: =SUM(Y24:Y33) -> 1621229.3 | Z34: =SUM(Z24:Z33) -> 1641463.6 | AA34: =N261 -> 1188595.6 | AB34: =O261 -> 1477154.9 | AC34: =P261 -> 1621229.3 | AD34: =Q261 -> 1641463.6
O35: =IF($N$5="","",M35*12) -> 0 | P35: =IF($N$5="","",SUM(K35:M35)*4) -> 0 | Q35: =IF($N$5="","",SUM(H35:M35)*2) -> 0
A36: 4300-0000 | B36: Miscellaneous Income | O36: =IF($N$5="","",M36*12) -> 0 | P36: =IF($N$5="","",SUM(K36:M36)*4) -> 0 | Q36: =IF($N$5="","",SUM(H36:M36)*2) -> 0 | V36: NET OPERATING INCOME | W36: =+W21-W34 -> 594595.59 | X36: =+X21-X34 -> 3671451.1 | Y36: =+Y21-Y34 -> 2758623.4 | Z36: =+Z21-Z34 -> 1584809.6 | AA36: =N263 -> 594595.59 | AB36: =O263 -> 3671451.1 | AC36: =P263 -> 2758623.4 | AD36: =Q263 -> 1584809.6
A37: 4300-0010 | B37: Miscellaneous Income | C37: 0 | D37: 0 | E37: 0 | F37: 0 | G37: 260 | H37: 201.07 | I37: 146.04 | J37: 244.69 | K37: 400 | L37: 20 | M37: 0 | N37: 1271.8 | O37: =IF($N$5="","",M37*12) -> 0 | P37: =IF($N$5="","",SUM(K37:M37)*4) -> 1680 | Q37: =IF($N$5="","",SUM(H37:M37)*2) -> 2023.6
A38: 4300-0030 | B38: Clubhouse Income | C38: 0 | D38: 0 | E38: 0 | F38: 0 | G38: 0 | H38: 0 | I38: 0 | J38: 1200 | K38: 125 | L38: 0 | M38: 0 | N38: 1325 | O38: =IF($N$5="","",M38*12) -> 0 | P38: =IF($N$5="","",SUM(K38:M38)*4) -> 500 | Q38: =IF($N$5="","",SUM(H38:M38)*2) -> 2650
A39: 4300-0120 | B39: Cable Income | C39: 0 | D39: 0 | E39: 0 | F39: 0 | G39: 0 | H39: -17.21 | I39: 0 | J39: 0 | K39: 290.73 | L39: 0 | M39: 625 | N39: 898.52 | O39: =IF($N$5="","",M39*12) -> 7500 | P39: =IF($N$5="","",SUM(K39:M39)*4) -> 3662.92 | Q39: =IF($N$5="","",SUM(H39:M39)*2) -> 1797.04
A40: 4300-0130 | B40: Collection Income | C40: 0 | D40: 0 | E40: 0 | F40: 0 | G40: 0 | H40: 0 | I40: 0 | J40: 0 | K40: 2092.42 | L40: 5594.91 | M40: -102.5 | N40: 7584.83 | O40: =IF($N$5="","",M40*12) -> -1230 | P40: =IF($N$5="","",SUM(K40:M40)*4) -> 30339.32 | Q40: =IF($N$5="","",SUM(H40:M40)*2) -> 15169.66
A41: 4300-0150 | B41: Bad Debt Income | C41: 0 | D41: 0 | E41: 0 | F41: 0 | G41: 0 | H41: 0 | I41: 0 | J41: 0 | K41: 6250 | L41: -6250 | M41: 0 | N41: 0 | O41: =IF($N$5="","",M41*12) -> 0 | P41: =IF($N$5="","",SUM(K41:M41)*4) -> 0 | Q41: =IF($N$5="","",SUM(H41:M41)*2) -> 0
A42: 4399-9999 | B42: Total Miscellaneous Income | C42: 0 | D42: 0 | E42: 0 | F42: 0 | G42: 260 | H42: 183.86 | I42: 146.04 | J42: 1444.69 | K42: 9158.15 | L42: -635.09 | M42: 522.5 | N42: 11080.15 | O42: =IF($N$5="","",M42*12) -> 6270 | P42: =IF($N$5="","",SUM(K42:M42)*4) -> 36182.24 | Q42: =IF($N$5="","",SUM(H42:M42)*2) -> 21640.3 | R42: OI
O43: =IF($N$5="","",M43*12) -> 0 | P43: =IF($N$5="","",SUM(K43:M43)*4) -> 0 | Q43: =IF($N$5="","",SUM(H43:M43)*2) -> 0
A44: 4700-0000 | B44: Utility Reimbursement Income | O44: =IF($N$5="","",M44*12) -> 0 | P44: =IF($N$5="","",SUM(K44:M44)*4) -> 0 | Q44: =IF($N$5="","",SUM(H44:M44)*2) -> 0
A45: 4700-0010 | B45: Reimbursed Electricity | C45: 0 | D45: 68 | E45: 148 | F45: 928 | G45: 1976.01 | H45: 3648.92 | I45: 4855.23 | J45: 6486.03 | K45: 7905.12 | L45: 11089.61 | M45: 13938.79 | N45: 51043.71 | O45: =IF($N$5="","",M45*12) -> 167265.48 | P45: =IF($N$5="","",SUM(K45:M45)*4) -> 131734.08 | Q45: =IF($N$5="","",SUM(H45:M45)*2) -> 95847.4
A46: 4700-0050 | B46: Reimbursed Trash Removal | C46: 0 | D46: 0 | E46: 0 | F46: 0 | G46: 0 | H46: 0 | I46: 0 | J46: 0 | K46: 0 | L46: -35 | M46: 0 | N46: -35 | O46: =IF($N$5="","",M46*12) -> 0 | P46: =IF($N$5="","",SUM(K46:M46)*4) -> -140 | Q46: =IF($N$5="","",SUM(H46:M46)*2) -> -70
A47: 4700-0100 | B47: Contract Utility Admin | C47: 0 | D47: 0 | E47: 0 | F47: 0 | G47: 0 | H47: 0 | I47: -143.85 | J47: 385.95 | K47: -760.6 | L47: 518.5 | M47: 0 | N47: 0 | O47: =IF($N$5="","",M47*12) -> 0 | P47: =IF($N$5="","",SUM(K47:M47)*4) -> -968.4 | Q47: =IF($N$5="","",SUM(H47:M47)*2) -> 0
A48: 4799-9999 | B48: Total Utility Reimbursement Income | C48: 0 | D48: 68 | E48: 148 | F48: 928 | G48: 1976.01 | H48: 3648.92 | I48: 4711.38 | J48: 6871.98 | K48: 7144.52 | L48: 11573.11 | M48: 13938.79 | N48: 51008.71 | O48: =IF($N$5="","",M48*12) -> 167265.48 | P48: =IF($N$5="","",SUM(K48:M48)*4) -> 130625.68 | Q48: =IF($N$5="","",SUM(H48:M48)*2) -> 95777.4 | R48: RUBS
O49: =IF($N$5="","",M49*12) -> 0 | P49: =IF($N$5="","",SUM(K49:M49)*4) -> 0 | Q49: =IF($N$5="","",SUM(H49:M49)*2) -> 0
A50: 4999-9998 | B50: Total Other Income | C50: 470 | D50: 6813.32 | E50: 15033.17 | F50: 17785.98 | G50: 17029.28 | H50: 22056.96 | I50: 23941.85 | J50: 31036.72 | K50: 49843.04 | L50: 37027.5 | M50: 57702.79 | N50: 278740.61 | O50: =IF($N$5="","",M50*12) -> 692433.48 | P50: =IF($N$5="","",SUM(K50:M50)*4) -> 578293.32 | Q50: =IF($N$5="","",SUM(H50:M50)*2) -> 443217.72
O51: =IF($N$5="","",M51*12) -> 0 | P51: =IF($N$5="","",SUM(K51:M51)*4) -> 0 | Q51: =IF($N$5="","",SUM(H51:M51)*2) -> 0
A52: 4999-9999 | B52: TOTAL INCOME | C52: -880 | D52: 7732.97 | E52: 21505 | F52: 59437.66 | G52: 82258.97 | H52: 119222.07 | I52: 154456.32 | J52: 244495.02 | K52: 311288.78 | L52: 354623.88 | M52: 429050.5 | N52: 1783191.2 | O52: =IF($N$5="","",M52*12) -> 5148606 | P52: =IF($N$5="","",SUM(K52:M52)*4) -> 4379852.6 | Q52: =IF($N$5="","",SUM(H52:M52)*2) -> 3226273.1
O53: =IF($N$5="","",M53*12) -> 0 | P53: =IF($N$5="","",SUM(K53:M53)*4) -> 0 | Q53: =IF($N$5="","",SUM(H53:M53)*2) -> 0
A54: 5000-0000 | B54: OPERATING EXPENSES | O54: =IF($N$5="","",M54*12) -> 0 | P54: =IF($N$5="","",SUM(K54:M54)*4) -> 0 | Q54: =IF($N$5="","",SUM(H54:M54)*2) -> 0
O55: =IF($N$5="","",M55*12) -> 0 | P55: =IF($N$5="","",SUM(K55:M55)*4) -> 0 | Q55: =IF($N$5="","",SUM(H55:M55)*2) -> 0
A56: 5100-0000 | B56: Payroll | O56: =IF($N$5="","",M56*12) -> 0 | P56: =IF($N$5="","",SUM(K56:M56)*4) -> 0 | Q56: =IF($N$5="","",SUM(H56:M56)*2) -> 0
O57: =IF($N$5="","",M57*12) -> 0 | P57: =IF($N$5="","",SUM(K57:M57)*4) -> 0 | Q57: =IF($N$5="","",SUM(H57:M57)*2) -> 0
A58: 5100-1000 | B58: Administrative Payroll | O58: =IF($N$5="","",M58*12) -> 0 | P58: =IF($N$5="","",SUM(K58:M58)*4) -> 0 | Q58: =IF($N$5="","",SUM(H58:M58)*2) -> 0
A59: 5100-1010 | B59: Regional Manager | C59: 0 | D59: 0 | E59: 567.7 | F59: 567.7 | G59: 0 | H59: 0 | I59: 0 | J59: 0 | K59: 0 | L59: 0 | M59: 0 | N59: 1135.4 | O59: =IF($N$5="","",M59*12) -> 0 | P59: =IF($N$5="","",SUM(K59:M59)*4) -> 0 | Q59: =IF($N$5="","",SUM(H59:M59)*2) -> 0
A60: 5100-1030 | B60: On-Site Manager | C60: 2570.93 | D60: 7617.99 | E60: 5447.76 | F60: 5519.76 | G60: 5663.76 | H60: 5946.45 | I60: 5718.38 | J60: 5796.38 | K60: 5841.38 | L60: 5818.38 | M60: 6166.65 | N60: 62107.82 | O60: =IF($N$5="","",M60*12) -> 73999.8 | P60: =IF($N$5="","",SUM(K60:M60)*4) -> 71305.64 | Q60: =IF($N$5="","",SUM(H60:M60)*2) -> 70575.24
A61: 5100-1040 | B61: Assistant Manager | C61: 0 | D61: 0 | E61: 0 | F61: 4964.3 | G61: 3172.8 | H61: 5474.83 | I61: 3551.01 | J61: 3654.63 | K61: 3550.8 | L61: 3596.85 | M61: 3499.7 | N61: 31464.92 | O61: =IF($N$5="","",M61*12) -> 41996.4 | P61: =IF($N$5="","",SUM(K61:M61)*4) -> 42589.4 | Q61: =IF($N$5="","",SUM(H61:M61)*2) -> 46655.64
A62: 5100-1100 | B62: Other Admin Payroll | C62: 0 | D62: 0 | E62: 1007.71 | F62: 0 | G62: 0 | H62: 28.66 | I62: 0 | J62: 0 | K62: 0 | L62: 0 | M62: 0 | N62: 1036.37 | O62: =IF($N$5="","",M62*12) -> 0 | P62: =IF($N$5="","",SUM(K62:M62)*4) -> 0 | Q62: =IF($N$5="","",SUM(H62:M62)*2) -> 57.32
A63: 5100-1999 | B63: Total Administrative Payroll | C63: 2570.93 | D63: 7617.99 | E63: 7023.17 | F63: 11051.76 | G63: 8836.56 | H63: 11449.94 | I63: 9269.39 | J63: 9451.01 | K63: 9392.18 | L63: 9415.23 | M63: 9666.35 | N63: 95744.51 | O63: =IF($N$5="","",M63*12) -> 115996.2 | P63: =IF($N$5="","",SUM(K63:M63)*4) -> 113895.04 | Q63: =IF($N$5="","",SUM(H63:M63)*2) -> 117288.2
O64: =IF($N$5="","",M64*12) -> 0 | P64: =IF($N$5="","",SUM(K64:M64)*4) -> 0 | Q64: =IF($N$5="","",SUM(H64:M64)*2) -> 0
A65: 5100-2000 | B65: Leasing Payroll | O65: =IF($N$5="","",M65*12) -> 0 | P65: =IF($N$5="","",SUM(K65:M65)*4) -> 0 | Q65: =IF($N$5="","",SUM(H65:M65)*2) -> 0
A66: 5100-2010 | B66: Leasing Manager | C66: 0 | D66: 0 | E66: 0 | F66: 0 | G66: 0 | H66: 3809.6 | I66: 3399.71 | J66: 1682.82 | K66: 2973.31 | L66: 3000.29 | M66: 2892.65 | N66: 17758.38 | O66: =IF($N$5="","",M66*12) -> 34711.8 | P66: =IF($N$5="","",SUM(K66:M66)*4) -> 35465 | Q66: =IF($N$5="","",SUM(H66:M66)*2) -> 35516.76
A67: 5100-2020 | B67: Leasing Consultant | C67: 4815.55 | D67: 6790.48 | E67: 5005.97 | F67: 5478.7 | G67: 5731.53 | H67: 3562.48 | I67: 4584.72 | J67: 6754.59 | K67: 5385.06 | L67: 5248.63 | M67: 5502.44 | N67: 58860.15 | O67: =IF($N$5="","",M67*12) -> 66029.28 | P67: =IF($N$5="","",SUM(K67:M67)*4) -> 64544.52 | Q67: =IF($N$5="","",SUM(H67:M67)*2) -> 62075.84
A68: 5100-2999 | B68: Total Leasing Payroll | C68: 4815.55 | D68: 6790.48 | E68: 5005.97 | F68: 5478.7 | G68: 5731.53 | H68: 7372.08 | I68: 7984.43 | J68: 8437.41 | K68: 8358.37 | L68: 8248.92 | M68: 8395.09 | N68: 76618.53 | O68: =IF($N$5="","",M68*12) -> 100741.08 | P68: =IF($N$5="","",SUM(K68:M68)*4) -> 100009.52 | Q68: =IF($N$5="","",SUM(H68:M68)*2) -> 97592.6
O69: =IF($N$5="","",M69*12) -> 0 | P69: =IF($N$5="","",SUM(K69:M69)*4) -> 0 | Q69: =IF($N$5="","",SUM(H69:M69)*2) -> 0
A70: 5100-3000 | B70: Maintenance Payroll | O70: =IF($N$5="","",M70*12) -> 0 | P70: =IF($N$5="","",SUM(K70:M70)*4) -> 0 | Q70: =IF($N$5="","",SUM(H70:M70)*2) -> 0
A71: 5100-3020 | B71: Sr. Maintenance Manager | C71: 0 | D71: 7888.68 | E71: 5768.27 | F71: 5874.16 | G71: 6043.05 | H71: 6339 | I71: 6287.34 | J71: 4711.47 | K71: 5795 | L71: 8026.89 | M71: 6099.64 | N71: 62833.5 | O71: =IF($N$5="","",M71*12) -> 73195.68 | P71: =IF($N$5="","",SUM(K71:M71)*4) -> 79686.12 | Q71: =IF($N$5="","",SUM(H71:M71)*2) -> 74518.68
A72: 5100-3030 | B72: Maintenance Manager | C72: 370.26 | D72: 0 | E72: 0 | F72: 0 | G72: 0 | H72: 0 | I72: 0 | J72: 0 | K72: 0 | L72: 0 | M72: 0 | N72: 370.26 | O72: =IF($N$5="","",M72*12) -> 0 | P72: =IF($N$5="","",SUM(K72:M72)*4) -> 0 | Q72: =IF($N$5="","",SUM(H72:M72)*2) -> 0
A73: 5100-3040 | B73: Asst. Maintenance Manager | C73: 0 | D73: 0 | E73: 0 | F73: 0 | G73: 304.95 | H73: 290.89 | I73: 0 | J73: 0 | K73: 0 | L73: 0 | M73: 0 | N73: 595.84 | O73: =IF($N$5="","",M73*12) -> 0 | P73: =IF($N$5="","",SUM(K73:M73)*4) -> 0 | Q73: =IF($N$5="","",SUM(H73:M73)*2) -> 581.78
A74: 5100-3050 | B74: Maintenance Person | C74: -369.16 | D74: 3184.13 | E74: 2411.49 | F74: 2630.22 | G74: 2634.69 | H74: 3006.82 | I74: 2785.18 | J74: 4532.02 | K74: 6152.46 | L74: 6409.49 | M74: 6174.74 | N74: 39552.08 | O74: =IF($N$5="","",M74*12) -> 74096.88 | P74: =IF($N$5="","",SUM(K74:M74)*4) -> 74946.76 | Q74: =IF($N$5="","",SUM(H74:M74)*2) -> 58121.42
A75: 5100-3999 | B75: Total Maintenance Payroll | C75: 1.1 | D75: 11072.81 | E75: 8179.76 | F75: 8504.38 | G75: 8982.69 | H75: 9636.71 | I75: 9072.52 | J75: 9243.49 | K75: 11947.46 | L75: 14436.38 | M75: 12274.38 | N75: 103351.68 | O75: =IF($N$5="","",M75*12) -> 147292.56 | P75: =IF($N$5="","",SUM(K75:M75)*4) -> 154632.88 | Q75: =IF($N$5="","",SUM(H75:M75)*2) -> 133221.88
O76: =IF($N$5="","",M76*12) -> 0 | P76: =IF($N$5="","",SUM(K76:M76)*4) -> 0 | Q76: =IF($N$5="","",SUM(H76:M76)*2) -> 0
A77: 5100-6000 | B77: Marketing Payroll | O77: =IF($N$5="","",M77*12) -> 0 | P77: =IF($N$5="","",SUM(K77:M77)*4) -> 0 | Q77: =IF($N$5="","",SUM(H77:M77)*2) -> 0
A78: 5100-6010 | B78: Marketing | C78: 0 | D78: 0 | E78: 212.42 | F78: 0 | G78: 0 | H78: 0 | I78: 0 | J78: 0 | K78: -212.42 | L78: 0 | M78: 0 | N78: 0 | O78: =IF($N$5="","",M78*12) -> 0 | P78: =IF($N$5="","",SUM(K78:M78)*4) -> -849.68 | Q78: =IF($N$5="","",SUM(H78:M78)*2) -> -424.84
A79: 5100-6999 | B79: Total Marketing Payroll | C79: 0 | D79: 0 | E79: 212.42 | F79: 0 | G79: 0 | H79: 0 | I79: 0 | J79: 0 | K79: -212.42 | L79: 0 | M79: 0 | N79: 0 | O79: =IF($N$5="","",M79*12) -> 0 | P79: =IF($N$5="","",SUM(K79:M79)*4) -> -849.68 | Q79: =IF($N$5="","",SUM(H79:M79)*2) -> -424.84
O80: =IF($N$5="","",M80*12) -> 0 | P80: =IF($N$5="","",SUM(K80:M80)*4) -> 0 | Q80: =IF($N$5="","",SUM(H80:M80)*2) -> 0
A81: 5200-0000 | B81: Overtime | O81: =IF($N$5="","",M81*12) -> 0 | P81: =IF($N$5="","",SUM(K81:M81)*4) -> 0 | Q81: =IF($N$5="","",SUM(H81:M81)*2) -> 0
A82: 5200-0010 | B82: Overtime - Administrative | C82: 0 | D82: 0 | E82: 70.61 | F82: 217.37 | G82: 0 | H82: 161.22 | I82: 193.35 | J82: 97.55 | K82: 137.31 | L82: 116.63 | M82: 156.89 | N82: 1150.93 | O82: =IF($N$5="","",M82*12) -> 1882.68 | P82: =IF($N$5="","",SUM(K82:M82)*4) -> 1643.32 | Q82: =IF($N$5="","",SUM(H82:M82)*2) -> 1725.9
A83: 5200-0020 | B83: Overtime - Leasing | C83: 62.12 | D83: 0 | E83: 9.12 | F83: 1.13 | G83: 203.42 | H83: 221.11 | I83: 398.36 | J83: 448.97 | K83: 181.99 | L83: 85.71 | M83: 131.96 | N83: 1743.89 | O83: =IF($N$5="","",M83*12) -> 1583.52 | P83: =IF($N$5="","",SUM(K83:M83)*4) -> 1598.64 | Q83: =IF($N$5="","",SUM(H83:M83)*2) -> 2936.2
A84: 5200-0030 | B84: Overtime - Maintenance | C84: 2.31 | D84: 38.54 | E84: 209.83 | F84: 176.78 | G84: 144.99 | H84: 698.86 | I84: 394.21 | J84: 208.51 | K84: 474.87 | L84: 269.69 | M84: 457.37 | N84: 3075.96 | O84: =IF($N$5="","",M84*12) -> 5488.44 | P84: =IF($N$5="","",SUM(K84:M84)*4) -> 4807.72 | Q84: =IF($N$5="","",SUM(H84:M84)*2) -> 5007.02
A85: 5249-9999 | B85: Total Overtime | C85: 64.43 | D85: 38.54 | E85: 289.56 | F85: 395.28 | G85: 348.41 | H85: 1081.19 | I85: 985.92 | J85: 755.03 | K85: 794.17 | L85: 472.03 | M85: 746.22 | N85: 5970.78 | O85: =IF($N$5="","",M85*12) -> 8954.64 | P85: =IF($N$5="","",SUM(K85:M85)*4) -> 8049.68 | Q85: =IF($N$5="","",SUM(H85:M85)*2) -> 9669.12
O86: =IF($N$5="","",M86*12) -> 0 | P86: =IF($N$5="","",SUM(K86:M86)*4) -> 0 | Q86: =IF($N$5="","",SUM(H86:M86)*2) -> 0
A87: 5250-0000 | B87: Bonus | O87: =IF($N$5="","",M87*12) -> 0 | P87: =IF($N$5="","",SUM(K87:M87)*4) -> 0 | Q87: =IF($N$5="","",SUM(H87:M87)*2) -> 0
A88: 5250-0010 | B88: Bonus - Administrative - Monthly | C88: 0 | D88: 1395 | E88: 1267 | F88: 5900.32 | G88: 2914 | H88: 9884.15 | I88: 12087.47 | J88: 13616.44 | K88: 9500.4 | L88: 10453.28 | M88: 3633.83 | N88: 70651.89 | O88: =IF($N$5="","",M88*12) -> 43605.96 | P88: =IF($N$5="","",SUM(K88:M88)*4) -> 94350.04 | Q88: =IF($N$5="","",SUM(H88:M88)*2) -> 118351.14
A89: 5250-0020 | B89: Bonus - Administrative - Commissions | C89: 8270.89 | D89: 0 | E89: 0 | F89: 550 | G89: 0 | H89: -550 | I89: 0 | J89: 0 | K89: 0 | L89: 0 | M89: 0 | N89: 8270.89 | O89: =IF($N$5="","",M89*12) -> 0 | P89: =IF($N$5="","",SUM(K89:M89)*4) -> 0 | Q89: =IF($N$5="","",SUM(H89:M89)*2) -> -1100
A90: 5250-0030 | B90: Bonus - Administrative - Quarterly | C90: 0 | D90: 0 | E90: 4250 | F90: 507.4 | G90: 0 | H90: 5636.66 | I90: 0 | J90: 0 | K90: 6477.39 | L90: 0 | M90: 0 | N90: 16871.45 | O90: =IF($N$5="","",M90*12) -> 0 | P90: =IF($N$5="","",SUM(K90:M90)*4) -> 25909.56 | Q90: =IF($N$5="","",SUM(H90:M90)*2) -> 24228.1
A91: 5250-0060 | B91: Bonus - Leasing - Commissions | C91: 0 | D91: 0 | E91: 0 | F91: 3056.34 | G91: 5078.26 | H91: 1112.44 | I91: 0 | J91: 0 | K91: 0 | L91: 19263 | M91: 0 | N91: 28510.04 | O91: =IF($N$5="","",M91*12) -> 0 | P91: =IF($N$5="","",SUM(K91:M91)*4) -> 77052 | Q91: =IF($N$5="","",SUM(H91:M91)*2) -> 40750.88
A92: 5250-0070 | B92: Bonus - Leasing - Quarterly | C92: 0 | D92: 0 | E92: 780 | F92: 0 | G92: 0 | H92: 1716 | I92: 0 | J92: 0 | K92: 2332.39 | L92: 0 | M92: 0 | N92: 4828.39 | O92: =IF($N$5="","",M92*12) -> 0 | P92: =IF($N$5="","",SUM(K92:M92)*4) -> 9329.56 | Q92: =IF($N$5="","",SUM(H92:M92)*2) -> 8096.78
A93: 5250-0090 | B93: Bonus - Maintenance - Monthly | C93: 91.67 | D93: 0 | E93: 0 | F93: 225 | G93: 625 | H93: 91.67 | I93: 0 | J93: 0 | K93: 0 | L93: 1923 | M93: 0 | N93: 2956.34 | O93: =IF($N$5="","",M93*12) -> 0 | P93: =IF($N$5="","",SUM(K93:M93)*4) -> 7692 | Q93: =IF($N$5="","",SUM(H93:M93)*2) -> 4029.34
A94: 5250-0110 | B94: Bonus - Maintenance - Quarterly | C94: 0 | D94: 0 | E94: 3720.6 | F94: 0 | G94: 0 | H94: 3640 | I94: 0 | J94: 0 | K94: 3676.4 | L94: 0 | M94: 0 | N94: 11037 | O94: =IF($N$5="","",M94*12) -> 0 | P94: =IF($N$5="","",SUM(K94:M94)*4) -> 14705.6 | Q94: =IF($N$5="","",SUM(H94:M94)*2) -> 14632.8
A95: 5299-9999 | B95: Total Bonus | C95: 8362.56 | D95: 1395 | E95: 10017.6 | F95: 10239.06 | G95: 8617.26 | H95: 21530.92 | I95: 12087.47 | J95: 13616.44 | K95: 21986.58 | L95: 31639.28 | M95: 3633.83 | N95: 143126 | O95: =IF($N$5="","",M95*12) -> 43605.96 | P95: =IF($N$5="","",SUM(K95:M95)*4) -> 229038.76 | Q95: =IF($N$5="","",SUM(H95:M95)*2) -> 208989.04
O96: =IF($N$5="","",M96*12) -> 0 | P96: =IF($N$5="","",SUM(K96:M96)*4) -> 0 | Q96: =IF($N$5="","",SUM(H96:M96)*2) -> 0
A97: 5400-0000 | B97: Check Processing Fees | O97: =IF($N$5="","",M97*12) -> 0 | P97: =IF($N$5="","",SUM(K97:M97)*4) -> 0 | Q97: =IF($N$5="","",SUM(H97:M97)*2) -> 0
A98: 5400-0010 | B98: Ck Processing - Administrative | C98: 43.12 | D98: 56 | E98: 64.76 | F98: 120.76 | G98: 56 | H98: 168 | I98: 112 | J98: 112 | K98: 112 | L98: 112 | M98: 112 | N98: 1068.64 | O98: =IF($N$5="","",M98*12) -> 1344 | P98: =IF($N$5="","",SUM(K98:M98)*4) -> 1344 | Q98: =IF($N$5="","",SUM(H98:M98)*2) -> 1456
A99: 5400-0020 | B99: Ck Processing - Leasing | C99: 114.52 | D99: 112 | E99: 112 | F99: 112 | G99: 168 | H99: 177.52 | I99: 168 | J99: 168 | K99: 168 | L99: 168 | M99: 168 | N99: 1636.04 | O99: =IF($N$5="","",M99*12) -> 2016 | P99: =IF($N$5="","",SUM(K99:M99)*4) -> 2016 | Q99: =IF($N$5="","",SUM(H99:M99)*2) -> 2035.04
A100: 5400-0030 | B100: Ck Processing - Maintenance | C100: 49.84 | D100: 112 | E100: 112 | F100: 112 | G100: 56 | H100: 175 | I100: 112 | J100: 140 | K100: 168 | L100: 168 | M100: 168 | N100: 1372.84 | O100: =IF($N$5="","",M100*12) -> 2016 | P100: =IF($N$5="","",SUM(K100:M100)*4) -> 2016 | Q100: =IF($N$5="","",SUM(H100:M100)*2) -> 1862
...
