Workbook

Sheet Office
B2: OFFICE - SUMMARY INCOME STATEMENT
B4: Net Rentable Area | D4: 200000
B5: Period Ending | D5: 2019
B6: REVENUE
B7: Rental Revenue | C7: PSF | D7: Amount
B8: Potential Base Rent | C8: =+D8/$D$4 -> 12.53235 | D8: ='Office Detailed OpSt'!H4 -> 2506470 | E8: Sum of all contract rent plus vacant space at market rent; concessed space at contract rate
B9: Actual Vacancy | C9: =+D9/$D$4 -> 0 | D9: ='Office Detailed OpSt'!H5 -> 0 | E9: Vacant space at market rent
B10: Actual Credit Loss | C10: =+D10/$D$4 -> 0 | D10: ='Office Detailed OpSt'!H6 -> 0 | E10: Loss due to tenants' nonpayment of rental obligations
B11: Concessions | C11: =+D11/$D$4 -> 0 | D11: ='Office Detailed OpSt'!H7 -> 0 | E11: Concessed space (e.g. free rent) at contract rate
B12: Total Rental Revenue | C12: =+D12/$D$4 -> 12.53235 | D12: =SUM(D8:D11) -> 2506470 | E12: Actual rental Revenue in period
B14: Other Income
B15: CAM Reimbursement | C15: =+D15/$D$4 -> 1.933925 | D15: ='Office Detailed OpSt'!H11 -> 386785 | E15: Actual tenant reimbursement of common area maintenance (security, repairs and maintenance, landscaping, etc)
B16: Utility Reimbursement | C16: =+D16/$D$4 -> 0.301915 | D16: ='Office Detailed OpSt'!H12 -> 60383 | E16: Actual tenant reimbursement of utility expenses
B17: Real Estate Tax Reimbursement | C17: =+D17/$D$4 -> 0 | D17: ='Office Detailed OpSt'!H13 -> 0 | E17: Actual tenant reimbursement of real estate taxes
B18: Parking Income | C18: =+D18/$D$4 -> 0.096 | D18: ='Office Detailed OpSt'!H14 -> 19200 | E18: Actual income from parking
B19: Other Income | C19: =+D19/$D$4 -> 0.047465 | D19: ='Office Detailed OpSt'!H15 -> 9493 | E19: Actual other income; such as telecom income, amenity fees, conference room rental, fitness center, misc income, etc
B20: Total Other Income | C20: =+D20/$D$4 -> 2.379305 | D20: =SUM(D15:D19) -> 475861 | E20: Actual other Revenue
B22: Effective Gross Revenue
B23: Gross Revenue | C23: =+D23/$D$4 -> 14.911655 | D23: =+D20+D12 -> 2982331 | E23: Sum of other income and rental revenue
B24: General Vacancy and Credit Loss | C24: =+D24/$D$4 -> 0 | D24: 0 | E24: Additional vacancy taken on gross Revenue to account for unforeseen vacancy or credit loss; used in forecasted periods
B25: Total Effective Gross Revenue | C25: =+D25/$D$4 -> 14.911655 | D25: =+D23+D24 -> 2982331 | E25: Gross revenue after adjusting for general vacancy and credit loss; commonly referred to as EGR
B26: OPERATING EXPENSES
B27: Reimbursable Operating Expenses | E27: Operating expenses incurred by landlord that tenants have agreed to reimburse
B28: Variable Operating Expenses | E28: Expenses that fluctuate based on occupancy
B29: Cleaning | C29: =+D29/$D$4 -> 0.586825 | D29: ='Office Detailed OpSt'!H25 -> 117365 | E29: Expenses related to cleaning the common areas
B30: Repairs and Maintenance | C30: =+D30/$D$4 -> 1.311595 | D30: ='Office Detailed OpSt'!H26 -> 262319 | E30: Expenses related to maintaining the general condition of the common areas
B31: Security | C31: =+D31/$D$4 -> 0.96415 | D31: ='Office Detailed OpSt'!H27 -> 192830 | E31: Expenses related to securing the premises
B32: Landscaping | C32: =+D32/$D$4 -> 0.16409 | D32: ='Office Detailed OpSt'!H28 -> 32818 | E32: Expenses related to maintaining the landscaping in the common areas
B33: Utilities | C33: =+D33/$D$4 -> 0.92587 | D33: ='Office Detailed OpSt'!H29 -> 185174 | E33: Electricity, gas, water, sewer, internet, and other utilities related to the common areas
B34: Payroll | C34: =+D34/$D$4 -> 0.932475 | D34: ='Office Detailed OpSt'!H30 -> 186495
B35: Property Management | C35: =+D35/$D$4 -> 0 | D35: ='Office Detailed OpSt'!H31 -> 0 | E35: Fee paid to professional property management
B36: Marketing | C36: =+D36/$D$4 -> 0 | D36: ='Office Detailed OpSt'!H32 -> 0 | E36: Costs related to marketing the property; does NOT include leasing commissions
B37: Other Variable Expenses | C37: =+D37/$D$4 -> 1.426885 | D37: ='Office Detailed OpSt'!H33 -> 285377 | E37: Other variable expenses that are reimbursable
B38: Total Variable Expenses | C38: =+D38/$D$4 -> 6.31189 | D38: =SUM(D29:D37) -> 1262378
B39: Fixed Expenses | E39: Expense that are fixed regardless of occupancy
B40: Real Estate Taxes | C40: =+D40/$D$4 -> 6.245525 | D40: ='Office Detailed OpSt'!H36 -> 1249105 | E40: Real estate taxes levied by the local government
B41: Insurance | C41: =+D41/$D$4 -> 0.03832 | D41: ='Office Detailed OpSt'!H37 -> 7664 | E41: Property and casualty insurance
B42: Total Fixed Operating Expenses | C42: =+D42/$D$4 -> 6.283845 | D42: =SUM(D40:D41) -> 1256769
B44: Total Reimbursable OpEx | C44: =+D44/$D$4 -> 12.595735 | D44: =+D42+D38 -> 2519147 | E44: Total operating expenses that are reimbursable
B46: Non-Reimbursable Operating Expenses | E46: Operating expenses incurred by landlord that tenants are not obligated to reimburse
B47: Variable Operating Expenses | E47: Expenses that fluctuate based on occupancy
B48: Cleaning | C48: =+D48/$D$4 -> 0 | D48: ='Office Detailed OpSt'!H44 -> 0 | E48: Expenses related to cleaning the common areas
B49: Repairs and Maintenance | C49: =+D49/$D$4 -> 0 | D49: ='Office Detailed OpSt'!H45 -> 0 | E49: Expenses related to maintaining the general condition of the common areas
B50: Security | C50: =+D50/$D$4 -> 0 | D50: ='Office Detailed OpSt'!H46 -> 0 | E50: Expenses related to securing the premises
B51: Landscaping | C51: =+D51/$D$4 -> 0 | D51: ='Office Detailed OpSt'!H47 -> 0 | E51: Expenses related to maintaining the landscaping in the common areas
B52: Utilities | C52: =+D52/$D$4 -> 0 | D52: ='Office Detailed OpSt'!H48 -> 0 | E52: Electricity, gas, water, sewer, internet, and other utilities related to the common areas
B53: Payroll | C53: =+D53/$D$4 -> 0 | D53: ='Office Detailed OpSt'!H49 -> 0
B54: Marketing | C54: =+D54/$D$4 -> 0.000575 | D54: ='Office Detailed OpSt'!H50 -> 115 | E54: Costs related to marketing the property; does NOT include leasing commissions
B55: Other Variable Expenses | C55: =+D55/$D$4 -> 0.163635 | D55: ='Office Detailed OpSt'!H51 -> 32727 | E55: Other variable expenses that are not reimbursable
B56: Total Variable Expenses | C56: =+D56/$D$4 -> 0.16421 | D56: =SUM(D48:D55) -> 32842
B57: Fixed Expenses | E57: Expense that are fixed regardless of occupancy
B58: Real Estate Taxes | C58: =+D58/$D$4 -> 0 | D58: 0 | E58: Real estate taxes levied by the local government
B59: Insurance | C59: =+D59/$D$4 -> 0 | D59: ='Office Detailed OpSt'!H55 -> 0 | E59: Property and casualty insurance
B60: Total Fixed Operating Expenses | C60: =+D60/$D$4 -> 0 | D60: =SUM(D58:D59) -> 0
B62: Total Non-Reimbursable OpEx | C62: =+D62/$D$4 -> 0.16421 | D62: =+D60+D56 -> 32842 | E62: Total operating expenses that are not reimbursable
B64: Total Operating Expenses | C64: =+D64/$D$4 -> 12.759945 | D64: =D62+D44 -> 2551989 | E64: Sum of reimbursable and non-reimbursable operating expenses; commonly referred to as OpEx
B66: NET OPERATING INCOME | C66: =+D66/$D$4 -> 2.1517099 | D66: =+D25-D64 -> 430341.97 | E66: Effective gross income minus total operating expenses; commonly referred to as NOI
B67: CAPITAL EXPENDITURES
B68: Leasing Commissions | C68: =+D68/$D$4 -> 0 | D68: 0 | E68: Commissions paid to leasing brokers
B69: Tenant Improvements | C69: =+D69/$D$4 -> 0 | D69: 0 | E69: Allowances offered to tenants upon signing a new lease or lease renewal; used to improve the tenant's physical space
B70: Capital Improvements | C70: =+D70/$D$4 -> 0 | D70: 0 | E70: Expenditures with a depreciable life greater than one year (e.g. roof repair, structural repairs, etc)
B71: Capital Reserve | C71: =+D71/$D$4 -> 0 | D71: 0 | E71: Amount set aside for future capital improvements and/or leasing costs
B72: Total Capital Expenditures | C72: =+D72/$D$4 -> 0 | D72: =SUM(D68:D71) -> 0
B74: CASH FLOW FROM OPERATIONS | D74: =+D66-D72 -> 430341.97 | E74: Net operating income minus total capital expenditures; commonly referred to as CFO
B76: DEBT SERVICE | D76: 0 | E76: Payment to lender(s) - either principal + interest, or interest-only; commonly referred to as DS
B78: CASH FLOW AFTER FINANCING | D78: =+D74-D76 -> 430341.97 | E78: Cash flow from operations minus debt service and any ground lease payments, if applicable; commonly referred to as CFAF

Sheet Office Detailed OpSt
A1: Office Park
A2: YTD Operating Statement
C3: EOY 2019 | D3: Label | F3: Label | G3: Rental Revenue | H3: Amount | I3: Error Check
A4: Income | F4: RENT | G4: Potential Base Rent | H4: =SUMIF($D$4:$D$90,$F4,$C$4:$C$90) -> 2506470
A5: Rental Income | F5: VAC | G5: Actual Vacancy | H5: =SUMIF($D$4:$D$90,$F5,$C$4:$C$90) -> 0
A6: Base Rent | C6: 2325327 | D6: RENT | F6: CREDIT | G6: Actual Credit Loss | H6: =SUMIF($D$4:$D$90,$F6,$C$4:$C$90) -> 0
A7: Escalations | C7: 181142.97 | D7: RENT | F7: CONC | G7: Concessions | H7: =SUMIF($D$4:$D$90,$F7,$C$4:$C$90) -> 0
A8: Free Rent | C8: 0 | G8: Total Rental Revenue | H8: =SUM(H4:H7) -> 2506470
A9: Total Rental Income | C9: 2506470
A10: CAM Expense Recoveries | G10: Other Income
A11: CAM Expense Recovery | C11: 386785 | F11: CAM | G11: CAM Reimbursement | H11: =SUMIF($D$4:$D$90,$F11,$C$4:$C$90) -> 386785
A12: Total CAM Expense Recoveries | C12: 386785 | D12: CAM | F12: UR | G12: Utility Reimbursement | H12: =SUMIF($D$4:$D$90,$F12,$C$4:$C$90) -> 60383
A13: Utility Recoveries | F13: RETR | G13: Real Estate Tax Reimbursement | H13: =SUMIF($D$4:$D$90,$F13,$C$4:$C$90) -> 0
A14: Utility Recovery | C14: 60383 | F14: PARK | G14: Parking Income | H14: =SUMIF($D$4:$D$90,$F14,$C$4:$C$90) -> 19200
A15: Total Utility Recoveries | C15: 60383 | D15: UR | F15: OI | G15: Other Income | H15: =SUMIF($D$4:$D$90,$F15,$C$4:$C$90) -> 9493
A16: Other Income-Building Related | G16: Total Other Income | H16: =SUM(H11:H15) -> 475861
A17: Parking Rent | C17: 19200 | D17: PARK
A18: Late Fees | C18: 1738 | D18: OI | G18: Effective Gross Revenue
A19: Other Reimbursements | C19: 3625 | D19: OI | G19: Gross Revenue | H19: =+H16+H8 -> 2982331
A20: Tenant Work Orders | C20: 405 | D20: OI | G20: General Vacancy and Credit Loss | H20: 0
A21: Other Income | C21: 505 | D21: OI | G21: Total Effective Gross Revenue | H21: =+H19+H20 -> 2982331 | I21: =C25 -> 2982331
A22: Telecom/Antenna | C22: 1350 | D22: OI | G22: OPERATING EXPENSES
A23: Building Amenity Income | C23: 1870 | D23: OI | G23: Reimbursable Operating Expenses
A24: Total Other Income | C24: 28693 | G24: Variable Operating Expenses
A25: Total Income | C25: 2982331 | F25: CLEAN | G25: Cleaning | H25: =SUMIF($D$4:$D$90,$F25,$C$4:$C$90) -> 117365
A26: Operating Expenses | F26: RM | G26: Repairs and Maintenance | H26: =SUMIF($D$4:$D$90,$F26,$C$4:$C$90) -> 262319
A27: Recoverable Expenses | F27: SEC | G27: Security | H27: =SUMIF($D$4:$D$90,$F27,$C$4:$C$90) -> 192830
A28: Utilities | F28: LAND | G28: Landscaping | H28: =SUMIF($D$4:$D$90,$F28,$C$4:$C$90) -> 32818
A29: Utilities-Water/Sewer | C29: 23491 | F29: U | G29: Utilities | H29: =SUMIF($D$4:$D$90,$F29,$C$4:$C$90) -> 185174
A30: Utilities-Electric | C30: 161683 | F30: PR | G30: Payroll | H30: =SUMIF($D$4:$D$90,$F30,$C$4:$C$90) -> 186495
A31: Tenant Reimb-Sub-Meter | C31: 0 | F31: PM | G31: Property Management | H31: =SUMIF($D$4:$D$90,$F31,$C$4:$C$90) -> 0
A32: Total Utilities | C32: 185174 | D32: U | F32: MARK | G32: Marketing | H32: =SUMIF($D$4:$D$90,$F32,$C$4:$C$90) -> 0
A33: Repairs & Maintenance | F33: OVE | G33: Other Variable Expenses | H33: =SUMIF($D$4:$D$90,$F33,$C$4:$C$90) -> 285377
A34: Payroll & Related | C34: 186495 | D34: PR | G34: Total Variable Expenses | H34: =SUM(H25:H33) -> 1262378
A35: HVAC | C35: 5579 | D35: RM | G35: Fixed Expenses
A36: Elevator | C36: 14673 | D36: RM | F36: RET | G36: Real Estate Taxes | H36: =SUMIF($D$4:$D$90,$F36,$C$4:$C$90) -> 1249105
A37: Janitorial | C37: 117365 | D37: CLEAN | F37: I | G37: Insurance | H37: =SUMIF($D$4:$D$90,$F37,$C$4:$C$90) -> 7664
A38: Grounds | C38: 32818 | D38: LAND | G38: Total Fixed Operating Expenses | H38: =SUM(H36:H37) -> 1256769
A39: Garage/Parking | C39: 11898 | D39: RM
A40: Fire/Life Safety | C40: 6076 | D40: SEC | G40: Total Reimbursable OpEx | H40: =+H38+H34 -> 2519147
A41: Security | C41: 186754 | D41: SEC
A42: Plumbing | C42: 3105 | D42: RM | G42: Non-Reimbursable Operating Expenses
A43: Electrical | C43: 1430 | D43: RM | G43: Variable Operating Expenses
A44: Exterior Maintenance | C44: 105927 | D44: RM | F44: CLEANN | G44: Cleaning | H44: =SUMIF($D$4:$D$90,$F44,$C$4:$C$90) -> 0
A45: Interior Maintenance | C45: 119707 | D45: RM | F45: RMN | G45: Repairs and Maintenance | H45: =SUMIF($D$4:$D$90,$F45,$C$4:$C$90) -> 0
A46: General Maintenance | C46: 0 | D46: RM | F46: SECN | G46: Security | H46: =SUMIF($D$4:$D$90,$F46,$C$4:$C$90) -> 0
A47: Total Repairs & Maintenance | C47: 791827 | F47: LANDN | G47: Landscaping | H47: =SUMIF($D$4:$D$90,$F47,$C$4:$C$90) -> 0
A48: Administrative Expenses | F48: UN | G48: Utilities | H48: =SUMIF($D$4:$D$90,$F48,$C$4:$C$90) -> 0
A49: Management Fees | C49: 44865 | F49: PRN | G49: Payroll | H49: =SUMIF($D$4:$D$90,$F49,$C$4:$C$90) -> 0
A50: Accounting Fees | C50: 36644 | F50: MARKN | G50: Marketing | H50: =SUMIF($D$4:$D$90,$F50,$C$4:$C$90) -> 115
A51: Payroll and Related | C51: 131816 | F51: OVEN | G51: Other Variable Expenses | H51: =SUMIF($D$4:$D$90,$F51,$C$4:$C$90) -> 32727
A52: Office Expenses | C52: 72052 | G52: Total Variable Expenses | H52: =SUM(H44:H51) -> 32842
A53: Tenant Relations | C53: 0 | G53: Fixed Expenses
A54: Total Administrative Expenses | C54: 285377 | D54: OVE | F54: RETN | G54: Real Estate Taxes | H54: =SUMIF($D$4:$D$90,$F54,$C$4:$C$90) -> 0
A55: Property Taxes | F55: IN | G55: Insurance | H55: =SUMIF($D$4:$D$90,$F55,$C$4:$C$90) -> 0
A56: Other Taxes | C56: 43584 | G56: Total Fixed Operating Expenses | H56: =SUM(H54:H55) -> 0
A57: Property Taxes | C57: 1198650
A58: Prop. Tax Consultant | C58: 6871 | G58: Total Non-Reimbursable OpEx | H58: =+H56+H52 -> 32842
A59: Margin Tax | C59: 0
A60: Total Property Taxes | C60: 1249105 | D60: RET | G60: Total Operating Expenses | H60: =H58+H40 -> 2551989 | I60: =C88 -> 2551989 | K60: =H58/H60 -> 0.012869178
A61: Insurance | K61: =H60/H21 -> 0.85570281
A62: Liability | C62: 7664 | G62: NET OPERATING INCOME | H62: =+H21-H60 -> 430341.97 | I62: =C90 -> 430341.97
A63: Property | C63: 0
A64: Total Insurance | C64: 7664 | D64: I
A65: Total Recoverable Expenses | C65: 2519147
A66: Non-Recoverable Expenses
A67: Non-Recoverable Bldg Related
A68: Legal & Professional Fees | C68: 2636
A69: Consultant | C69: 12160
A70: Telecom Management Fee | C70: 166
A71: Non-CAM Administrative | C71: 3634
A72: Non-CAM Tenant Related | C72: 2910
A73: Tenant Signage | C73: 1166
A74: Locks and Keys | C74: 2554
A75: Misc. - R&M | C75: 145
A76: Building Conf. Room | C76: 3669
A77: Bad Debt | C77: 0
A78: Total Non-Recoverable-Bldg Related | C78: 29040 | D78: OVEN
A79: Other Non-Recoverable Expenses
A80: Advertising | C80: 115 | D80: MARKN
A81: Tenant Related | C81: 750 | D81: OVEN
A82: Dead Deals-Tenants / Test Fits | C82: 1510 | D82: OVEN
A83: General Architect/Engin | C83: 1427 | D83: OVEN
A84: Franchise and Other Taxes | C84: 0
A85: Total Other Non-Recoverable Expenses | C85: 3802
A86: Total Non-Recoverable Expenses | C86: 32842
A88: Total Expenses | C88: 2551989
A90: Net Operating Income | C90: 430341.97
