Workbook

Sheet Long-Term Leases
B2: MODELING LONG-TERM LEASES
B4: INCOME
B5: Other Income Growth | D5: 0.025 | E5: OpEx Growth | G5: 0.02 | I5: 43466 | J5: =EOMONTH(I5,-1) -> 43465 | K5: =EOMONTH(J5,1) -> 43496 | L5: =EOMONTH(K5,1) -> 43524 | M5: =EOMONTH(L5,1) -> 43555 | N5: =EOMONTH(M5,1) -> 43585 | O5: =EOMONTH(N5,1) -> 43616 | P5: =EOMONTH(O5,1) -> 43646 | Q5: =EOMONTH(P5,1) -> 43677 | R5: =EOMONTH(Q5,1) -> 43708 | ... EL5: =EOMONTH(EK5,1) -> 47483
B6: Reversion Cap Rate | D6: 0.0575 | E6: Target Unlevered IRR | G6: 0.08 | J6: =ROUNDUP(J7/12,0) -> 0 | K6: =ROUNDUP(K7/12,0) -> 1 | L6: =ROUNDUP(L7/12,0) -> 1 | M6: =ROUNDUP(M7/12,0) -> 1 | N6: =ROUNDUP(N7/12,0) -> 1 | O6: =ROUNDUP(O7/12,0) -> 1 | P6: =ROUNDUP(P7/12,0) -> 1 | Q6: =ROUNDUP(Q7/12,0) -> 1 | ... EL6: =ROUNDUP(EL7/12,0) -> 11
G7: Pro Forma | J7: 0 | K7: =J7+1 -> 1 | L7: =K7+1 -> 2 | M7: =L7+1 -> 3 | N7: =M7+1 -> 4 | O7: =N7+1 -> 5 | P7: =O7+1 -> 6 | Q7: =P7+1 -> 7 | R7: =Q7+1 -> 8 | ... EL7: =EK7+1 -> 132
B8: Potential Base Rent | G8: ='Rent Roll'!H6 -> 1907314.9 | I8: Rental Income | K8: ='Rent Roll'!VB6 -> 158942.91 | L8: ='Rent Roll'!VC6 -> 158942.91 | M8: ='Rent Roll'!VD6 -> 158942.91 | N8: ='Rent Roll'!VE6 -> 159184.17 | O8: ='Rent Roll'!VF6 -> 159184.17 | P8: ='Rent Roll'!VG6 -> 160436.1 | Q8: ='Rent Roll'!VH6 -> 160436.1 | R8: ='Rent Roll'!VI6 -> 160436.1 | ... EL8: ='Rent Roll'!AAC6 -> 195895.78
B9: - Concessions | G9: =SUM(K9:EL9)/11 -> -90064.947 | I9: Concessions | K9: =-'Rent Roll'!AAF6 -> 0 | L9: =-'Rent Roll'!AAG6 -> 0 | M9: =-'Rent Roll'!AAH6 -> 0 | N9: =-'Rent Roll'!AAI6 -> 0 | O9: =-'Rent Roll'!AAJ6 -> 0 | P9: =-'Rent Roll'!AAK6 -> 0 | Q9: =-'Rent Roll'!AAL6 -> 0 | R9: =-'Rent Roll'!AAM6 -> 0 | ... EL9: =-'Rent Roll'!AFG6 -> 0
B10: Total Rental Revenue | G10: =SUM(G8:G9) -> 1817250 | I10: Total Rental Revenue | K10: =SUM(K8:K9) -> 158942.91 | L10: =SUM(L8:L9) -> 158942.91 | M10: =SUM(M8:M9) -> 158942.91 | N10: =SUM(N8:N9) -> 159184.17 | O10: =SUM(O8:O9) -> 159184.17 | P10: =SUM(P8:P9) -> 160436.1 | Q10: =SUM(Q8:Q9) -> 160436.1 | R10: =SUM(R8:R9) -> 160436.1 | ... EL10: =SUM(EL8:EL9) -> 195895.78
B11: Reimbursement Income | F11: 1 | G11: =+F11*G17 -> 767341 | K11: ='Rent Roll'!AFJ6+'Rent Roll'!AKN6 -> 63945.083 | L11: ='Rent Roll'!AFK6+'Rent Roll'!AKO6 -> 63945.083 | M11: ='Rent Roll'!AFL6+'Rent Roll'!AKP6 -> 63945.083 | N11: ='Rent Roll'!AFM6+'Rent Roll'!AKQ6 -> 63945.083 | O11: ='Rent Roll'!AFN6+'Rent Roll'!AKR6 -> 63945.083 | P11: ='Rent Roll'!AFO6+'Rent Roll'!AKS6 -> 63945.083 | Q11: ='Rent Roll'!AFP6+'Rent Roll'!AKT6 -> 63945.083 | R11: ='Rent Roll'!AFQ6+'Rent Roll'!AKU6 -> 63945.083 | ... EL11: ='Rent Roll'!AKK6+'Rent Roll'!APO6 -> 77948.7
B12: Other Income | G12: =7700+241780*0.75 -> 189035 | K12: =$G$12/12*(1+$D$5)^(K$6-1) -> 15752.917 | L12: =$G$12/12*(1+$D$5)^(L$6-1) -> 15752.917 | M12: =$G$12/12*(1+$D$5)^(M$6-1) -> 15752.917 | N12: =$G$12/12*(1+$D$5)^(N$6-1) -> 15752.917 | O12: =$G$12/12*(1+$D$5)^(O$6-1) -> 15752.917 | P12: =$G$12/12*(1+$D$5)^(P$6-1) -> 15752.917 | Q12: =$G$12/12*(1+$D$5)^(Q$6-1) -> 15752.917 | R12: =$G$12/12*(1+$D$5)^(R$6-1) -> 15752.917 | ... EL12: =$G$12/12*(1+$D$5)^(EL$6-1) -> 20165.065
B13: Gross Revenue | G13: =SUM(G10:G12) -> 2773626 | K13: =SUM(K10:K12) -> 238640.91 | L13: =SUM(L10:L12) -> 238640.91 | M13: =SUM(M10:M12) -> 238640.91 | N13: =SUM(N10:N12) -> 238882.17 | O13: =SUM(O10:O12) -> 238882.17 | P13: =SUM(P10:P12) -> 240134.1 | Q13: =SUM(Q10:Q12) -> 240134.1 | R13: =SUM(R10:R12) -> 240134.1 | ... EL13: =SUM(EL10:EL12) -> 294009.54
B14: - General Vacancy and Credit Loss | F14: 0.04 | G14: =+-F14*G13 -> -110945.04 | K14: =-$F$14*K13 -> -9545.6365 | L14: =-$F$14*L13 -> -9545.6365 | M14: =-$F$14*M13 -> -9545.6365 | N14: =-$F$14*N13 -> -9555.2869 | O14: =-$F$14*O13 -> -9555.2869 | P14: =-$F$14*P13 -> -9605.3638 | Q14: =-$F$14*Q13 -> -9605.3638 | R14: =-$F$14*R13 -> -9605.3638 | ... EL14: =-$F$14*EL13 -> -11760.382
B15: Total Effective Gross Revenue | G15: =SUM(G13:G14) -> 2662681 | K15: =SUM(K13:K14) -> 229095.28 | L15: =SUM(L13:L14) -> 229095.28 | M15: =SUM(M13:M14) -> 229095.28 | N15: =SUM(N13:N14) -> 229326.89 | O15: =SUM(O13:O14) -> 229326.89 | P15: =SUM(P13:P14) -> 230528.73 | Q15: =SUM(Q13:Q14) -> 230528.73 | R15: =SUM(R13:R14) -> 230528.73 | ... EL15: =SUM(EL13:EL14) -> 282249.16
B17: Operating Expenses | G17: 767341 | K17: =$G$17/12*(1+$G$5)^(K$6-1) -> 63945.083 | L17: =$G$17/12*(1+$G$5)^(L$6-1) -> 63945.083 | M17: =$G$17/12*(1+$G$5)^(M$6-1) -> 63945.083 | N17: =$G$17/12*(1+$G$5)^(N$6-1) -> 63945.083 | O17: =$G$17/12*(1+$G$5)^(O$6-1) -> 63945.083 | P17: =$G$17/12*(1+$G$5)^(P$6-1) -> 63945.083 | Q17: =$G$17/12*(1+$G$5)^(Q$6-1) -> 63945.083 | R17: =$G$17/12*(1+$G$5)^(R$6-1) -> 63945.083 | ... EL17: =$G$17/12*(1+$G$5)^(EL$6-1) -> 77948.7
B18: Net Operating Income | G18: =G15-G17 -> 1895340 | K18: =+K15-K17 -> 165150.19 | L18: =+L15-L17 -> 165150.19 | M18: =+M15-M17 -> 165150.19 | N18: =+N15-N17 -> 165381.8 | O18: =+O15-O17 -> 165381.8 | P18: =+P15-P17 -> 166583.65 | Q18: =+Q15-Q17 -> 166583.65 | R18: =+R15-R17 -> 166583.65 | ... EL18: =+EL15-EL17 -> 204300.46
B19: Leasing Costs | E19: =SUMPRODUCT('Rent Roll'!Q7:Q13,'Rent Roll'!D7:D13)/'Rent Roll'!D6/12 -> 11.675379 | F19: =SUMPRODUCT('Rent Roll'!AH7:AH13,'Rent Roll'!D7:D13)/'Rent Roll'!D6 -> 18.241596 | G19: =F19*'Rent Roll'!D6/E19 -> 213697.07 | K19: ='Rent Roll'!APR6 -> 0 | L19: ='Rent Roll'!APS6 -> 0 | M19: ='Rent Roll'!APT6 -> 0 | N19: ='Rent Roll'!APU6 -> 0 | O19: ='Rent Roll'!APV6 -> 0 | P19: ='Rent Roll'!APW6 -> 0 | Q19: ='Rent Roll'!APX6 -> 0 | R19: ='Rent Roll'!APY6 -> 0 | ... EL19: ='Rent Roll'!AUS6 -> 0
B20: Cash Flow from Operations | G20: =+G18-G19 -> 1681642.9 | K20: =K18-K19 -> 165150.19 | L20: =L18-L19 -> 165150.19 | M20: =M18-M19 -> 165150.19 | N20: =N18-N19 -> 165381.8 | O20: =O18-O19 -> 165381.8 | P20: =P18-P19 -> 166583.65 | Q20: =Q18-Q19 -> 166583.65 | R20: =R18-R19 -> 166583.65 | ... EL20: =EL18-EL19 -> 204300.46
B22: Reversion Value | G22: =SUM(EA18:EL18)/D6 -> 42266373 | K22: =(K7=120)*$G$22 -> 0 | L22: =(L7=120)*$G$22 -> 0 | M22: =(M7=120)*$G$22 -> 0 | N22: =(N7=120)*$G$22 -> 0 | O22: =(O7=120)*$G$22 -> 0 | P22: =(P7=120)*$G$22 -> 0 | Q22: =(Q7=120)*$G$22 -> 0 | R22: =(R7=120)*$G$22 -> 0 | ... EL22: =(EL7=120)*$G$22 -> 0
B23: Net Cash Flow | J23: =+J22+J20 -> 0 | K23: =(K7<=120)*(K22+K20) -> 165150.19 | L23: =(L7<=120)*(L22+L20) -> 165150.19 | M23: =(M7<=120)*(M22+M20) -> 165150.19 | N23: =(N7<=120)*(N22+N20) -> 165381.8 | O23: =(O7<=120)*(O22+O20) -> 165381.8 | P23: =(P7<=120)*(P22+P20) -> 166583.65 | Q23: =(Q7<=120)*(Q22+Q20) -> 166583.65 | R23: =(R7<=120)*(R22+R20) -> 166583.65 | ... EL23: =(EL7<=120)*(EL22+EL20) -> 0 | EN23: =(EN2<=120)*(EN22+EN18) -> 0 | EO23: =(EO2<=120)*(EO22+EO18) -> 0
B24: ="Present Value @ "&TEXT(G6,"0.00%") -> Present Value @ 8.00% | G24: =XNPV(G6,J23:EL23,J5:EL5) -> 32482488
B26: Unlevered Net Cash Flow | J26: =+-G24 -> -32482488 | K26: =+K23 -> 165150.19 | L26: =+L23 -> 165150.19 | M26: =+M23 -> 165150.19 | N26: =+N23 -> 165381.8 | O26: =+O23 -> 165381.8 | P26: =+P23 -> 166583.65 | Q26: =+Q23 -> 166583.65 | R26: =+R23 -> 166583.65 | ... EL26: =+EL23 -> 0 | EN26: =+EN23 -> 0 | EO26: =+EO23 -> 0
B27: Unlevered Internal Rate of Return | G27: =XIRR(J26:EL26,J5:EL5) -> 0.079999998

Sheet Rent Roll
B2: RENT ROLL | AJ2: 1st Generation NRA Occupied | FL2: 1st. | FN2: 2nd Generation NRA Occupied | KP2: 2nd | KR2: 1st Generation Rent | PU2: 1st. | PW2: 2nd Generation Rent | UZ2: 2nd | VB2: Potential Base Rent | AAD2: Pot. | AAF2: Concessions | AFH2: Conc. | AFJ2: 1st Generation Reimbursement | AKL2: 1st | AKN2: 2nd Generation Reimbursement | APP2: 2nd | APR2: Leasing Costs | AUT2: Leasing
B3: 1st Generation Tenant | M3: 2nd Generation Tenant | AJ3: ='Long-Term Leases'!$K$5 -> 43496 | AK3: =EOMONTH(AJ3,1) -> 43524 | AL3: =EOMONTH(AK3,1) -> 43555 | AM3: =EOMONTH(AL3,1) -> 43585 | AN3: =EOMONTH(AM3,1) -> 43616 | AO3: =EOMONTH(AN3,1) -> 43646 | AP3: =EOMONTH(AO3,1) -> 43677 | AQ3: =EOMONTH(AP3,1) -> 43708 | AR3: =EOMONTH(AQ3,1) -> 43738 | ... FK3: =EOMONTH(FJ3,1) -> 47483 | FL3: Gen | FN3: ='Long-Term Leases'!$K$5 -> 43496 | FO3: =EOMONTH(FN3,1) -> 43524 | FP3: =EOMONTH(FO3,1) -> 43555 | FQ3: =EOMONTH(FP3,1) -> 43585 | FR3: =EOMONTH(FQ3,1) -> 43616 | FS3: =EOMONTH(FR3,1) -> 43646 | FT3: =EOMONTH(FS3,1) -> 43677 | FU3: =EOMONTH(FT3,1) -> 43708 | FV3: =EOMONTH(FU3,1) -> 43738 | ... KO3: =EOMONTH(KN3,1) -> 47483 | KP3: Gen | KR3: =+G4 -> Current | KS3: ='Long-Term Leases'!$K$5 -> 43496 | KT3: =EOMONTH(KS3,1) -> 43524 | KU3: =EOMONTH(KT3,1) -> 43555 | KV3: =EOMONTH(KU3,1) -> 43585 | KW3: =EOMONTH(KV3,1) -> 43616 | KX3: =EOMONTH(KW3,1) -> 43646 | KY3: =EOMONTH(KX3,1) -> 43677 | KZ3: =EOMONTH(KY3,1) -> 43708 | LA3: =EOMONTH(KZ3,1) -> 43738 | ... PT3: =EOMONTH(PS3,1) -> 47483 | PU3: Gen | PW3: =T4 -> Rent at | PX3: ='Long-Term Leases'!$K$5 -> 43496 | PY3: =EOMONTH(PX3,1) -> 43524 | PZ3: =EOMONTH(PY3,1) -> 43555 | QA3: =EOMONTH(PZ3,1) -> 43585 | QB3: =EOMONTH(QA3,1) -> 43616 | QC3: =EOMONTH(QB3,1) -> 43646 | QD3: =EOMONTH(QC3,1) -> 43677 | QE3: =EOMONTH(QD3,1) -> 43708 | QF3: =EOMONTH(QE3,1) -> 43738 | ... UY3: =EOMONTH(UX3,1) -> 47483 | UZ3: Gen | VB3: ='Long-Term Leases'!$K$5 -> 43496 | VC3: =EOMONTH(VB3,1) -> 43524 | VD3: =EOMONTH(VC3,1) -> 43555 | VE3: =EOMONTH(VD3,1) -> 43585 | VF3: =EOMONTH(VE3,1) -> 43616 | VG3: =EOMONTH(VF3,1) -> 43646 | VH3: =EOMONTH(VG3,1) -> 43677 | VI3: =EOMONTH(VH3,1) -> 43708 | VJ3: =EOMONTH(VI3,1) -> 43738 | ... AAC3: =EOMONTH(AAB3,1) -> 47483 | AAD3: Base | AAF3: ='Long-Term Leases'!$K$5 -> 43496 | AAG3: =EOMONTH(AAF3,1) -> 43524 | AAH3: =EOMONTH(AAG3,1) -> 43555 | AAI3: =EOMONTH(AAH3,1) -> 43585 | AAJ3: =EOMONTH(AAI3,1) -> 43616 | AAK3: =EOMONTH(AAJ3,1) -> 43646 | AAL3: =EOMONTH(AAK3,1) -> 43677 | AAM3: =EOMONTH(AAL3,1) -> 43708 | AAN3: =EOMONTH(AAM3,1) -> 43738 | ... AFG3: =EOMONTH(AFF3,1) -> 47483 | AFJ3: ='Long-Term Leases'!$K$5 -> 43496 | AFK3: =EOMONTH(AFJ3,1) -> 43524 | AFL3: =EOMONTH(AFK3,1) -> 43555 | AFM3: =EOMONTH(AFL3,1) -> 43585 | AFN3: =EOMONTH(AFM3,1) -> 43616 | AFO3: =EOMONTH(AFN3,1) -> 43646 | AFP3: =EOMONTH(AFO3,1) -> 43677 | AFQ3: =EOMONTH(AFP3,1) -> 43708 | AFR3: =EOMONTH(AFQ3,1) -> 43738 | ... AKK3: =EOMONTH(AKJ3,1) -> 47483 | AKL3: Gen | AKN3: ='Long-Term Leases'!$K$5 -> 43496 | AKO3: =EOMONTH(AKN3,1) -> 43524 | AKP3: =EOMONTH(AKO3,1) -> 43555 | AKQ3: =EOMONTH(AKP3,1) -> 43585 | AKR3: =EOMONTH(AKQ3,1) -> 43616 | AKS3: =EOMONTH(AKR3,1) -> 43646 | AKT3: =EOMONTH(AKS3,1) -> 43677 | AKU3: =EOMONTH(AKT3,1) -> 43708 | AKV3: =EOMONTH(AKU3,1) -> 43738 | ... APO3: =EOMONTH(APN3,1) -> 47483 | APP3: Gen | APR3: ='Long-Term Leases'!$K$5 -> 43496 | APS3: =EOMONTH(APR3,1) -> 43524 | APT3: =EOMONTH(APS3,1) -> 43555 | APU3: =EOMONTH(APT3,1) -> 43585 | APV3: =EOMONTH(APU3,1) -> 43616 | APW3: =EOMONTH(APV3,1) -> 43646 | APX3: =EOMONTH(APW3,1) -> 43677 | APY3: =EOMONTH(APX3,1) -> 43708 | APZ3: =EOMONTH(APY3,1) -> 43738 | ... AUS3: =EOMONTH(AUR3,1) -> 47483 | AUT3: Costs
E4: Month | F4: Month | G4: Current | H4: Current | I4: Ann. Base | J4: Escalation | K4: Reimb. | L4: Pro Rata | M4: Market | N4: Mkt Rent | O4: Renewal | P4: Downtime | Q4: Lease | R4: Month | S4: Month | T4: Rent at | U4: Ann. Base | V4: Escalation | W4: Reimb. | X4: Pro Rata | Y4: Free Rent | Z4: Free Rent | AA4: Free Rent | AB4: TI | AC4: TI | AD4: LC | AE4: LC | AF4: TI | AG4: LC | AH4: Leasing | AJ4: =ROUNDUP(AJ5/12,0) -> 1 | AK4: =ROUNDUP(AK5/12,0) -> 1 | AL4: =ROUNDUP(AL5/12,0) -> 1 | AM4: =ROUNDUP(AM5/12,0) -> 1 | AN4: =ROUNDUP(AN5/12,0) -> 1 | AO4: =ROUNDUP(AO5/12,0) -> 1 | AP4: =ROUNDUP(AP5/12,0) -> 1 | AQ4: =ROUNDUP(AQ5/12,0) -> 1 | ... FK4: =ROUNDUP(FK5/12,0) -> 11 | FL4: NRA | FN4: =ROUNDUP(FN5/12,0) -> 1 | FO4: =ROUNDUP(FO5/12,0) -> 1 | FP4: =ROUNDUP(FP5/12,0) -> 1 | FQ4: =ROUNDUP(FQ5/12,0) -> 1 | FR4: =ROUNDUP(FR5/12,0) -> 1 | FS4: =ROUNDUP(FS5/12,0) -> 1 | FT4: =ROUNDUP(FT5/12,0) -> 1 | FU4: =ROUNDUP(FU5/12,0) -> 1 | ... KO4: =ROUNDUP(KO5/12,0) -> 11 | KP4: NRA | KR4: =+G5 -> Rent/SF | KS4: =ROUNDUP(KS5/12,0) -> 1 | KT4: =ROUNDUP(KT5/12,0) -> 1 | KU4: =ROUNDUP(KU5/12,0) -> 1 | KV4: =ROUNDUP(KV5/12,0) -> 1 | KW4: =ROUNDUP(KW5/12,0) -> 1 | KX4: =ROUNDUP(KX5/12,0) -> 1 | KY4: =ROUNDUP(KY5/12,0) -> 1 | KZ4: =ROUNDUP(KZ5/12,0) -> 1 | ... PT4: =ROUNDUP(PT5/12,0) -> 11 | PU4: Rent | PW4: =T5 -> Start | PX4: =ROUNDUP(PX5/12,0) -> 1 | PY4: =ROUNDUP(PY5/12,0) -> 1 | PZ4: =ROUNDUP(PZ5/12,0) -> 1 | QA4: =ROUNDUP(QA5/12,0) -> 1 | QB4: =ROUNDUP(QB5/12,0) -> 1 | QC4: =ROUNDUP(QC5/12,0) -> 1 | QD4: =ROUNDUP(QD5/12,0) -> 1 | QE4: =ROUNDUP(QE5/12,0) -> 1 | ... UY4: =ROUNDUP(UY5/12,0) -> 11 | UZ4: Rent | VB4: =ROUNDUP(VB5/12,0) -> 1 | VC4: =ROUNDUP(VC5/12,0) -> 1 | VD4: =ROUNDUP(VD5/12,0) -> 1 | VE4: =ROUNDUP(VE5/12,0) -> 1 | VF4: =ROUNDUP(VF5/12,0) -> 1 | VG4: =ROUNDUP(VG5/12,0) -> 1 | VH4: =ROUNDUP(VH5/12,0) -> 1 | VI4: =ROUNDUP(VI5/12,0) -> 1 | ... AAC4: =ROUNDUP(AAC5/12,0) -> 11 | AAD4: Rent | AAF4: =ROUNDUP(AAF5/12,0) -> 1 | AAG4: =ROUNDUP(AAG5/12,0) -> 1 | AAH4: =ROUNDUP(AAH5/12,0) -> 1 | AAI4: =ROUNDUP(AAI5/12,0) -> 1 | AAJ4: =ROUNDUP(AAJ5/12,0) -> 1 | AAK4: =ROUNDUP(AAK5/12,0) -> 1 | AAL4: =ROUNDUP(AAL5/12,0) -> 1 | AAM4: =ROUNDUP(AAM5/12,0) -> 1 | ... AFG4: =ROUNDUP(AFG5/12,0) -> 11 | AFJ4: =ROUNDUP(AFJ5/12,0) -> 1 | AFK4: =ROUNDUP(AFK5/12,0) -> 1 | AFL4: =ROUNDUP(AFL5/12,0) -> 1 | AFM4: =ROUNDUP(AFM5/12,0) -> 1 | AFN4: =ROUNDUP(AFN5/12,0) -> 1 | AFO4: =ROUNDUP(AFO5/12,0) -> 1 | AFP4: =ROUNDUP(AFP5/12,0) -> 1 | AFQ4: =ROUNDUP(AFQ5/12,0) -> 1 | ... AKK4: =ROUNDUP(AKK5/12,0) -> 11 | AKL4: Reimb | AKN4: =ROUNDUP(AKN5/12,0) -> 1 | AKO4: =ROUNDUP(AKO5/12,0) -> 1 | AKP4: =ROUNDUP(AKP5/12,0) -> 1 | AKQ4: =ROUNDUP(AKQ5/12,0) -> 1 | AKR4: =ROUNDUP(AKR5/12,0) -> 1 | AKS4: =ROUNDUP(AKS5/12,0) -> 1 | AKT4: =ROUNDUP(AKT5/12,0) -> 1 | AKU4: =ROUNDUP(AKU5/12,0) -> 1 | ... APO4: =ROUNDUP(APO5/12,0) -> 11 | APP4: Reimb | APR4: =ROUNDUP(APR5/12,0) -> 1 | APS4: =ROUNDUP(APS5/12,0) -> 1 | APT4: =ROUNDUP(APT5/12,0) -> 1 | APU4: =ROUNDUP(APU5/12,0) -> 1 | APV4: =ROUNDUP(APV5/12,0) -> 1 | APW4: =ROUNDUP(APW5/12,0) -> 1 | APX4: =ROUNDUP(APX5/12,0) -> 1 | APY4: =ROUNDUP(APY5/12,0) -> 1 | ... AUS4: =ROUNDUP(AUS5/12,0) -> 11
B5: Suite | C5: Tenant | D5: NRA (SF) | E5: Start | F5: Expire | G5: Rent/SF | H5: Rent | I5: Rent Inc. % | J5: Month (#) | K5: % | L5: Share | M5: Rent | N5: Growth % | O5: Probability | P5: Months | Q5: Term | R5: Start | S5: Expire | T5: Start | U5: Rent Inc. % | V5: Month (#) | W5: % | X5: Share | Y5: New | Z5: Renew | AA5: Cost/SF | AB5: New | AC5: Renew | AD5: New | AE5: Renew | AF5: Cost/SF | AG5: Cost/SF | AH5: Cost/SF | AJ5: 1 | AK5: =+AJ5+1 -> 2 | AL5: =+AK5+1 -> 3 | AM5: =+AL5+1 -> 4 | AN5: =+AM5+1 -> 5 | AO5: =+AN5+1 -> 6 | AP5: =+AO5+1 -> 7 | AQ5: =+AP5+1 -> 8 | AR5: =+AQ5+1 -> 9 | ... FK5: =+FJ5+1 -> 132 | FL5: Occ. | FN5: 1 | FO5: =+FN5+1 -> 2 | FP5: =+FO5+1 -> 3 | FQ5: =+FP5+1 -> 4 | FR5: =+FQ5+1 -> 5 | FS5: =+FR5+1 -> 6 | FT5: =+FS5+1 -> 7 | FU5: =+FT5+1 -> 8 | FV5: =+FU5+1 -> 9 | ... KO5: =+KN5+1 -> 132 | KP5: Occ. | KR5: Adj. | KS5: 1 | KT5: =+KS5+1 -> 2 | KU5: =+KT5+1 -> 3 | KV5: =+KU5+1 -> 4 | KW5: =+KV5+1 -> 5 | KX5: =+KW5+1 -> 6 | KY5: =+KX5+1 -> 7 | KZ5: =+KY5+1 -> 8 | LA5: =+KZ5+1 -> 9 | ... PT5: =+PS5+1 -> 132 | PW5: Adj. | PX5: 1 | PY5: =+PX5+1 -> 2 | PZ5: =+PY5+1 -> 3 | QA5: =+PZ5+1 -> 4 | QB5: =+QA5+1 -> 5 | QC5: =+QB5+1 -> 6 | QD5: =+QC5+1 -> 7 | QE5: =+QD5+1 -> 8 | QF5: =+QE5+1 -> 9 | ... UY5: =+UX5+1 -> 132 | VB5: 1 | VC5: =+VB5+1 -> 2 | VD5: =+VC5+1 -> 3 | VE5: =+VD5+1 -> 4 | VF5: =+VE5+1 -> 5 | VG5: =+VF5+1 -> 6 | VH5: =+VG5+1 -> 7 | VI5: =+VH5+1 -> 8 | VJ5: =+VI5+1 -> 9 | ... AAC5: =+AAB5+1 -> 132 | AAF5: 1 | AAG5: =+AAF5+1 -> 2 | AAH5: =+AAG5+1 -> 3 | AAI5: =+AAH5+1 -> 4 | AAJ5: =+AAI5+1 -> 5 | AAK5: =+AAJ5+1 -> 6 | AAL5: =+AAK5+1 -> 7 | AAM5: =+AAL5+1 -> 8 | AAN5: =+AAM5+1 -> 9 | ... AFG5: =+AFF5+1 -> 132 | AFJ5: 1 | AFK5: =+AFJ5+1 -> 2 | AFL5: =+AFK5+1 -> 3 | AFM5: =+AFL5+1 -> 4 | AFN5: =+AFM5+1 -> 5 | AFO5: =+AFN5+1 -> 6 | AFP5: =+AFO5+1 -> 7 | AFQ5: =+AFP5+1 -> 8 | AFR5: =+AFQ5+1 -> 9 | ... AKK5: =+AKJ5+1 -> 132 | AKN5: 1 | AKO5: =+AKN5+1 -> 2 | AKP5: =+AKO5+1 -> 3 | AKQ5: =+AKP5+1 -> 4 | AKR5: =+AKQ5+1 -> 5 | AKS5: =+AKR5+1 -> 6 | AKT5: =+AKS5+1 -> 7 | AKU5: =+AKT5+1 -> 8 | AKV5: =+AKU5+1 -> 9 | ... APO5: =+APN5+1 -> 132 | APR5: 1 | APS5: =+APR5+1 -> 2 | APT5: =+APS5+1 -> 3 | APU5: =+APT5+1 -> 4 | APV5: =+APU5+1 -> 5 | APW5: =+APV5+1 -> 6 | APX5: =+APW5+1 -> 7 | APY5: =+APX5+1 -> 8 | APZ5: =+APY5+1 -> 9 | ... AUS5: =+AUR5+1 -> 132
D6: =SUM(D7:D13) -> 136775 | G6: =+H6/D6 -> 13.944909 | H6: =SUM(H7:H13) -> 1907314.9 | I6: 0.02 | L6: =SUM(L7:L13) -> 1 | U6: 0.02 | VB6: =SUM(VB7:VB17) -> 158942.91 | VC6: =SUM(VC7:VC17) -> 158942.91 | VD6: =SUM(VD7:VD17) -> 158942.91 | VE6: =SUM(VE7:VE17) -> 159184.17 | VF6: =SUM(VF7:VF17) -> 159184.17 | VG6: =SUM(VG7:VG17) -> 160436.1 | VH6: =SUM(VH7:VH17) -> 160436.1 | VI6: =SUM(VI7:VI17) -> 160436.1 | ... AAC6: =SUM(AAC7:AAC17) -> 195895.78 | AAF6: =SUM(AAF7:AAF17) -> 0 | AAG6: =SUM(AAG7:AAG17) -> 0 | AAH6: =SUM(AAH7:AAH17) -> 0 | AAI6: =SUM(AAI7:AAI17) -> 0 | AAJ6: =SUM(AAJ7:AAJ17) -> 0 | AAK6: =SUM(AAK7:AAK17) -> 0 | AAL6: =SUM(AAL7:AAL17) -> 0 | AAM6: =SUM(AAM7:AAM17) -> 0 | ... AFG6: =SUM(AFG7:AFG17) -> 0 | AFJ6: =SUM(AFJ7:AFJ17) -> 63945.083 | AFK6: =SUM(AFK7:AFK17) -> 63945.083 | AFL6: =SUM(AFL7:AFL17) -> 63945.083 | AFM6: =SUM(AFM7:AFM17) -> 63945.083 | AFN6: =SUM(AFN7:AFN17) -> 63945.083 | AFO6: =SUM(AFO7:AFO17) -> 63945.083 | AFP6: =SUM(AFP7:AFP17) -> 63945.083 | AFQ6: =SUM(AFQ7:AFQ17) -> 63945.083 | ... AKK6: =SUM(AKK7:AKK17) -> 0 | AKN6: =SUM(AKN7:AKN17) -> 0 | AKO6: =SUM(AKO7:AKO17) -> 0 | AKP6: =SUM(AKP7:AKP17) -> 0 | AKQ6: =SUM(AKQ7:AKQ17) -> 0 | AKR6: =SUM(AKR7:AKR17) -> 0 | AKS6: =SUM(AKS7:AKS17) -> 0 | AKT6: =SUM(AKT7:AKT17) -> 0 | AKU6: =SUM(AKU7:AKU17) -> 0 | ... APO6: =SUM(APO7:APO17) -> 77948.7 | APR6: =SUM(APR7:APR17) -> 0 | APS6: =SUM(APS7:APS17) -> 0 | APT6: =SUM(APT7:APT17) -> 0 | APU6: =SUM(APU7:APU17) -> 0 | APV6: =SUM(APV7:APV17) -> 0 | APW6: =SUM(APW7:APW17) -> 0 | APX6: =SUM(APX7:APX17) -> 0 | APY6: =SUM(APY7:APY17) -> 0 | ... AUS6: =SUM(AUS7:AUS17) -> 0
B7: 100 | C7: Trampoline Madness | D7: 24100 | E7: 1 | F7: 98 | G7: 11.97 | H7: =+G7*D7 -> 288477 | I7: =$I$6 -> 0.02 | J7: 1 | K7: 1 | L7: =D7/$D$6 -> 0.17620179 | M7: 14.5 | N7: 0.02 | O7: 0.8 | P7: 12 | Q7: 120 | R7: =ROUNDUP((1-O7)*P7,0)+F7+1 -> 102 | S7: =+R7+Q7-1 -> 221 | T7: =M7*(1+N7)^(ROUNDUP(R7/12,0)-1) -> 16.989061 | U7: =$U$6 -> 0.02 | V7: =12-(ROUNDUP(R7/12,0)*12-R7) -> 6 | W7: =+K7 -> 1 | X7: =+L7 -> 0.17620179 | Y7: 9 | Z7: 3 | AA7: =ROUNDUP(O7*Z7+(1-O7)*Y7,0)*T7/12 -> 7.0787754 | AB7: 25 | AC7: 10 | AD7: 0.06 | AE7: 0.03 | AF7: =AC7*O7+AB7*(1-O7) -> 13 | AG7: =(AE7*O7+AD7*(1-O7))*T7*Q7/12 -> 6.116062 | AH7: =SUM(AF7:AG7) -> 19.116062 | AJ7: =AND(AJ$5>=$E7,AJ$5<=$F7)*$D7 -> 24100 | AK7: =AND(AK$5>=$E7,AK$5<=$F7)*$D7 -> 24100 | AL7: =AND(AL$5>=$E7,AL$5<=$F7)*$D7 -> 24100 | AM7: =AND(AM$5>=$E7,AM$5<=$F7)*$D7 -> 24100 | AN7: =AND(AN$5>=$E7,AN$5<=$F7)*$D7 -> 24100 | AO7: =AND(AO$5>=$E7,AO$5<=$F7)*$D7 -> 24100 | AP7: =AND(AP$5>=$E7,AP$5<=$F7)*$D7 -> 24100 | AQ7: =AND(AQ$5>=$E7,AQ$5<=$F7)*$D7 -> 24100 | ... FK7: =AND(FK$5>=$E7,FK$5<=$F7)*$D7 -> 0 | FN7: =AND(FN$5>=$R7,FN$5<=$S7)*$D7 -> 0 | FO7: =AND(FO$5>=$R7,FO$5<=$S7)*$D7 -> 0 | FP7: =AND(FP$5>=$R7,FP$5<=$S7)*$D7 -> 0 | FQ7: =AND(FQ$5>=$R7,FQ$5<=$S7)*$D7 -> 0 | FR7: =AND(FR$5>=$R7,FR$5<=$S7)*$D7 -> 0 | FS7: =AND(FS$5>=$R7,FS$5<=$S7)*$D7 -> 0 | FT7: =AND(FT$5>=$R7,FT$5<=$S7)*$D7 -> 0 | FU7: =AND(FU$5>=$R7,FU$5<=$S7)*$D7 -> 0 | ... KO7: =AND(KO$5>=$R7,KO$5<=$S7)*$D7 -> 24100 | KR7: =IF(AND(J7>1,$E7=1),G7/12,G7/12/(1+$I7)) -> 0.97794118 | KS7: =(AJ7>0)*(MAX($KR7:KR7)+(MONTH(KS$3)=$J7)*MAX($KR7:KR7)*$I7) -> 0.9975 | KT7: =(AK7>0)*(MAX($KR7:KS7)+(MONTH(KT$3)=$J7)*MAX($KR7:KS7)*$I7) -> 0.9975 | KU7: =(AL7>0)*(MAX($KR7:KT7)+(MONTH(KU$3)=$J7)*MAX($KR7:KT7)*$I7) -> 0.9975 | KV7: =(AM7>0)*(MAX($KR7:KU7)+(MONTH(KV$3)=$J7)*MAX($KR7:KU7)*$I7) -> 0.9975 | KW7: =(AN7>0)*(MAX($KR7:KV7)+(MONTH(KW$3)=$J7)*MAX($KR7:KV7)*$I7) -> 0.9975 | KX7: =(AO7>0)*(MAX($KR7:KW7)+(MONTH(KX$3)=$J7)*MAX($KR7:KW7)*$I7) -> 0.9975 | KY7: =(AP7>0)*(MAX($KR7:KX7)+(MONTH(KY$3)=$J7)*MAX($KR7:KX7)*$I7) -> 0.9975 | KZ7: =(AQ7>0)*(MAX($KR7:KY7)+(MONTH(KZ$3)=$J7)*MAX($KR7:KY7)*$I7) -> 0.9975 | ... PT7: =(FK7>0)*(MAX($KR7:PS7)+(MONTH(PT$3)=$J7)*MAX($KR7:PS7)*$I7) -> 0 | PW7: =T7/12/(1+U7) -> 1.3879952 | PX7: =(FN7>0)*(MAX($PW7:PW7)+(MONTH(PX$3)=$V7)*MAX($PW7:PW7)*$U7) -> 0 | PY7: =(FO7>0)*(MAX($PW7:PX7)+(MONTH(PY$3)=$V7)*MAX($PW7:PX7)*$U7) -> 0 | PZ7: =(FP7>0)*(MAX($PW7:PY7)+(MONTH(PZ$3)=$V7)*MAX($PW7:PY7)*$U7) -> 0 | QA7: =(FQ7>0)*(MAX($PW7:PZ7)+(MONTH(QA$3)=$V7)*MAX($PW7:PZ7)*$U7) -> 0 | QB7: =(FR7>0)*(MAX($PW7:QA7)+(MONTH(QB$3)=$V7)*MAX($PW7:QA7)*$U7) -> 0 | QC7: =(FS7>0)*(MAX($PW7:QB7)+(MONTH(QC$3)=$V7)*MAX($PW7:QB7)*$U7) -> 0 | QD7: =(FT7>0)*(MAX($PW7:QC7)+(MONTH(QD$3)=$V7)*MAX($PW7:QC7)*$U7) -> 0 | QE7: =(FU7>0)*(MAX($PW7:QD7)+(MONTH(QE$3)=$V7)*MAX($PW7:QD7)*$U7) -> 0 | ... UY7: =(KO7>0)*(MAX($PW7:UX7)+(MONTH(UY$3)=$V7)*MAX($PW7:UX7)*$U7) -> 1.4729516 | VB7: =AJ7*KS7+FN7*PX7 -> 24039.75 | VC7: =AK7*KT7+FO7*PY7 -> 24039.75 | VD7: =AL7*KU7+FP7*PZ7 -> 24039.75 | VE7: =AM7*KV7+FQ7*QA7 -> 24039.75 | VF7: =AN7*KW7+FR7*QB7 -> 24039.75 | VG7: =AO7*KX7+FS7*QC7 -> 24039.75 | VH7: =AP7*KY7+FT7*QD7 -> 24039.75 | VI7: =AQ7*KZ7+FU7*QE7 -> 24039.75 | ... AAC7: =FK7*PT7+KO7*UY7 -> 35498.133 | AAF7: =(AAF$5=$R7)*$AA7*$D7 -> 0 | AAG7: =(AAG$5=$R7)*$AA7*$D7 -> 0 | AAH7: =(AAH$5=$R7)*$AA7*$D7 -> 0 | AAI7: =(AAI$5=$R7)*$AA7*$D7 -> 0 | AAJ7: =(AAJ$5=$R7)*$AA7*$D7 -> 0 | AAK7: =(AAK$5=$R7)*$AA7*$D7 -> 0 | AAL7: =(AAL$5=$R7)*$AA7*$D7 -> 0 | AAM7: =(AAM$5=$R7)*$AA7*$D7 -> 0 | ... AFG7: =(AFG$5=$R7)*$AA7*$D7 -> 0 | AFJ7: =(AJ7>0)*'Long-Term Leases'!K$17*$L7*$K7 -> 11267.238 | AFK7: =(AK7>0)*'Long-Term Leases'!L$17*$L7*$K7 -> 11267.238 | AFL7: =(AL7>0)*'Long-Term Leases'!M$17*$L7*$K7 -> 11267.238 | AFM7: =(AM7>0)*'Long-Term Leases'!N$17*$L7*$K7 -> 11267.238 | AFN7: =(AN7>0)*'Long-Term Leases'!O$17*$L7*$K7 -> 11267.238 | AFO7: =(AO7>0)*'Long-Term Leases'!P$17*$L7*$K7 -> 11267.238 | AFP7: =(AP7>0)*'Long-Term Leases'!Q$17*$L7*$K7 -> 11267.238 | AFQ7: =(AQ7>0)*'Long-Term Leases'!R$17*$L7*$K7 -> 11267.238 | ... AKK7: =(FK7>0)*'Long-Term Leases'!EL$17*$L7*$K7 -> 0 | AKN7: =(FN7>0)*'Long-Term Leases'!K$17*$X7*$W7 -> 0 | AKO7: =(FO7>0)*'Long-Term Leases'!L$17*$X7*$W7 -> 0 | AKP7: =(FP7>0)*'Long-Term Leases'!M$17*$X7*$W7 -> 0 | AKQ7: =(FQ7>0)*'Long-Term Leases'!N$17*$X7*$W7 -> 0 | AKR7: =(FR7>0)*'Long-Term Leases'!O$17*$X7*$W7 -> 0 | AKS7: =(FS7>0)*'Long-Term Leases'!P$17*$X7*$W7 -> 0 | AKT7: =(FT7>0)*'Long-Term Leases'!Q$17*$X7*$W7 -> 0 | AKU7: =(FU7>0)*'Long-Term Leases'!R$17*$X7*$W7 -> 0 | ... APO7: =(KO7>0)*'Long-Term Leases'!EL$17*$X7*$W7 -> 13734.701 | APR7: =(APR$5=$R7)*$AH7*$D7 -> 0 | APS7: =(APS$5=$R7)*$AH7*$D7 -> 0 | APT7: =(APT$5=$R7)*$AH7*$D7 -> 0 | APU7: =(APU$5=$R7)*$AH7*$D7 -> 0 | APV7: =(APV$5=$R7)*$AH7*$D7 -> 0 | APW7: =(APW$5=$R7)*$AH7*$D7 -> 0 | APX7: =(APX$5=$R7)*$AH7*$D7 -> 0 | APY7: =(APY$5=$R7)*$AH7*$D7 -> 0 | ... AUS7: =(AUS$5=$R7)*$AH7*$D7 -> 0
B8: 200 | C8: Farmer's Market | D8: 17850 | E8: 1 | F8: 36 | G8: 11.09 | H8: =+G8*D8 -> 197956.5 | I8: =$I$6 -> 0.02 | J8: 1 | K8: 1 | L8: =D8/$D$6 -> 0.13050631 | M8: 14.5 | N8: 0.02 | O8: 0.8 | P8: 12 | Q8: 120 | R8: =ROUNDUP((1-O8)*P8,0)+F8+1 -> 40 | S8: =+R8+Q8-1 -> 159 | T8: =M8*(1+N8)^(ROUNDUP(R8/12,0)-1) -> 15.387516 | U8: =$U$6 -> 0.02 | V8: =12-(ROUNDUP(R8/12,0)*12-R8) -> 4 | W8: =+K8 -> 1 | X8: =+L8 -> 0.13050631 | Y8: 9 | Z8: 3 | AA8: =ROUNDUP(O8*Z8+(1-O8)*Y8,0)*T8/12 -> 6.411465 | AB8: 25 | AC8: 10 | AD8: 0.06 | AE8: 0.03 | AF8: =AC8*O8+AB8*(1-O8) -> 13 | AG8: =(AE8*O8+AD8*(1-O8))*T8*Q8/12 -> 5.5395058 | AH8: =SUM(AF8:AG8) -> 18.539506 | AJ8: =AND(AJ$5>=$E8,AJ$5<=$F8)*$D8 -> 17850 | AK8: =AND(AK$5>=$E8,AK$5<=$F8)*$D8 -> 17850 | AL8: =AND(AL$5>=$E8,AL$5<=$F8)*$D8 -> 17850 | AM8: =AND(AM$5>=$E8,AM$5<=$F8)*$D8 -> 17850 | AN8: =AND(AN$5>=$E8,AN$5<=$F8)*$D8 -> 17850 | AO8: =AND(AO$5>=$E8,AO$5<=$F8)*$D8 -> 17850 | AP8: =AND(AP$5>=$E8,AP$5<=$F8)*$D8 -> 17850 | AQ8: =AND(AQ$5>=$E8,AQ$5<=$F8)*$D8 -> 17850 | ... FK8: =AND(FK$5>=$E8,FK$5<=$F8)*$D8 -> 0 | FN8: =AND(FN$5>=$R8,FN$5<=$S8)*$D8 -> 0 | FO8: =AND(FO$5>=$R8,FO$5<=$S8)*$D8 -> 0 | FP8: =AND(FP$5>=$R8,FP$5<=$S8)*$D8 -> 0 | FQ8: =AND(FQ$5>=$R8,FQ$5<=$S8)*$D8 -> 0 | FR8: =AND(FR$5>=$R8,FR$5<=$S8)*$D8 -> 0 | FS8: =AND(FS$5>=$R8,FS$5<=$S8)*$D8 -> 0 | FT8: =AND(FT$5>=$R8,FT$5<=$S8)*$D8 -> 0 | FU8: =AND(FU$5>=$R8,FU$5<=$S8)*$D8 -> 0 | ... KO8: =AND(KO$5>=$R8,KO$5<=$S8)*$D8 -> 17850 | KR8: =IF(AND(J8>1,$E8=1),G8/12,G8/12/(1+$I8)) -> 0.90604575 | KS8: =(AJ8>0)*(MAX($KR8:KR8)+(MONTH(KS$3)=$J8)*MAX($KR8:KR8)*$I8) -> 0.92416667 | KT8: =(AK8>0)*(MAX($KR8:KS8)+(MONTH(KT$3)=$J8)*MAX($KR8:KS8)*$I8) -> 0.92416667 | KU8: =(AL8>0)*(MAX($KR8:KT8)+(MONTH(KU$3)=$J8)*MAX($KR8:KT8)*$I8) -> 0.92416667 | KV8: =(AM8>0)*(MAX($KR8:KU8)+(MONTH(KV$3)=$J8)*MAX($KR8:KU8)*$I8) -> 0.92416667 | KW8: =(AN8>0)*(MAX($KR8:KV8)+(MONTH(KW$3)=$J8)*MAX($KR8:KV8)*$I8) -> 0.92416667 | KX8: =(AO8>0)*(MAX($KR8:KW8)+(MONTH(KX$3)=$J8)*MAX($KR8:KW8)*$I8) -> 0.92416667 | KY8: =(AP8>0)*(MAX($KR8:KX8)+(MONTH(KY$3)=$J8)*MAX($KR8:KX8)*$I8) -> 0.92416667 | KZ8: =(AQ8>0)*(MAX($KR8:KY8)+(MONTH(KZ$3)=$J8)*MAX($KR8:KY8)*$I8) -> 0.92416667 | ... PT8: =(FK8>0)*(MAX($KR8:PS8)+(MONTH(PT$3)=$J8)*MAX($KR8:PS8)*$I8) -> 0 | PW8: =T8/12/(1+U8) -> 1.25715 | PX8: =(FN8>0)*(MAX($PW8:PW8)+(MONTH(PX$3)=$V8)*MAX($PW8:PW8)*$U8) -> 0 | PY8: =(FO8>0)*(MAX($PW8:PX8)+(MONTH(PY$3)=$V8)*MAX($PW8:PX8)*$U8) -> 0 | PZ8: =(FP8>0)*(MAX($PW8:PY8)+(MONTH(PZ$3)=$V8)*MAX($PW8:PY8)*$U8) -> 0 | QA8: =(FQ8>0)*(MAX($PW8:PZ8)+(MONTH(QA$3)=$V8)*MAX($PW8:PZ8)*$U8) -> 0 | QB8: =(FR8>0)*(MAX($PW8:QA8)+(MONTH(QB$3)=$V8)*MAX($PW8:QA8)*$U8) -> 0 | QC8: =(FS8>0)*(MAX($PW8:QB8)+(MONTH(QC$3)=$V8)*MAX($PW8:QB8)*$U8) -> 0 | QD8: =(FT8>0)*(MAX($PW8:QC8)+(MONTH(QD$3)=$V8)*MAX($PW8:QC8)*$U8) -> 0 | QE8: =(FU8>0)*(MAX($PW8:QD8)+(MONTH(QE$3)=$V8)*MAX($PW8:QD8)*$U8) -> 0 | ... UY8: =(KO8>0)*(MAX($PW8:UX8)+(MONTH(UY$3)=$V8)*MAX($PW8:UX8)*$U8) -> 1.4729516 | VB8: =AJ8*KS8+FN8*PX8 -> 16496.375 | VC8: =AK8*KT8+FO8*PY8 -> 16496.375 | VD8: =AL8*KU8+FP8*PZ8 -> 16496.375 | VE8: =AM8*KV8+FQ8*QA8 -> 16496.375 | VF8: =AN8*KW8+FR8*QB8 -> 16496.375 | VG8: =AO8*KX8+FS8*QC8 -> 16496.375 | VH8: =AP8*KY8+FT8*QD8 -> 16496.375 | VI8: =AQ8*KZ8+FU8*QE8 -> 16496.375 | ... AAC8: =FK8*PT8+KO8*UY8 -> 26292.186 | AAF8: =(AAF$5=$R8)*$AA8*$D8 -> 0 | AAG8: =(AAG$5=$R8)*$AA8*$D8 -> 0 | AAH8: =(AAH$5=$R8)*$AA8*$D8 -> 0 | AAI8: =(AAI$5=$R8)*$AA8*$D8 -> 0 | AAJ8: =(AAJ$5=$R8)*$AA8*$D8 -> 0 | AAK8: =(AAK$5=$R8)*$AA8*$D8 -> 0 | AAL8: =(AAL$5=$R8)*$AA8*$D8 -> 0 | AAM8: =(AAM$5=$R8)*$AA8*$D8 -> 0 | ... AFG8: =(AFG$5=$R8)*$AA8*$D8 -> 0 | AFJ8: =(AJ8>0)*'Long-Term Leases'!K$17*$L8*$K8 -> 8345.2366 | AFK8: =(AK8>0)*'Long-Term Leases'!L$17*$L8*$K8 -> 8345.2366 | AFL8: =(AL8>0)*'Long-Term Leases'!M$17*$L8*$K8 -> 8345.2366 | AFM8: =(AM8>0)*'Long-Term Leases'!N$17*$L8*$K8 -> 8345.2366 | AFN8: =(AN8>0)*'Long-Term Leases'!O$17*$L8*$K8 -> 8345.2366 | AFO8: =(AO8>0)*'Long-Term Leases'!P$17*$L8*$K8 -> 8345.2366 | AFP8: =(AP8>0)*'Long-Term Leases'!Q$17*$L8*$K8 -> 8345.2366 | AFQ8: =(AQ8>0)*'Long-Term Leases'!R$17*$L8*$K8 -> 8345.2366 | ... AKK8: =(FK8>0)*'Long-Term Leases'!EL$17*$L8*$K8 -> 0 | AKN8: =(FN8>0)*'Long-Term Leases'!K$17*$X8*$W8 -> 0 | AKO8: =(FO8>0)*'Long-Term Leases'!L$17*$X8*$W8 -> 0 | AKP8: =(FP8>0)*'Long-Term Leases'!M$17*$X8*$W8 -> 0 | AKQ8: =(FQ8>0)*'Long-Term Leases'!N$17*$X8*$W8 -> 0 | AKR8: =(FR8>0)*'Long-Term Leases'!O$17*$X8*$W8 -> 0 | AKS8: =(FS8>0)*'Long-Term Leases'!P$17*$X8*$W8 -> 0 | AKT8: =(FT8>0)*'Long-Term Leases'!Q$17*$X8*$W8 -> 0 | AKU8: =(FU8>0)*'Long-Term Leases'!R$17*$X8*$W8 -> 0 | ... APO8: =(KO8>0)*'Long-Term Leases'!EL$17*$X8*$W8 -> 10172.797 | APR8: =(APR$5=$R8)*$AH8*$D8 -> 0 | APS8: =(APS$5=$R8)*$AH8*$D8 -> 0 | APT8: =(APT$5=$R8)*$AH8*$D8 -> 0 | APU8: =(APU$5=$R8)*$AH8*$D8 -> 0 | APV8: =(APV$5=$R8)*$AH8*$D8 -> 0 | APW8: =(APW$5=$R8)*$AH8*$D8 -> 0 | APX8: =(APX$5=$R8)*$AH8*$D8 -> 0 | APY8: =(APY$5=$R8)*$AH8*$D8 -> 0 | ... AUS8: =(AUS$5=$R8)*$AH8*$D8 -> 0
B9: 300 | C9: Wheels On Us | D9: 10400 | E9: 1 | F9: 48 | G9: 18 | H9: =+G9*D9 -> 187200 | I9: =$I$6 -> 0.02 | J9: 1 | K9: 1 | L9: =D9/$D$6 -> 0.076037288 | M9: 14.5 | N9: 0.02 | O9: 0.8 | P9: 12 | Q9: 120 | R9: =ROUNDUP((1-O9)*P9,0)+F9+1 -> 52 | S9: =+R9+Q9-1 -> 171 | T9: =M9*(1+N9)^(ROUNDUP(R9/12,0)-1) -> 15.695266 | U9: =$U$6 -> 0.02 | V9: =12-(ROUNDUP(R9/12,0)*12-R9) -> 4 | W9: =+K9 -> 1 | X9: =+L9 -> 0.076037288 | Y9: 9 | Z9: 3 | AA9: =ROUNDUP(O9*Z9+(1-O9)*Y9,0)*T9/12 -> 6.5396943 | AB9: 25 | AC9: 10 | AD9: 0.06 | AE9: 0.03 | AF9: =AC9*O9+AB9*(1-O9) -> 13 | AG9: =(AE9*O9+AD9*(1-O9))*T9*Q9/12 -> 5.6502959 | AH9: =SUM(AF9:AG9) -> 18.650296 | AJ9: =AND(AJ$5>=$E9,AJ$5<=$F9)*$D9 -> 10400 | AK9: =AND(AK$5>=$E9,AK$5<=$F9)*$D9 -> 10400 | AL9: =AND(AL$5>=$E9,AL$5<=$F9)*$D9 -> 10400 | AM9: =AND(AM$5>=$E9,AM$5<=$F9)*$D9 -> 10400 | AN9: =AND(AN$5>=$E9,AN$5<=$F9)*$D9 -> 10400 | AO9: =AND(AO$5>=$E9,AO$5<=$F9)*$D9 -> 10400 | AP9: =AND(AP$5>=$E9,AP$5<=$F9)*$D9 -> 10400 | AQ9: =AND(AQ$5>=$E9,AQ$5<=$F9)*$D9 -> 10400 | ... FK9: =AND(FK$5>=$E9,FK$5<=$F9)*$D9 -> 0 | FN9: =AND(FN$5>=$R9,FN$5<=$S9)*$D9 -> 0 | FO9: =AND(FO$5>=$R9,FO$5<=$S9)*$D9 -> 0 | FP9: =AND(FP$5>=$R9,FP$5<=$S9)*$D9 -> 0 | FQ9: =AND(FQ$5>=$R9,FQ$5<=$S9)*$D9 -> 0 | FR9: =AND(FR$5>=$R9,FR$5<=$S9)*$D9 -> 0 | FS9: =AND(FS$5>=$R9,FS$5<=$S9)*$D9 -> 0 | FT9: =AND(FT$5>=$R9,FT$5<=$S9)*$D9 -> 0 | FU9: =AND(FU$5>=$R9,FU$5<=$S9)*$D9 -> 0 | ... KO9: =AND(KO$5>=$R9,KO$5<=$S9)*$D9 -> 10400 | KR9: =IF(AND(J9>1,$E9=1),G9/12,G9/12/(1+$I9)) -> 1.4705882 | KS9: =(AJ9>0)*(MAX($KR9:KR9)+(MONTH(KS$3)=$J9)*MAX($KR9:KR9)*$I9) -> 1.5 | KT9: =(AK9>0)*(MAX($KR9:KS9)+(MONTH(KT$3)=$J9)*MAX($KR9:KS9)*$I9) -> 1.5 | KU9: =(AL9>0)*(MAX($KR9:KT9)+(MONTH(KU$3)=$J9)*MAX($KR9:KT9)*$I9) -> 1.5 | KV9: =(AM9>0)*(MAX($KR9:KU9)+(MONTH(KV$3)=$J9)*MAX($KR9:KU9)*$I9) -> 1.5 | KW9: =(AN9>0)*(MAX($KR9:KV9)+(MONTH(KW$3)=$J9)*MAX($KR9:KV9)*$I9) -> 1.5 | KX9: =(AO9>0)*(MAX($KR9:KW9)+(MONTH(KX$3)=$J9)*MAX($KR9:KW9)*$I9) -> 1.5 | KY9: =(AP9>0)*(MAX($KR9:KX9)+(MONTH(KY$3)=$J9)*MAX($KR9:KX9)*$I9) -> 1.5 | KZ9: =(AQ9>0)*(MAX($KR9:KY9)+(MONTH(KZ$3)=$J9)*MAX($KR9:KY9)*$I9) -> 1.5 | ... PT9: =(FK9>0)*(MAX($KR9:PS9)+(MONTH(PT$3)=$J9)*MAX($KR9:PS9)*$I9) -> 0 | PW9: =T9/12/(1+U9) -> 1.282293 | PX9: =(FN9>0)*(MAX($PW9:PW9)+(MONTH(PX$3)=$V9)*MAX($PW9:PW9)*$U9) -> 0 | PY9: =(FO9>0)*(MAX($PW9:PX9)+(MONTH(PY$3)=$V9)*MAX($PW9:PX9)*$U9) -> 0 | PZ9: =(FP9>0)*(MAX($PW9:PY9)+(MONTH(PZ$3)=$V9)*MAX($PW9:PY9)*$U9) -> 0 | QA9: =(FQ9>0)*(MAX($PW9:PZ9)+(MONTH(QA$3)=$V9)*MAX($PW9:PZ9)*$U9) -> 0 | QB9: =(FR9>0)*(MAX($PW9:QA9)+(MONTH(QB$3)=$V9)*MAX($PW9:QA9)*$U9) -> 0 | QC9: =(FS9>0)*(MAX($PW9:QB9)+(MONTH(QC$3)=$V9)*MAX($PW9:QB9)*$U9) -> 0 | QD9: =(FT9>0)*(MAX($PW9:QC9)+(MONTH(QD$3)=$V9)*MAX($PW9:QC9)*$U9) -> 0 | QE9: =(FU9>0)*(MAX($PW9:QD9)+(MONTH(QE$3)=$V9)*MAX($PW9:QD9)*$U9) -> 0 | ... UY9: =(KO9>0)*(MAX($PW9:UX9)+(MONTH(UY$3)=$V9)*MAX($PW9:UX9)*$U9) -> 1.4729516 | VB9: =AJ9*KS9+FN9*PX9 -> 15600 | VC9: =AK9*KT9+FO9*PY9 -> 15600 | VD9: =AL9*KU9+FP9*PZ9 -> 15600 | VE9: =AM9*KV9+FQ9*QA9 -> 15600 | VF9: =AN9*KW9+FR9*QB9 -> 15600 | VG9: =AO9*KX9+FS9*QC9 -> 15600 | VH9: =AP9*KY9+FT9*QD9 -> 15600 | VI9: =AQ9*KZ9+FU9*QE9 -> 15600 | ... AAC9: =FK9*PT9+KO9*UY9 -> 15318.697 | AAF9: =(AAF$5=$R9)*$AA9*$D9 -> 0 | AAG9: =(AAG$5=$R9)*$AA9*$D9 -> 0 | AAH9: =(AAH$5=$R9)*$AA9*$D9 -> 0 | AAI9: =(AAI$5=$R9)*$AA9*$D9 -> 0 | AAJ9: =(AAJ$5=$R9)*$AA9*$D9 -> 0 | AAK9: =(AAK$5=$R9)*$AA9*$D9 -> 0 | AAL9: =(AAL$5=$R9)*$AA9*$D9 -> 0 | AAM9: =(AAM$5=$R9)*$AA9*$D9 -> 0 | ... AFG9: =(AFG$5=$R9)*$AA9*$D9 -> 0 | AFJ9: =(AJ9>0)*'Long-Term Leases'!K$17*$L9*$K9 -> 4862.2107 | AFK9: =(AK9>0)*'Long-Term Leases'!L$17*$L9*$K9 -> 4862.2107 | AFL9: =(AL9>0)*'Long-Term Leases'!M$17*$L9*$K9 -> 4862.2107 | AFM9: =(AM9>0)*'Long-Term Leases'!N$17*$L9*$K9 -> 4862.2107 | AFN9: =(AN9>0)*'Long-Term Leases'!O$17*$L9*$K9 -> 4862.2107 | AFO9: =(AO9>0)*'Long-Term Leases'!P$17*$L9*$K9 -> 4862.2107 | AFP9: =(AP9>0)*'Long-Term Leases'!Q$17*$L9*$K9 -> 4862.2107 | AFQ9: =(AQ9>0)*'Long-Term Leases'!R$17*$L9*$K9 -> 4862.2107 | ... AKK9: =(FK9>0)*'Long-Term Leases'!EL$17*$L9*$K9 -> 0 | AKN9: =(FN9>0)*'Long-Term Leases'!K$17*$X9*$W9 -> 0 | AKO9: =(FO9>0)*'Long-Term Leases'!L$17*$X9*$W9 -> 0 | AKP9: =(FP9>0)*'Long-Term Leases'!M$17*$X9*$W9 -> 0 | AKQ9: =(FQ9>0)*'Long-Term Leases'!N$17*$X9*$W9 -> 0 | AKR9: =(FR9>0)*'Long-Term Leases'!O$17*$X9*$W9 -> 0 | AKS9: =(FS9>0)*'Long-Term Leases'!P$17*$X9*$W9 -> 0 | AKT9: =(FT9>0)*'Long-Term Leases'!Q$17*$X9*$W9 -> 0 | AKU9: =(FU9>0)*'Long-Term Leases'!R$17*$X9*$W9 -> 0 | ... APO9: =(KO9>0)*'Long-Term Leases'!EL$17*$X9*$W9 -> 5927.0077 | APR9: =(APR$5=$R9)*$AH9*$D9 -> 0 | APS9: =(APS$5=$R9)*$AH9*$D9 -> 0 | APT9: =(APT$5=$R9)*$AH9*$D9 -> 0 | APU9: =(APU$5=$R9)*$AH9*$D9 -> 0 | APV9: =(APV$5=$R9)*$AH9*$D9 -> 0 | APW9: =(APW$5=$R9)*$AH9*$D9 -> 0 | APX9: =(APX$5=$R9)*$AH9*$D9 -> 0 | APY9: =(APY$5=$R9)*$AH9*$D9 -> 0 | ... AUS9: =(AUS$5=$R9)*$AH9*$D9 -> 0
B10: 400 | C10: Trader Mart | D10: 45830 | E10: 1 | F10: 113 | G10: 16.39 | H10: =+G10*D10 -> 751153.7 | I10: =$I$6 -> 0.02 | J10: 6 | K10: 1 | L10: =D10/$D$6 -> 0.33507585 | M10: 13 | N10: 0.02 | O10: 0.9 | P10: 18 | Q10: 180 | R10: =ROUNDUP((1-O10)*P10,0)+F10+1 -> 116 | S10: =+R10+Q10-1 -> 295 | T10: =M10*(1+N10)^(ROUNDUP(R10/12,0)-1) -> 15.536203 | U10: =$U$6 -> 0.02 | V10: =12-(ROUNDUP(R10/12,0)*12-R10) -> 8 | W10: =+K10 -> 1 | X10: =+L10 -> 0.33507585 | Y10: 12 | Z10: 6 | AA10: =ROUNDUP(O10*Z10+(1-O10)*Y10,0)*T10/12 -> 9.0627853 | AB10: 20 | AC10: 7.5 | AD10: 0.06 | AE10: 0.03 | AF10: =AC10*O10+AB10*(1-O10) -> 8.75 | AG10: =(AE10*O10+AD10*(1-O10))*T10*Q10/12 -> 7.6904207 | AH10: =SUM(AF10:AG10) -> 16.440421 | AJ10: =AND(AJ$5>=$E10,AJ$5<=$F10)*$D10 -> 45830 | AK10: =AND(AK$5>=$E10,AK$5<=$F10)*$D10 -> 45830 | AL10: =AND(AL$5>=$E10,AL$5<=$F10)*$D10 -> 45830 | AM10: =AND(AM$5>=$E10,AM$5<=$F10)*$D10 -> 45830 | AN10: =AND(AN$5>=$E10,AN$5<=$F10)*$D10 -> 45830 | AO10: =AND(AO$5>=$E10,AO$5<=$F10)*$D10 -> 45830 | AP10: =AND(AP$5>=$E10,AP$5<=$F10)*$D10 -> 45830 | AQ10: =AND(AQ$5>=$E10,AQ$5<=$F10)*$D10 -> 45830 | ... FK10: =AND(FK$5>=$E10,FK$5<=$F10)*$D10 -> 0 | FN10: =AND(FN$5>=$R10,FN$5<=$S10)*$D10 -> 0 | FO10: =AND(FO$5>=$R10,FO$5<=$S10)*$D10 -> 0 | FP10: =AND(FP$5>=$R10,FP$5<=$S10)*$D10 -> 0 | FQ10: =AND(FQ$5>=$R10,FQ$5<=$S10)*$D10 -> 0 | FR10: =AND(FR$5>=$R10,FR$5<=$S10)*$D10 -> 0 | FS10: =AND(FS$5>=$R10,FS$5<=$S10)*$D10 -> 0 | FT10: =AND(FT$5>=$R10,FT$5<=$S10)*$D10 -> 0 | FU10: =AND(FU$5>=$R10,FU$5<=$S10)*$D10 -> 0 | ... KO10: =AND(KO$5>=$R10,KO$5<=$S10)*$D10 -> 45830 | KR10: =IF(AND(J10>1,$E10=1),G10/12,G10/12/(1+$I10)) -> 1.3658333 | KS10: =(AJ10>0)*(MAX($KR10:KR10)+(MONTH(KS$3)=$J10)*MAX($KR10:KR10)*$I10) -> 1.3658333 | KT10: =(AK10>0)*(MAX($KR10:KS10)+(MONTH(KT$3)=$J10)*MAX($KR10:KS10)*$I10) -> 1.3658333 | KU10: =(AL10>0)*(MAX($KR10:KT10)+(MONTH(KU$3)=$J10)*MAX($KR10:KT10)*$I10) -> 1.3658333 | KV10: =(AM10>0)*(MAX($KR10:KU10)+(MONTH(KV$3)=$J10)*MAX($KR10:KU10)*$I10) -> 1.3658333 | KW10: =(AN10>0)*(MAX($KR10:KV10)+(MONTH(KW$3)=$J10)*MAX($KR10:KV10)*$I10) -> 1.3658333 | KX10: =(AO10>0)*(MAX($KR10:KW10)+(MONTH(KX$3)=$J10)*MAX($KR10:KW10)*$I10) -> 1.39315 | KY10: =(AP10>0)*(MAX($KR10:KX10)+(MONTH(KY$3)=$J10)*MAX($KR10:KX10)*$I10) -> 1.39315 | KZ10: =(AQ10>0)*(MAX($KR10:KY10)+(MONTH(KZ$3)=$J10)*MAX($KR10:KY10)*$I10) -> 1.39315 | ... PT10: =(FK10>0)*(MAX($KR10:PS10)+(MONTH(PT$3)=$J10)*MAX($KR10:PS10)*$I10) -> 0 | PW10: =T10/12/(1+U10) -> 1.2692977 | PX10: =(FN10>0)*(MAX($PW10:PW10)+(MONTH(PX$3)=$V10)*MAX($PW10:PW10)*$U10) -> 0 | PY10: =(FO10>0)*(MAX($PW10:PX10)+(MONTH(PY$3)=$V10)*MAX($PW10:PX10)*$U10) -> 0 | PZ10: =(FP10>0)*(MAX($PW10:PY10)+(MONTH(PZ$3)=$V10)*MAX($PW10:PY10)*$U10) -> 0 | QA10: =(FQ10>0)*(MAX($PW10:PZ10)+(MONTH(QA$3)=$V10)*MAX($PW10:PZ10)*$U10) -> 0 | QB10: =(FR10>0)*(MAX($PW10:QA10)+(MONTH(QB$3)=$V10)*MAX($PW10:QA10)*$U10) -> 0 | QC10: =(FS10>0)*(MAX($PW10:QB10)+(MONTH(QC$3)=$V10)*MAX($PW10:QB10)*$U10) -> 0 | QD10: =(FT10>0)*(MAX($PW10:QC10)+(MONTH(QD$3)=$V10)*MAX($PW10:QC10)*$U10) -> 0 | QE10: =(FU10>0)*(MAX($PW10:QD10)+(MONTH(QE$3)=$V10)*MAX($PW10:QD10)*$U10) -> 0 | ... UY10: =(KO10>0)*(MAX($PW10:UX10)+(MONTH(UY$3)=$V10)*MAX($PW10:UX10)*$U10) -> 1.3205773 | VB10: =AJ10*KS10+FN10*PX10 -> 62596.142 | VC10: =AK10*KT10+FO10*PY10 -> 62596.142 | VD10: =AL10*KU10+FP10*PZ10 -> 62596.142 | VE10: =AM10*KV10+FQ10*QA10 -> 62596.142 | VF10: =AN10*KW10+FR10*QB10 -> 62596.142 | VG10: =AO10*KX10+FS10*QC10 -> 63848.065 | VH10: =AP10*KY10+FT10*QD10 -> 63848.065 | VI10: =AQ10*KZ10+FU10*QE10 -> 63848.065 | ... AAC10: =FK10*PT10+KO10*UY10 -> 60522.057 | AAF10: =(AAF$5=$R10)*$AA10*$D10 -> 0 | AAG10: =(AAG$5=$R10)*$AA10*$D10 -> 0 | AAH10: =(AAH$5=$R10)*$AA10*$D10 -> 0 | AAI10: =(AAI$5=$R10)*$AA10*$D10 -> 0 | AAJ10: =(AAJ$5=$R10)*$AA10*$D10 -> 0 | AAK10: =(AAK$5=$R10)*$AA10*$D10 -> 0 | AAL10: =(AAL$5=$R10)*$AA10*$D10 -> 0 | AAM10: =(AAM$5=$R10)*$AA10*$D10 -> 0 | ... AFG10: =(AFG$5=$R10)*$AA10*$D10 -> 0 | AFJ10: =(AJ10>0)*'Long-Term Leases'!K$17*$L10*$K10 -> 21426.453 | AFK10: =(AK10>0)*'Long-Term Leases'!L$17*$L10*$K10 -> 21426.453 | AFL10: =(AL10>0)*'Long-Term Leases'!M$17*$L10*$K10 -> 21426.453 | AFM10: =(AM10>0)*'Long-Term Leases'!N$17*$L10*$K10 -> 21426.453 | AFN10: =(AN10>0)*'Long-Term Leases'!O$17*$L10*$K10 -> 21426.453 | AFO10: =(AO10>0)*'Long-Term Leases'!P$17*$L10*$K10 -> 21426.453 | AFP10: =(AP10>0)*'Long-Term Leases'!Q$17*$L10*$K10 -> 21426.453 | AFQ10: =(AQ10>0)*'Long-Term Leases'!R$17*$L10*$K10 -> 21426.453 | ... AKK10: =(FK10>0)*'Long-Term Leases'!EL$17*$L10*$K10 -> 0 | AKN10: =(FN10>0)*'Long-Term Leases'!K$17*$X10*$W10 -> 0 | AKO10: =(FO10>0)*'Long-Term Leases'!L$17*$X10*$W10 -> 0 | AKP10: =(FP10>0)*'Long-Term Leases'!M$17*$X10*$W10 -> 0 | AKQ10: =(FQ10>0)*'Long-Term Leases'!N$17*$X10*$W10 -> 0 | AKR10: =(FR10>0)*'Long-Term Leases'!O$17*$X10*$W10 -> 0 | AKS10: =(FS10>0)*'Long-Term Leases'!P$17*$X10*$W10 -> 0 | AKT10: =(FT10>0)*'Long-Term Leases'!Q$17*$X10*$W10 -> 0 | AKU10: =(FU10>0)*'Long-Term Leases'!R$17*$X10*$W10 -> 0 | ... APO10: =(KO10>0)*'Long-Term Leases'!EL$17*$X10*$W10 -> 26118.727 | APR10: =(APR$5=$R10)*$AH10*$D10 -> 0 | APS10: =(APS$5=$R10)*$AH10*$D10 -> 0 | APT10: =(APT$5=$R10)*$AH10*$D10 -> 0 | APU10: =(APU$5=$R10)*$AH10*$D10 -> 0 | APV10: =(APV$5=$R10)*$AH10*$D10 -> 0 | APW10: =(APW$5=$R10)*$AH10*$D10 -> 0 | APX10: =(APX$5=$R10)*$AH10*$D10 -> 0 | APY10: =(APY$5=$R10)*$AH10*$D10 -> 0 | ... AUS10: =(AUS$5=$R10)*$AH10*$D10 -> 0
B11: 500 | C11: Charlie's Chicken | D11: 8832 | E11: 1 | F11: 15 | G11: 16.39 | H11: =+G11*D11 -> 144756.48 | I11: =$I$6 -> 0.02 | J11: 4 | K11: 1 | L11: =D11/$D$6 -> 0.064573204 | M11: 16 | N11: 0.025 | O11: 0.7 | P11: 9 | Q11: 120 | R11: =ROUNDUP((1-O11)*P11,0)+F11+1 -> 19 | S11: =+R11+Q11-1 -> 138 | T11: =M11*(1+N11)^(ROUNDUP(R11/12,0)-1) -> 16.4 | U11: =$U$6 -> 0.02 | V11: =12-(ROUNDUP(R11/12,0)*12-R11) -> 7 | W11: =+K11 -> 1 | X11: =+L11 -> 0.064573204 | Y11: 6 | Z11: 0 | AA11: =ROUNDUP(O11*Z11+(1-O11)*Y11,0)*T11/12 -> 2.7333333 | AB11: 30 | AC11: 10 | AD11: 0.06 | AE11: 0.03 | AF11: =AC11*O11+AB11*(1-O11) -> 16 | AG11: =(AE11*O11+AD11*(1-O11))*T11*Q11/12 -> 6.396 | AH11: =SUM(AF11:AG11) -> 22.396 | AJ11: =AND(AJ$5>=$E11,AJ$5<=$F11)*$D11 -> 8832 | AK11: =AND(AK$5>=$E11,AK$5<=$F11)*$D11 -> 8832 | AL11: =AND(AL$5>=$E11,AL$5<=$F11)*$D11 -> 8832 | AM11: =AND(AM$5>=$E11,AM$5<=$F11)*$D11 -> 8832 | AN11: =AND(AN$5>=$E11,AN$5<=$F11)*$D11 -> 8832 | AO11: =AND(AO$5>=$E11,AO$5<=$F11)*$D11 -> 8832 | AP11: =AND(AP$5>=$E11,AP$5<=$F11)*$D11 -> 8832 | AQ11: =AND(AQ$5>=$E11,AQ$5<=$F11)*$D11 -> 8832 | ... FK11: =AND(FK$5>=$E11,FK$5<=$F11)*$D11 -> 0 | FN11: =AND(FN$5>=$R11,FN$5<=$S11)*$D11 -> 0 | FO11: =AND(FO$5>=$R11,FO$5<=$S11)*$D11 -> 0 | FP11: =AND(FP$5>=$R11,FP$5<=$S11)*$D11 -> 0 | FQ11: =AND(FQ$5>=$R11,FQ$5<=$S11)*$D11 -> 0 | FR11: =AND(FR$5>=$R11,FR$5<=$S11)*$D11 -> 0 | FS11: =AND(FS$5>=$R11,FS$5<=$S11)*$D11 -> 0 | FT11: =AND(FT$5>=$R11,FT$5<=$S11)*$D11 -> 0 | FU11: =AND(FU$5>=$R11,FU$5<=$S11)*$D11 -> 0 | ... KO11: =AND(KO$5>=$R11,KO$5<=$S11)*$D11 -> 8832 | KR11: =IF(AND(J11>1,$E11=1),G11/12,G11/12/(1+$I11)) -> 1.3658333 | KS11: =(AJ11>0)*(MAX($KR11:KR11)+(MONTH(KS$3)=$J11)*MAX($KR11:KR11)*$I11) -> 1.3658333 | KT11: =(AK11>0)*(MAX($KR11:KS11)+(MONTH(KT$3)=$J11)*MAX($KR11:KS11)*$I11) -> 1.3658333 | KU11: =(AL11>0)*(MAX($KR11:KT11)+(MONTH(KU$3)=$J11)*MAX($KR11:KT11)*$I11) -> 1.3658333 | KV11: =(AM11>0)*(MAX($KR11:KU11)+(MONTH(KV$3)=$J11)*MAX($KR11:KU11)*$I11) -> 1.39315 | KW11: =(AN11>0)*(MAX($KR11:KV11)+(MONTH(KW$3)=$J11)*MAX($KR11:KV11)*$I11) -> 1.39315 | KX11: =(AO11>0)*(MAX($KR11:KW11)+(MONTH(KX$3)=$J11)*MAX($KR11:KW11)*$I11) -> 1.39315 | KY11: =(AP11>0)*(MAX($KR11:KX11)+(MONTH(KY$3)=$J11)*MAX($KR11:KX11)*$I11) -> 1.39315 | KZ11: =(AQ11>0)*(MAX($KR11:KY11)+(MONTH(KZ$3)=$J11)*MAX($KR11:KY11)*$I11) -> 1.39315 | ... PT11: =(FK11>0)*(MAX($KR11:PS11)+(MONTH(PT$3)=$J11)*MAX($KR11:PS11)*$I11) -> 0 | PW11: =T11/12/(1+U11) -> 1.3398693 | PX11: =(FN11>0)*(MAX($PW11:PW11)+(MONTH(PX$3)=$V11)*MAX($PW11:PW11)*$U11) -> 0 | PY11: =(FO11>0)*(MAX($PW11:PX11)+(MONTH(PY$3)=$V11)*MAX($PW11:PX11)*$U11) -> 0 | PZ11: =(FP11>0)*(MAX($PW11:PY11)+(MONTH(PZ$3)=$V11)*MAX($PW11:PY11)*$U11) -> 0 | QA11: =(FQ11>0)*(MAX($PW11:PZ11)+(MONTH(QA$3)=$V11)*MAX($PW11:PZ11)*$U11) -> 0 | QB11: =(FR11>0)*(MAX($PW11:QA11)+(MONTH(QB$3)=$V11)*MAX($PW11:QA11)*$U11) -> 0 | QC11: =(FS11>0)*(MAX($PW11:QB11)+(MONTH(QC$3)=$V11)*MAX($PW11:QB11)*$U11) -> 0 | QD11: =(FT11>0)*(MAX($PW11:QC11)+(MONTH(QD$3)=$V11)*MAX($PW11:QC11)*$U11) -> 0 | QE11: =(FU11>0)*(MAX($PW11:QD11)+(MONTH(QE$3)=$V11)*MAX($PW11:QD11)*$U11) -> 0 | ... UY11: =(KO11>0)*(MAX($PW11:UX11)+(MONTH(UY$3)=$V11)*MAX($PW11:UX11)*$U11) -> 1.6332932 | VB11: =AJ11*KS11+FN11*PX11 -> 12063.04 | VC11: =AK11*KT11+FO11*PY11 -> 12063.04 | VD11: =AL11*KU11+FP11*PZ11 -> 12063.04 | VE11: =AM11*KV11+FQ11*QA11 -> 12304.301 | VF11: =AN11*KW11+FR11*QB11 -> 12304.301 | VG11: =AO11*KX11+FS11*QC11 -> 12304.301 | VH11: =AP11*KY11+FT11*QD11 -> 12304.301 | VI11: =AQ11*KZ11+FU11*QE11 -> 12304.301 | ... AAC11: =FK11*PT11+KO11*UY11 -> 14425.245 | AAF11: =(AAF$5=$R11)*$AA11*$D11 -> 0 | AAG11: =(AAG$5=$R11)*$AA11*$D11 -> 0 | AAH11: =(AAH$5=$R11)*$AA11*$D11 -> 0 | AAI11: =(AAI$5=$R11)*$AA11*$D11 -> 0 | AAJ11: =(AAJ$5=$R11)*$AA11*$D11 -> 0 | AAK11: =(AAK$5=$R11)*$AA11*$D11 -> 0 | AAL11: =(AAL$5=$R11)*$AA11*$D11 -> 0 | AAM11: =(AAM$5=$R11)*$AA11*$D11 -> 0 | ... AFG11: =(AFG$5=$R11)*$AA11*$D11 -> 0 | AFJ11: =(AJ11>0)*'Long-Term Leases'!K$17*$L11*$K11 -> 4129.1389 | AFK11: =(AK11>0)*'Long-Term Leases'!L$17*$L11*$K11 -> 4129.1389 | AFL11: =(AL11>0)*'Long-Term Leases'!M$17*$L11*$K11 -> 4129.1389 | AFM11: =(AM11>0)*'Long-Term Leases'!N$17*$L11*$K11 -> 4129.1389 | AFN11: =(AN11>0)*'Long-Term Leases'!O$17*$L11*$K11 -> 4129.1389 | AFO11: =(AO11>0)*'Long-Term Leases'!P$17*$L11*$K11 -> 4129.1389 | AFP11: =(AP11>0)*'Long-Term Leases'!Q$17*$L11*$K11 -> 4129.1389 | AFQ11: =(AQ11>0)*'Long-Term Leases'!R$17*$L11*$K11 -> 4129.1389 | ... AKK11: =(FK11>0)*'Long-Term Leases'!EL$17*$L11*$K11 -> 0 | AKN11: =(FN11>0)*'Long-Term Leases'!K$17*$X11*$W11 -> 0 | AKO11: =(FO11>0)*'Long-Term Leases'!L$17*$X11*$W11 -> 0 | AKP11: =(FP11>0)*'Long-Term Leases'!M$17*$X11*$W11 -> 0 | AKQ11: =(FQ11>0)*'Long-Term Leases'!N$17*$X11*$W11 -> 0 | AKR11: =(FR11>0)*'Long-Term Leases'!O$17*$X11*$W11 -> 0 | AKS11: =(FS11>0)*'Long-Term Leases'!P$17*$X11*$W11 -> 0 | AKT11: =(FT11>0)*'Long-Term Leases'!Q$17*$X11*$W11 -> 0 | AKU11: =(FU11>0)*'Long-Term Leases'!R$17*$X11*$W11 -> 0 | ... APO11: =(KO11>0)*'Long-Term Leases'!EL$17*$X11*$W11 -> 5033.3973 | APR11: =(APR$5=$R11)*$AH11*$D11 -> 0 | APS11: =(APS$5=$R11)*$AH11*$D11 -> 0 | APT11: =(APT$5=$R11)*$AH11*$D11 -> 0 | APU11: =(APU$5=$R11)*$AH11*$D11 -> 0 | APV11: =(APV$5=$R11)*$AH11*$D11 -> 0 | APW11: =(APW$5=$R11)*$AH11*$D11 -> 0 | APX11: =(APX$5=$R11)*$AH11*$D11 -> 0 | APY11: =(APY$5=$R11)*$AH11*$D11 -> 0 | ... AUS11: =(AUS$5=$R11)*$AH11*$D11 -> 0
B12: 600 | C12: Fitness Fantasy | D12: 15864 | E12: 1 | F12: 44 | G12: 10.34 | H12: =+G12*D12 -> 164033.76 | I12: =$I$6 -> 0.02 | J12: 9 | K12: 1 | L12: =D12/$D$6 -> 0.11598611 | M12: 14.5 | N12: 0.02 | O12: 0.8 | P12: 12 | Q12: 120 | R12: =ROUNDUP((1-O12)*P12,0)+F12+1 -> 48 | S12: =+R12+Q12-1 -> 167 | T12: =M12*(1+N12)^(ROUNDUP(R12/12,0)-1) -> 15.387516 | U12: =$U$6 -> 0.02 | V12: =12-(ROUNDUP(R12/12,0)*12-R12) -> 12 | W12: =+K12 -> 1 | X12: =+L12 -> 0.11598611 | Y12: 9 | Z12: 3 | AA12: =ROUNDUP(O12*Z12+(1-O12)*Y12,0)*T12/12 -> 6.411465 | AB12: 25 | AC12: 10 | AD12: 0.06 | AE12: 0.03 | AF12: =AC12*O12+AB12*(1-O12) -> 13 | AG12: =(AE12*O12+AD12*(1-O12))*T12*Q12/12 -> 5.5395058 | AH12: =SUM(AF12:AG12) -> 18.539506 | AJ12: =AND(AJ$5>=$E12,AJ$5<=$F12)*$D12 -> 15864 | AK12: =AND(AK$5>=$E12,AK$5<=$F12)*$D12 -> 15864 | AL12: =AND(AL$5>=$E12,AL$5<=$F12)*$D12 -> 15864 | AM12: =AND(AM$5>=$E12,AM$5<=$F12)*$D12 -> 15864 | AN12: =AND(AN$5>=$E12,AN$5<=$F12)*$D12 -> 15864 | AO12: =AND(AO$5>=$E12,AO$5<=$F12)*$D12 -> 15864 | AP12: =AND(AP$5>=$E12,AP$5<=$F12)*$D12 -> 15864 | AQ12: =AND(AQ$5>=$E12,AQ$5<=$F12)*$D12 -> 15864 | ... FK12: =AND(FK$5>=$E12,FK$5<=$F12)*$D12 -> 0 | FN12: =AND(FN$5>=$R12,FN$5<=$S12)*$D12 -> 0 | FO12: =AND(FO$5>=$R12,FO$5<=$S12)*$D12 -> 0 | FP12: =AND(FP$5>=$R12,FP$5<=$S12)*$D12 -> 0 | FQ12: =AND(FQ$5>=$R12,FQ$5<=$S12)*$D12 -> 0 | FR12: =AND(FR$5>=$R12,FR$5<=$S12)*$D12 -> 0 | FS12: =AND(FS$5>=$R12,FS$5<=$S12)*$D12 -> 0 | FT12: =AND(FT$5>=$R12,FT$5<=$S12)*$D12 -> 0 | FU12: =AND(FU$5>=$R12,FU$5<=$S12)*$D12 -> 0 | ... KO12: =AND(KO$5>=$R12,KO$5<=$S12)*$D12 -> 15864 | KR12: =IF(AND(J12>1,$E12=1),G12/12,G12/12/(1+$I12)) -> 0.86166667 | KS12: =(AJ12>0)*(MAX($KR12:KR12)+(MONTH(KS$3)=$J12)*MAX($KR12:KR12)*$I12) -> 0.86166667 | KT12: =(AK12>0)*(MAX($KR12:KS12)+(MONTH(KT$3)=$J12)*MAX($KR12:KS12)*$I12) -> 0.86166667 | KU12: =(AL12>0)*(MAX($KR12:KT12)+(MONTH(KU$3)=$J12)*MAX($KR12:KT12)*$I12) -> 0.86166667 | KV12: =(AM12>0)*(MAX($KR12:KU12)+(MONTH(KV$3)=$J12)*MAX($KR12:KU12)*$I12) -> 0.86166667 | KW12: =(AN12>0)*(MAX($KR12:KV12)+(MONTH(KW$3)=$J12)*MAX($KR12:KV12)*$I12) -> 0.86166667 | KX12: =(AO12>0)*(MAX($KR12:KW12)+(MONTH(KX$3)=$J12)*MAX($KR12:KW12)*$I12) -> 0.86166667 | KY12: =(AP12>0)*(MAX($KR12:KX12)+(MONTH(KY$3)=$J12)*MAX($KR12:KX12)*$I12) -> 0.86166667 | KZ12: =(AQ12>0)*(MAX($KR12:KY12)+(MONTH(KZ$3)=$J12)*MAX($KR12:KY12)*$I12) -> 0.86166667 | ... PT12: =(FK12>0)*(MAX($KR12:PS12)+(MONTH(PT$3)=$J12)*MAX($KR12:PS12)*$I12) -> 0 | PW12: =T12/12/(1+U12) -> 1.25715 | PX12: =(FN12>0)*(MAX($PW12:PW12)+(MONTH(PX$3)=$V12)*MAX($PW12:PW12)*$U12) -> 0 | PY12: =(FO12>0)*(MAX($PW12:PX12)+(MONTH(PY$3)=$V12)*MAX($PW12:PX12)*$U12) -> 0 | PZ12: =(FP12>0)*(MAX($PW12:PY12)+(MONTH(PZ$3)=$V12)*MAX($PW12:PY12)*$U12) -> 0 | QA12: =(FQ12>0)*(MAX($PW12:PZ12)+(MONTH(QA$3)=$V12)*MAX($PW12:PZ12)*$U12) -> 0 | QB12: =(FR12>0)*(MAX($PW12:QA12)+(MONTH(QB$3)=$V12)*MAX($PW12:QA12)*$U12) -> 0 | QC12: =(FS12>0)*(MAX($PW12:QB12)+(MONTH(QC$3)=$V12)*MAX($PW12:QB12)*$U12) -> 0 | QD12: =(FT12>0)*(MAX($PW12:QC12)+(MONTH(QD$3)=$V12)*MAX($PW12:QC12)*$U12) -> 0 | QE12: =(FU12>0)*(MAX($PW12:QD12)+(MONTH(QE$3)=$V12)*MAX($PW12:QD12)*$U12) -> 0 | ... UY12: =(KO12>0)*(MAX($PW12:UX12)+(MONTH(UY$3)=$V12)*MAX($PW12:UX12)*$U12) -> 1.4729516 | VB12: =AJ12*KS12+FN12*PX12 -> 13669.48 | VC12: =AK12*KT12+FO12*PY12 -> 13669.48 | VD12: =AL12*KU12+FP12*PZ12 -> 13669.48 | VE12: =AM12*KV12+FQ12*QA12 -> 13669.48 | VF12: =AN12*KW12+FR12*QB12 -> 13669.48 | VG12: =AO12*KX12+FS12*QC12 -> 13669.48 | VH12: =AP12*KY12+FT12*QD12 -> 13669.48 | VI12: =AQ12*KZ12+FU12*QE12 -> 13669.48 | ... AAC12: =FK12*PT12+KO12*UY12 -> 23366.904 | AAF12: =(AAF$5=$R12)*$AA12*$D12 -> 0 | AAG12: =(AAG$5=$R12)*$AA12*$D12 -> 0 | AAH12: =(AAH$5=$R12)*$AA12*$D12 -> 0 | AAI12: =(AAI$5=$R12)*$AA12*$D12 -> 0 | AAJ12: =(AAJ$5=$R12)*$AA12*$D12 -> 0 | AAK12: =(AAK$5=$R12)*$AA12*$D12 -> 0 | AAL12: =(AAL$5=$R12)*$AA12*$D12 -> 0 | AAM12: =(AAM$5=$R12)*$AA12*$D12 -> 0 | ... AFG12: =(AFG$5=$R12)*$AA12*$D12 -> 0 | AFJ12: =(AJ12>0)*'Long-Term Leases'!K$17*$L12*$K12 -> 7416.7414 | AFK12: =(AK12>0)*'Long-Term Leases'!L$17*$L12*$K12 -> 7416.7414 | AFL12: =(AL12>0)*'Long-Term Leases'!M$17*$L12*$K12 -> 7416.7414 | AFM12: =(AM12>0)*'Long-Term Leases'!N$17*$L12*$K12 -> 7416.7414 | AFN12: =(AN12>0)*'Long-Term Leases'!O$17*$L12*$K12 -> 7416.7414 | AFO12: =(AO12>0)*'Long-Term Leases'!P$17*$L12*$K12 -> 7416.7414 | AFP12: =(AP12>0)*'Long-Term Leases'!Q$17*$L12*$K12 -> 7416.7414 | AFQ12: =(AQ12>0)*'Long-Term Leases'!R$17*$L12*$K12 -> 7416.7414 | ... AKK12: =(FK12>0)*'Long-Term Leases'!EL$17*$L12*$K12 -> 0 | AKN12: =(FN12>0)*'Long-Term Leases'!K$17*$X12*$W12 -> 0 | AKO12: =(FO12>0)*'Long-Term Leases'!L$17*$X12*$W12 -> 0 | AKP12: =(FP12>0)*'Long-Term Leases'!M$17*$X12*$W12 -> 0 | AKQ12: =(FQ12>0)*'Long-Term Leases'!N$17*$X12*$W12 -> 0 | AKR12: =(FR12>0)*'Long-Term Leases'!O$17*$X12*$W12 -> 0 | AKS12: =(FS12>0)*'Long-Term Leases'!P$17*$X12*$W12 -> 0 | AKT12: =(FT12>0)*'Long-Term Leases'!Q$17*$X12*$W12 -> 0 | AKU12: =(FU12>0)*'Long-Term Leases'!R$17*$X12*$W12 -> 0 | ... APO12: =(KO12>0)*'Long-Term Leases'!EL$17*$X12*$W12 -> 9040.9664 | APR12: =(APR$5=$R12)*$AH12*$D12 -> 0 | APS12: =(APS$5=$R12)*$AH12*$D12 -> 0 | APT12: =(APT$5=$R12)*$AH12*$D12 -> 0 | APU12: =(APU$5=$R12)*$AH12*$D12 -> 0 | APV12: =(APV$5=$R12)*$AH12*$D12 -> 0 | APW12: =(APW$5=$R12)*$AH12*$D12 -> 0 | APX12: =(APX$5=$R12)*$AH12*$D12 -> 0 | APY12: =(APY$5=$R12)*$AH12*$D12 -> 0 | ... AUS12: =(AUS$5=$R12)*$AH12*$D12 -> 0
B13: 700 | C13: Playroom Kidz | D13: 13899 | E13: 1 | F13: 84 | G13: 12.5 | H13: =+G13*D13 -> 173737.5 | I13: =$I$6 -> 0.02 | J13: 1 | K13: 1 | L13: =D13/$D$6 -> 0.10161945 | M13: 14.5 | N13: 0.02 | O13: 0.8 | P13: 12 | Q13: 120 | R13: =ROUNDUP((1-O13)*P13,0)+F13+1 -> 88 | S13: =+R13+Q13-1 -> 207 | T13: =M13*(1+N13)^(ROUNDUP(R13/12,0)-1) -> 16.655942 | U13: =$U$6 -> 0.02 | V13: =12-(ROUNDUP(R13/12,0)*12-R13) -> 4 | W13: =+K13 -> 1 | X13: =+L13 -> 0.10161945 | Y13: 9 | Z13: 3 | AA13: =ROUNDUP(O13*Z13+(1-O13)*Y13,0)*T13/12 -> 6.9399759 | AB13: 25 | AC13: 10 | AD13: 0.06 | AE13: 0.03 | AF13: =AC13*O13+AB13*(1-O13) -> 13 | AG13: =(AE13*O13+AD13*(1-O13))*T13*Q13/12 -> 5.9961392 | AH13: =SUM(AF13:AG13) -> 18.996139 | AJ13: =AND(AJ$5>=$E13,AJ$5<=$F13)*$D13 -> 13899 | AK13: =AND(AK$5>=$E13,AK$5<=$F13)*$D13 -> 13899 | AL13: =AND(AL$5>=$E13,AL$5<=$F13)*$D13 -> 13899 | AM13: =AND(AM$5>=$E13,AM$5<=$F13)*$D13 -> 13899 | AN13: =AND(AN$5>=$E13,AN$5<=$F13)*$D13 -> 13899 | AO13: =AND(AO$5>=$E13,AO$5<=$F13)*$D13 -> 13899 | AP13: =AND(AP$5>=$E13,AP$5<=$F13)*$D13 -> 13899 | AQ13: =AND(AQ$5>=$E13,AQ$5<=$F13)*$D13 -> 13899 | ... FK13: =AND(FK$5>=$E13,FK$5<=$F13)*$D13 -> 0 | FN13: =AND(FN$5>=$R13,FN$5<=$S13)*$D13 -> 0 | FO13: =AND(FO$5>=$R13,FO$5<=$S13)*$D13 -> 0 | FP13: =AND(FP$5>=$R13,FP$5<=$S13)*$D13 -> 0 | FQ13: =AND(FQ$5>=$R13,FQ$5<=$S13)*$D13 -> 0 | FR13: =AND(FR$5>=$R13,FR$5<=$S13)*$D13 -> 0 | FS13: =AND(FS$5>=$R13,FS$5<=$S13)*$D13 -> 0 | FT13: =AND(FT$5>=$R13,FT$5<=$S13)*$D13 -> 0 | FU13: =AND(FU$5>=$R13,FU$5<=$S13)*$D13 -> 0 | ... KO13: =AND(KO$5>=$R13,KO$5<=$S13)*$D13 -> 13899 | KR13: =IF(AND(J13>1,$E13=1),G13/12,G13/12/(1+$I13)) -> 1.0212418 | KS13: =(AJ13>0)*(MAX($KR13:KR13)+(MONTH(KS$3)=$J13)*MAX($KR13:KR13)*$I13) -> 1.0416667 | KT13: =(AK13>0)*(MAX($KR13:KS13)+(MONTH(KT$3)=$J13)*MAX($KR13:KS13)*$I13) -> 1.0416667 | KU13: =(AL13>0)*(MAX($KR13:KT13)+(MONTH(KU$3)=$J13)*MAX($KR13:KT13)*$I13) -> 1.0416667 | KV13: =(AM13>0)*(MAX($KR13:KU13)+(MONTH(KV$3)=$J13)*MAX($KR13:KU13)*$I13) -> 1.0416667 | KW13: =(AN13>0)*(MAX($KR13:KV13)+(MONTH(KW$3)=$J13)*MAX($KR13:KV13)*$I13) -> 1.0416667 | KX13: =(AO13>0)*(MAX($KR13:KW13)+(MONTH(KX$3)=$J13)*MAX($KR13:KW13)*$I13) -> 1.0416667 | KY13: =(AP13>0)*(MAX($KR13:KX13)+(MONTH(KY$3)=$J13)*MAX($KR13:KX13)*$I13) -> 1.0416667 | KZ13: =(AQ13>0)*(MAX($KR13:KY13)+(MONTH(KZ$3)=$J13)*MAX($KR13:KY13)*$I13) -> 1.0416667 | ... PT13: =(FK13>0)*(MAX($KR13:PS13)+(MONTH(PT$3)=$J13)*MAX($KR13:PS13)*$I13) -> 0 | PW13: =T13/12/(1+U13) -> 1.3607796 | PX13: =(FN13>0)*(MAX($PW13:PW13)+(MONTH(PX$3)=$V13)*MAX($PW13:PW13)*$U13) -> 0 | PY13: =(FO13>0)*(MAX($PW13:PX13)+(MONTH(PY$3)=$V13)*MAX($PW13:PX13)*$U13) -> 0 | PZ13: =(FP13>0)*(MAX($PW13:PY13)+(MONTH(PZ$3)=$V13)*MAX($PW13:PY13)*$U13) -> 0 | QA13: =(FQ13>0)*(MAX($PW13:PZ13)+(MONTH(QA$3)=$V13)*MAX($PW13:PZ13)*$U13) -> 0 | QB13: =(FR13>0)*(MAX($PW13:QA13)+(MONTH(QB$3)=$V13)*MAX($PW13:QA13)*$U13) -> 0 | QC13: =(FS13>0)*(MAX($PW13:QB13)+(MONTH(QC$3)=$V13)*MAX($PW13:QB13)*$U13) -> 0 | QD13: =(FT13>0)*(MAX($PW13:QC13)+(MONTH(QD$3)=$V13)*MAX($PW13:QC13)*$U13) -> 0 | QE13: =(FU13>0)*(MAX($PW13:QD13)+(MONTH(QE$3)=$V13)*MAX($PW13:QD13)*$U13) -> 0 | ... UY13: =(KO13>0)*(MAX($PW13:UX13)+(MONTH(UY$3)=$V13)*MAX($PW13:UX13)*$U13) -> 1.4729516 | VB13: =AJ13*KS13+FN13*PX13 -> 14478.125 | VC13: =AK13*KT13+FO13*PY13 -> 14478.125 | VD13: =AL13*KU13+FP13*PZ13 -> 14478.125 | VE13: =AM13*KV13+FQ13*QA13 -> 14478.125 | VF13: =AN13*KW13+FR13*QB13 -> 14478.125 | VG13: =AO13*KX13+FS13*QC13 -> 14478.125 | VH13: =AP13*KY13+FT13*QD13 -> 14478.125 | VI13: =AQ13*KZ13+FU13*QE13 -> 14478.125 | ... AAC13: =FK13*PT13+KO13*UY13 -> 20472.554 | AAF13: =(AAF$5=$R13)*$AA13*$D13 -> 0 | AAG13: =(AAG$5=$R13)*$AA13*$D13 -> 0 | AAH13: =(AAH$5=$R13)*$AA13*$D13 -> 0 | AAI13: =(AAI$5=$R13)*$AA13*$D13 -> 0 | AAJ13: =(AAJ$5=$R13)*$AA13*$D13 -> 0 | AAK13: =(AAK$5=$R13)*$AA13*$D13 -> 0 | AAL13: =(AAL$5=$R13)*$AA13*$D13 -> 0 | AAM13: =(AAM$5=$R13)*$AA13*$D13 -> 0 | ... AFG13: =(AFG$5=$R13)*$AA13*$D13 -> 0 | AFJ13: =(AJ13>0)*'Long-Term Leases'!K$17*$L13*$K13 -> 6498.0641 | AFK13: =(AK13>0)*'Long-Term Leases'!L$17*$L13*$K13 -> 6498.0641 | AFL13: =(AL13>0)*'Long-Term Leases'!M$17*$L13*$K13 -> 6498.0641 | AFM13: =(AM13>0)*'Long-Term Leases'!N$17*$L13*$K13 -> 6498.0641 | AFN13: =(AN13>0)*'Long-Term Leases'!O$17*$L13*$K13 -> 6498.0641 | AFO13: =(AO13>0)*'Long-Term Leases'!P$17*$L13*$K13 -> 6498.0641 | AFP13: =(AP13>0)*'Long-Term Leases'!Q$17*$L13*$K13 -> 6498.0641 | AFQ13: =(AQ13>0)*'Long-Term Leases'!R$17*$L13*$K13 -> 6498.0641 | ... AKK13: =(FK13>0)*'Long-Term Leases'!EL$17*$L13*$K13 -> 0 | AKN13: =(FN13>0)*'Long-Term Leases'!K$17*$X13*$W13 -> 0 | AKO13: =(FO13>0)*'Long-Term Leases'!L$17*$X13*$W13 -> 0 | AKP13: =(FP13>0)*'Long-Term Leases'!M$17*$X13*$W13 -> 0 | AKQ13: =(FQ13>0)*'Long-Term Leases'!N$17*$X13*$W13 -> 0 | AKR13: =(FR13>0)*'Long-Term Leases'!O$17*$X13*$W13 -> 0 | AKS13: =(FS13>0)*'Long-Term Leases'!P$17*$X13*$W13 -> 0 | AKT13: =(FT13>0)*'Long-Term Leases'!Q$17*$X13*$W13 -> 0 | AKU13: =(FU13>0)*'Long-Term Leases'!R$17*$X13*$W13 -> 0 | ... APO13: =(KO13>0)*'Long-Term Leases'!EL$17*$X13*$W13 -> 7921.1038 | APR13: =(APR$5=$R13)*$AH13*$D13 -> 0 | APS13: =(APS$5=$R13)*$AH13*$D13 -> 0 | APT13: =(APT$5=$R13)*$AH13*$D13 -> 0 | APU13: =(APU$5=$R13)*$AH13*$D13 -> 0 | APV13: =(APV$5=$R13)*$AH13*$D13 -> 0 | APW13: =(APW$5=$R13)*$AH13*$D13 -> 0 | APX13: =(APX$5=$R13)*$AH13*$D13 -> 0 | APY13: =(APY$5=$R13)*$AH13*$D13 -> 0 | ... AUS13: =(AUS$5=$R13)*$AH13*$D13 -> 0
